[{"id":29017317,"language_id":0,"language_iso":"en","urlhtml":"<a class=\"wikimapia-link\" href=\"http://wikimapia.org/29017317/Rue-Sainte-Foy-8\">Rue Sainte-Foy, 8</a>","title":null,"tags":[{"id":109,"title":"building"}],"wikipedia":null,"is_building":true,"is_region":false,"is_deleted":false,"parent_id":"0","polygon":[{"x":2.3506484,"y":48.8685646},{"x":2.3507036,"y":48.8685117},{"x":2.350608,"y":48.8684863},{"x":2.3505976,"y":48.8684762},{"x":2.3505782,"y":48.8684679},{"x":2.3505846,"y":48.8684575},{"x":2.3506409,"y":48.8684448},{"x":2.3506193,"y":48.868402},{"x":2.3505788,"y":48.8684174},{"x":2.3504838,"y":48.8684583},{"x":2.3504439,"y":48.8684913},{"x":2.3504247,"y":48.8685037},{"x":2.3505655,"y":48.8685427}],"location":{"lon":2.3505641,"lat":48.8684833,"north":48.8685646,"south":48.868402,"east":2.3507036,"west":2.3504247,"country":"France","state":"Ile-de-France","place":"Paris","country_adm_id":0,"gadm":null,"city_id":"5009811","city":"Paris","zoom":19},"description":null},{"id":29017938,"language_id":0,"language_iso":"en","urlhtml":"<a class=\"wikimapia-link\" href=\"http://wikimapia.org/29017938/Rue-Sainte-Apolline-1-3\">Rue Sainte-Apolline, 1, 3</a>","title":null,"tags":[{"id":109,"title":"building"}],"wikipedia":null,"is_building":true,"is_region":false,"is_deleted":false,"parent_id":"0","polygon":[{"x":2.3548896,"y":48.8687246},{"x":2.3552677,"y":48.8686497},{"x":2.3552504,"y":48.8686173},{"x":2.3552101,"y":48.8686255},{"x":2.3551791,"y":48.868566},{"x":2.3551338,"y":48.8685733},{"x":2.355142,"y":48.8685913},{"x":2.3551312,"y":48.8685952},{"x":2.3551202,"y":48.8685773},{"x":2.355092,"y":48.868587},{"x":2.3551173,"y":48.8686339},{"x":2.3550987,"y":48.8686383},{"x":2.3550992,"y":48.8686438},{"x":2.3550539,"y":48.8686518},{"x":2.3549783,"y":48.8686713},{"x":2.3549727,"y":48.8686687},{"x":2.354871,"y":48.868688}],"location":{"lon":2.3550693,"lat":48.8686453,"north":48.8687246,"south":48.868566,"east":2.3552677,"west":2.354871,"country":"France","state":"Ile-de-France","place":"Paris","country_adm_id":0,"gadm":null,"city_id":"5009811","city":"Paris","zoom":19},"description":null},{"id":29018467,"language_id":2,"language_iso":"fr","urlhtml":"<a class=\"wikimapia-link\" href=\"http://wikimapia.org/29018467/fr/Rue-Lucien-Sampaix-2\">Rue Lucien Sampaix, 2</a>","title":null,"tags":[{"id":17,"title":"magasin"}],"wikipedia":null,"is_building":true,"is_region":false,"is_deleted":false,"parent_id":"0","polygon":[{"x":2.3597822,"y":48.8707452},{"x":2.3596668,"y":48.8706137},{"x":2.3595986,"y":48.8705449},{"x":2.3596106,"y":48.8705168},{"x":2.359656,"y":48.8704931},{"x":2.3597046,"y":48.8705383},{"x":2.359751,"y":48.8706024},{"x":2.3597284,"y":48.8706109},{"x":2.3597588,"y":48.8706433},{"x":2.3597799,"y":48.8706338},{"x":2.3598006,"y":48.8706595},{"x":2.3598257,"y":48.8706897},{"x":2.3598463,"y":48.870716}],"location":{"lon":2.3597224,"lat":48.8706191,"north":48.8707452,"south":48.8704931,"east":2.3598463,"west":2.3595986,"country":"France","state":"Ile-de-France","place":"Paris","country_adm_id":0,"gadm":null,"city_id":"5009811","city":"Paris","zoom":19},"description":null},{"id":29020096,"language_id":2,"language_iso":"fr","urlhtml":"<a class=\"wikimapia-link\" href=\"http://wikimapia.org/29020096/fr/Avenue-de-la-R%C3%A9publique-22\">Avenue de la République, 22</a>","title":null,"tags":[{"id":108,"title":"café, bar, brasserie"}],"wikipedia":null,"is_building":true,"is_region":false,"is_deleted":false,"parent_id":"0","polygon":[{"x":2.3686506,"y":48.866226},{"x":2.3686125,"y":48.8661355},{"x":2.3686046,"y":48.866116},{"x":2.368621,"y":48.8660832},{"x":2.3687128,"y":48.8661097},{"x":2.3688512,"y":48.8661482},{"x":2.3688243,"y":48.8661785},{"x":2.3688111,"y":48.8661943},{"x":2.3687293,"y":48.8662107}],"location":{"lon":2.3687279,"lat":48.8661546,"north":48.866226,"south":48.8660832,"east":2.3688512,"west":2.3686046,"country":"France","state":"Ile-de-France","place":"Paris","country_adm_id":0,"gadm":null,"city_id":"5009811","city":"Paris","zoom":20},"description":null},{"id":29020164,"language_id":0,"language_iso":"en","urlhtml":"<a class=\"wikimapia-link\" href=\"http://wikimapia.org/29020164/Rue-du-Temple-205\">Rue du Temple, 205</a>","title":null,"tags":[{"id":217,"title":"bank"}],"wikipedia":null,"is_building":true,"is_region":false,"is_deleted":false,"parent_id":"0","polygon":[{"x":2.3623207,"y":48.8672399},{"x":2.3623912,"y":48.8672285},{"x":2.3624813,"y":48.8672115},{"x":2.3624846,"y":48.8671844},{"x":2.3624889,"y":48.8671656},{"x":2.3623871,"y":48.8671252},{"x":2.3622845,"y":48.8670848},{"x":2.3622583,"y":48.86712},{"x":2.362283,"y":48.8671637},{"x":2.362286,"y":48.8671613},{"x":2.3622887,"y":48.8671546},{"x":2.3623238,"y":48.867166},{"x":2.36232,"y":48.8671735},{"x":2.3622896,"y":48.8671777}],"location":{"lon":2.3623736,"lat":48.8671623,"north":48.8672399,"south":48.8670848,"east":2.3624889,"west":2.3622583,"country":"France","state":"Ile-de-France","place":"Paris","country_adm_id":0,"gadm":null,"city_id":"5009811","city":"Paris","zoom":20},"description":null},{"id":29021536,"language_id":2,"language_iso":"fr","urlhtml":"<a class=\"wikimapia-link\" href=\"http://wikimapia.org/29021536/fr/Rue-de-la-Folie-M%C3%A9ricourt-92\">Rue de la Folie-Méricourt, 92</a>","title":null,"tags":null,"wikipedia":null,"is_building":true,"is_region":false,"is_deleted":false,"parent_id":"0","polygon":[{"x":2.369498,"y":48.8669502},{"x":2.3695906,"y":48.8669766},{"x":2.3695679,"y":48.8670073},{"x":2.3695346,"y":48.8669974},{"x":2.369526,"y":48.867005},{"x":2.3696201,"y":48.8670376},{"x":2.3696132,"y":48.8670476},{"x":2.3696413,"y":48.8670541},{"x":2.3696148,"y":48.8670943},{"x":2.3695752,"y":48.8670817},{"x":2.3695576,"y":48.8670984},{"x":2.3695214,"y":48.8670871},{"x":2.3695356,"y":48.8670681},{"x":2.369487,"y":48.8670551},{"x":2.3694742,"y":48.8670705},{"x":2.369414,"y":48.8670524},{"x":2.3693882,"y":48.8670427},{"x":2.3694315,"y":48.8669945},{"x":2.3694729,"y":48.8669433}],"location":{"lon":2.3695147,"lat":48.8670208,"north":48.8670984,"south":48.8669433,"east":2.3696413,"west":2.3693882,"country":"France","state":"Ile-de-France","place":"Paris","country_adm_id":0,"gadm":null,"city_id":"5009811","city":"Paris","zoom":19},"description":null},{"id":29027141,"language_id":2,"language_iso":"fr","urlhtml":"<a class=\"wikimapia-link\" href=\"http://wikimapia.org/29027141/fr/Rue-du-Ch%C3%A2teau-d-Eau-78\">Rue du Château d'Eau, 78</a>","title":null,"tags":null,"wikipedia":null,"is_building":true,"is_region":false,"is_deleted":false,"parent_id":"0","polygon":[{"x":2.35479,"y":48.8728499},{"x":2.354575,"y":48.8729355},{"x":2.3545573,"y":48.8729106},{"x":2.3545469,"y":48.8728931},{"x":2.354559,"y":48.8728669},{"x":2.3546883,"y":48.8728169},{"x":2.3548103,"y":48.8727672},{"x":2.3548606,"y":48.8728226},{"x":2.3548092,"y":48.8728435},{"x":2.354793,"y":48.8728287},{"x":2.3547617,"y":48.8728414},{"x":2.3547713,"y":48.8728485},{"x":2.3547849,"y":48.8728465}],"location":{"lon":2.3547037,"lat":48.8728513,"north":48.8729355,"south":48.8727672,"east":2.3548606,"west":2.3545469,"country":"France","state":"Ile-de-France","place":"Paris","country_adm_id":0,"gadm":null,"city_id":"5009811","city":"Paris","zoom":19},"description":null},{"id":29027335,"language_id":2,"language_iso":"fr","urlhtml":"<a class=\"wikimapia-link\" href=\"http://wikimapia.org/29027335/fr/Rue-d-Enghien-43\">Rue d'Enghien, 43</a>","title":null,"tags":null,"wikipedia":null,"is_building":true,"is_region":false,"is_deleted":false,"parent_id":"0","polygon":[{"x":2.348758,"y":48.8722806},{"x":2.3486914,"y":48.8721268},{"x":2.3487493,"y":48.8721144},{"x":2.3487738,"y":48.8721697},{"x":2.3488656,"y":48.8721523},{"x":2.3489118,"y":48.8722556},{"x":2.3488326,"y":48.8722674}],"location":{"lon":2.3488016,"lat":48.8721975,"north":48.8722806,"south":48.8721144,"east":2.3489118,"west":2.3486914,"country":"France","state":"Ile-de-France","place":"Paris","country_adm_id":0,"gadm":null,"city_id":"5009811","city":"Paris","zoom":20},"description":null},{"id":29029247,"language_id":2,"language_iso":"fr","urlhtml":"<a class=\"wikimapia-link\" href=\"http://wikimapia.org/29029247/fr/Rue-de-Marseille-12\">Rue de Marseille, 12</a>","title":null,"tags":null,"wikipedia":null,"is_building":true,"is_region":false,"is_deleted":false,"parent_id":"0","polygon":[{"x":2.3637271,"y":48.8715524},{"x":2.3638517,"y":48.8713962},{"x":2.3639075,"y":48.8714346},{"x":2.3638659,"y":48.8714897},{"x":2.3639261,"y":48.8715077},{"x":2.3638572,"y":48.8715986}],"location":{"lon":2.3638266,"lat":48.8714974,"north":48.8715986,"south":48.8713962,"east":2.3639261,"west":2.3637271,"country":"France","state":"Ile-de-France","place":"Paris","country_adm_id":0,"gadm":null,"city_id":"5009811","city":"Paris","zoom":20},"description":null},{"id":29550416,"language_id":0,"language_iso":"en","urlhtml":"<a class=\"wikimapia-link\" href=\"http://wikimapia.org/29550416/Hotel\">Hotel</a>","title":"Hotel","tags":[{"id":50,"title":"hotel"}],"wikipedia":null,"is_building":false,"is_region":false,"is_deleted":false,"parent_id":"0","polygon":[{"x":2.360439,"y":48.8707069},{"x":2.3603109,"y":48.8705766},{"x":2.360197,"y":48.8706277},{"x":2.3603223,"y":48.8707464}],"location":{"lon":2.360318,"lat":48.8706615,"north":48.8707464,"south":48.8705766,"east":2.360439,"west":2.360197,"country":"France","state":"Ile-de-France","place":"Paris","country_adm_id":0,"gadm":null,"city_id":"5009811","city":"Paris","zoom":19},"description":null},{"id":10604578,"language_id":0,"language_iso":"en","urlhtml":"<a class=\"wikimapia-link\" href=\"http://wikimapia.org/10604578/Librairie-Franco-Allemande\">Librairie Franco-Allemande</a>","title":"Librairie Franco-Allemande","tags":[{"id":17,"title":"store / shop"},{"id":3392,"title":"bookstore"}],"wikipedia":null,"is_building":false,"is_region":false,"is_deleted":false,"parent_id":"0","polygon":[{"x":2.3531462,"y":48.8614721},{"x":2.3530939,"y":48.8613685},{"x":2.3529236,"y":48.8614033},{"x":2.3529779,"y":48.8615087}],"location":{"lon":2.3530349,"lat":48.8614386,"north":48.8615087,"south":48.8613685,"east":2.3531462,"west":2.3529236,"country":"France","state":"Ile-de-France","place":"Paris","country_adm_id":0,"gadm":null,"city_id":"5009811","city":"Paris","zoom":20},"description":" "},{"id":28976043,"language_id":2,"language_iso":"fr","urlhtml":"<a class=\"wikimapia-link\" href=\"http://wikimapia.org/28976043/fr/Rue-Jean-Beausire-15\">Rue Jean Beausire, 15</a>","title":null,"tags":null,"wikipedia":null,"is_building":true,"is_region":false,"is_deleted":false,"parent_id":"0","polygon":[{"x":2.3680642,"y":48.8546691},{"x":2.3680652,"y":48.8545928},{"x":2.368068,"y":48.8545596},{"x":2.3680513,"y":48.8545601},{"x":2.3679079,"y":48.8545603},{"x":2.3678873,"y":48.8545613},{"x":2.3678829,"y":48.8546704}],"location":{"lon":2.3679754,"lat":48.854615,"north":48.8546704,"south":48.8545596,"east":2.368068,"west":2.3678829,"country":"France","state":"Ile-de-France","place":"Paris","country_adm_id":0,"gadm":null,"city_id":"5009811","city":"Paris","zoom":20},"description":null},{"id":28988068,"language_id":2,"language_iso":"fr","urlhtml":"<a class=\"wikimapia-link\" href=\"http://wikimapia.org/28988068/Pont-Neuf-27\">Pont Neuf, 27</a>","title":null,"tags":null,"wikipedia":null,"is_building":true,"is_region":false,"is_deleted":false,"parent_id":"0","polygon":[{"x":2.3445543,"y":48.8608435},{"x":2.3445308,"y":48.8608129},{"x":2.3444949,"y":48.8607651},{"x":2.3444471,"y":48.8607055},{"x":2.3443827,"y":48.8607318},{"x":2.3443544,"y":48.8607431},{"x":2.3443658,"y":48.8607879},{"x":2.3443934,"y":48.8608617},{"x":2.3444562,"y":48.8608669},{"x":2.3445208,"y":48.8608557}],"location":{"lon":2.3444543,"lat":48.8607862,"north":48.8608669,"south":48.8607055,"east":2.3445543,"west":2.3443544,"country":"France","state":"Ile-de-France","place":"Paris","country_adm_id":0,"gadm":null,"city_id":"5009811","city":"Paris","zoom":20},"description":null},{"id":28988824,"language_id":0,"language_iso":"en","urlhtml":"<a class=\"wikimapia-link\" href=\"http://wikimapia.org/28988824/Rue-Saint-Denis-56-58\">Rue Saint-Denis, 56, 58</a>","title":null,"tags":[{"id":17,"title":"store / shop"},{"id":109,"title":"building"}],"wikipedia":null,"is_building":true,"is_region":false,"is_deleted":false,"parent_id":"0","polygon":[{"x":2.3489834,"y":48.8612154},{"x":2.3491131,"y":48.8611854},{"x":2.349094,"y":48.8611481},{"x":2.3490746,"y":48.861153},{"x":2.3490437,"y":48.8610987},{"x":2.3490699,"y":48.8610928},{"x":2.3490437,"y":48.8610445},{"x":2.3489073,"y":48.8610762}],"location":{"lon":2.3490102,"lat":48.8611299,"north":48.8612154,"south":48.8610445,"east":2.3491131,"west":2.3489073,"country":"France","state":"Ile-de-France","place":"Paris","country_adm_id":0,"gadm":null,"city_id":"5009811","city":"Paris","zoom":20},"description":null},{"id":28989245,"language_id":2,"language_iso":"fr","urlhtml":"<a class=\"wikimapia-link\" href=\"http://wikimapia.org/28989245/fr/Rue-Jean-Lantier-7\">Rue Jean Lantier, 7</a>","title":null,"tags":null,"wikipedia":null,"is_building":true,"is_region":false,"is_deleted":false,"parent_id":"0","polygon":[{"x":2.3464084,"y":48.8584478},{"x":2.3464908,"y":48.8584256},{"x":2.3465851,"y":48.8584007},{"x":2.3465242,"y":48.8583026},{"x":2.3463926,"y":48.8583396},{"x":2.3463505,"y":48.8583506}],"location":{"lon":2.3464678,"lat":48.8583752,"north":48.8584478,"south":48.8583026,"east":2.3465851,"west":2.3463505,"country":"France","state":"Ile-de-France","place":"Paris","country_adm_id":0,"gadm":null,"city_id":"5009811","city":"Paris","zoom":19},"description":null},{"id":28989370,"language_id":0,"language_iso":"en","urlhtml":"<a class=\"wikimapia-link\" href=\"http://wikimapia.org/28989370/Rue-Sainte-Opportune-5\">Rue Sainte-Opportune, 5</a>","title":null,"tags":[{"id":109,"title":"building"}],"wikipedia":null,"is_building":true,"is_region":false,"is_deleted":false,"parent_id":"0","polygon":[{"x":2.3470912,"y":48.8602191},{"x":2.3471415,"y":48.860214},{"x":2.3471916,"y":48.8602142},{"x":2.3471906,"y":48.8602065},{"x":2.3472149,"y":48.8602035},{"x":2.3472523,"y":48.8601996},{"x":2.3472362,"y":48.8601358},{"x":2.3472185,"y":48.8600768},{"x":2.3471523,"y":48.8600798},{"x":2.3471664,"y":48.8601205},{"x":2.347088,"y":48.86013},{"x":2.3470759,"y":48.8600806},{"x":2.3470389,"y":48.860082},{"x":2.3470456,"y":48.860117}],"location":{"lon":2.3471456,"lat":48.8601479,"north":48.8602191,"south":48.8600768,"east":2.3472523,"west":2.3470389,"country":"France","state":"Ile-de-France","place":"Paris","country_adm_id":0,"gadm":null,"city_id":"5009811","city":"Paris","zoom":20},"description":null},{"id":28989885,"language_id":2,"language_iso":"fr","urlhtml":"<a class=\"wikimapia-link\" href=\"http://wikimapia.org/28989885/fr/rue-du-Saint-Martin-69\">rue du Saint-Martin, 69</a>","title":null,"tags":null,"wikipedia":null,"is_building":true,"is_region":false,"is_deleted":false,"parent_id":"0","polygon":[{"x":2.3503901,"y":48.8593508},{"x":2.3503761,"y":48.8593265},{"x":2.3503569,"y":48.859295},{"x":2.3501194,"y":48.8593519},{"x":2.3500755,"y":48.8593686},{"x":2.3501004,"y":48.8594077},{"x":2.3501062,"y":48.8594079},{"x":2.3501194,"y":48.8594251},{"x":2.3501226,"y":48.8594302},{"x":2.3501447,"y":48.8594236},{"x":2.3501444,"y":48.859421}],"location":{"lon":2.3502328,"lat":48.8593626,"north":48.8594302,"south":48.859295,"east":2.3503901,"west":2.3500755,"country":"France","state":"Ile-de-France","place":"Paris","country_adm_id":0,"gadm":null,"city_id":"5009811","city":"Paris","zoom":20},"description":null},{"id":28989919,"language_id":2,"language_iso":"fr","urlhtml":"<a class=\"wikimapia-link\" href=\"http://wikimapia.org/28989919/fr/Rue-de-la-Reynie-15\">Rue de la Reynie, 15</a>","title":null,"tags":null,"wikipedia":null,"is_building":true,"is_region":false,"is_deleted":false,"parent_id":"0","polygon":[{"x":2.3494517,"y":48.8599305},{"x":2.3495384,"y":48.8599186},{"x":2.3496084,"y":48.8599127},{"x":2.3495831,"y":48.8598459},{"x":2.3495423,"y":48.8597829},{"x":2.3495276,"y":48.8597871},{"x":2.3494862,"y":48.8597994},{"x":2.3494836,"y":48.859796},{"x":2.3494786,"y":48.8597984},{"x":2.3494823,"y":48.8598063},{"x":2.3494762,"y":48.8598198},{"x":2.3494452,"y":48.8598244},{"x":2.3494275,"y":48.8597827},{"x":2.3493955,"y":48.8597854}],"location":{"lon":2.3495019,"lat":48.8598566,"north":48.8599305,"south":48.8597827,"east":2.3496084,"west":2.3493955,"country":"France","state":"Ile-de-France","place":"Paris","country_adm_id":0,"gadm":null,"city_id":"5009811","city":"Paris","zoom":20},"description":null},{"id":28990249,"language_id":2,"language_iso":"fr","urlhtml":"<a class=\"wikimapia-link\" href=\"http://wikimapia.org/28990249/fr/Rue-Simon-Le-Franc-7\">Rue Simon Le Franc, 7</a>","title":null,"tags":null,"wikipedia":null,"is_building":true,"is_region":false,"is_deleted":false,"parent_id":"0","polygon":[{"x":2.3537955,"y":48.860034},{"x":2.3537177,"y":48.859952},{"x":2.3536508,"y":48.85989},{"x":2.3536344,"y":48.8598794},{"x":2.3535474,"y":48.8599138},{"x":2.3536199,"y":48.8599861},{"x":2.3536298,"y":48.8599885},{"x":2.3537012,"y":48.8600679},{"x":2.3537416,"y":48.8600505}],"location":{"lon":2.3536714,"lat":48.8599736,"north":48.8600679,"south":48.8598794,"east":2.3537955,"west":2.3535474,"country":"France","state":"Ile-de-France","place":"Paris","country_adm_id":0,"gadm":null,"city_id":"5009811","city":"Paris","zoom":19},"description":null},{"id":28991202,"language_id":2,"language_iso":"fr","urlhtml":"<a class=\"wikimapia-link\" href=\"http://wikimapia.org/28991202/fr/Rue-des-Rosiers-24\">Rue des Rosiers, 24</a>","title":null,"tags":null,"wikipedia":null,"is_building":true,"is_region":false,"is_deleted":false,"parent_id":"0","polygon":[{"x":2.3596258,"y":48.8571112},{"x":2.3595901,"y":48.8571296},{"x":2.3595712,"y":48.8571376},{"x":2.3597843,"y":48.8573096},{"x":2.3598052,"y":48.8573265},{"x":2.3598626,"y":48.8573728},{"x":2.3599079,"y":48.8573391},{"x":2.3598172,"y":48.8572657},{"x":2.3597845,"y":48.8572428}],"location":{"lon":2.3597395,"lat":48.857242,"north":48.8573728,"south":48.8571112,"east":2.3599079,"west":2.3595712,"country":"France","state":"Ile-de-France","place":"Paris","country_adm_id":0,"gadm":null,"city_id":"5009811","city":"Paris","zoom":19},"description":null},{"id":28991518,"language_id":2,"language_iso":"fr","urlhtml":"<a class=\"wikimapia-link\" href=\"http://wikimapia.org/28991518/fr/rue-Rambuteau-12\">rue Rambuteau, 12</a>","title":null,"tags":null,"wikipedia":null,"is_building":true,"is_region":false,"is_deleted":false,"parent_id":"0","polygon":[{"x":2.3560221,"y":48.8604154},{"x":2.3559586,"y":48.8604354},{"x":2.3558932,"y":48.8604574},{"x":2.3558926,"y":48.8604627},{"x":2.3560382,"y":48.8605704},{"x":2.3560786,"y":48.8605449},{"x":2.3561455,"y":48.8605044}],"location":{"lon":2.356019,"lat":48.8604929,"north":48.8605704,"south":48.8604154,"east":2.3561455,"west":2.3558926,"country":"France","state":"Ile-de-France","place":"Paris","country_adm_id":0,"gadm":null,"city_id":"5009811","city":"Paris","zoom":19},"description":null},{"id":28992102,"language_id":2,"language_iso":"fr","urlhtml":"<a class=\"wikimapia-link\" href=\"http://wikimapia.org/28992102/fr/rue-Malher-13\">rue Malher, 13</a>","title":null,"tags":null,"wikipedia":null,"is_building":true,"is_region":false,"is_deleted":false,"parent_id":"0","polygon":[{"x":2.3612688,"y":48.8563138},{"x":2.3612326,"y":48.8563046},{"x":2.3610841,"y":48.8563785},{"x":2.3611566,"y":48.8564409},{"x":2.3611729,"y":48.856439},{"x":2.3612187,"y":48.8564354},{"x":2.3612208,"y":48.8564452},{"x":2.3612309,"y":48.8564468},{"x":2.3612337,"y":48.8564569},{"x":2.3612939,"y":48.8564514},{"x":2.3612823,"y":48.856385}],"location":{"lon":2.361189,"lat":48.8563807,"north":48.8564569,"south":48.8563046,"east":2.3612939,"west":2.3610841,"country":"France","state":"Ile-de-France","place":"Paris","country_adm_id":0,"gadm":null,"city_id":"5009811","city":"Paris","zoom":20},"description":null},{"id":28992465,"language_id":2,"language_iso":"fr","urlhtml":"<a class=\"wikimapia-link\" href=\"http://wikimapia.org/28992465/fr/rue-de-S%C3%A9vign%C3%A9-30\">rue de Sévigné, 30</a>","title":null,"tags":null,"wikipedia":null,"is_building":true,"is_region":false,"is_deleted":false,"parent_id":"0","polygon":[{"x":2.3627503,"y":48.8566586},{"x":2.3627696,"y":48.8566903},{"x":2.3627985,"y":48.8567308},{"x":2.362891,"y":48.8567033},{"x":2.3629456,"y":48.8566851},{"x":2.3630195,"y":48.8566653},{"x":2.3630512,"y":48.856655},{"x":2.3630004,"y":48.8565845},{"x":2.3629547,"y":48.8565958},{"x":2.3629842,"y":48.8566407},{"x":2.3629382,"y":48.8566551},{"x":2.3629098,"y":48.8566097},{"x":2.3628571,"y":48.8566237}],"location":{"lon":2.3629007,"lat":48.8566576,"north":48.8567308,"south":48.8565845,"east":2.3630512,"west":2.3627503,"country":"France","state":"Ile-de-France","place":"Paris","country_adm_id":0,"gadm":null,"city_id":"5009811","city":"Paris","zoom":20},"description":null},{"id":28992473,"language_id":2,"language_iso":"fr","urlhtml":"<a class=\"wikimapia-link\" href=\"http://wikimapia.org/28992473/fr/Rue-des-Francs-Bourgeois-15\">Rue des Francs Bourgeois, 15</a>","title":null,"tags":null,"wikipedia":null,"is_building":true,"is_region":false,"is_deleted":false,"parent_id":"0","polygon":[{"x":2.3633158,"y":48.8567246},{"x":2.3633642,"y":48.8567113},{"x":2.3634101,"y":48.8566963},{"x":2.363332,"y":48.8565694},{"x":2.3632994,"y":48.8565234},{"x":2.3632058,"y":48.8565514},{"x":2.3632383,"y":48.8565996}],"location":{"lon":2.3633079,"lat":48.856624,"north":48.8567246,"south":48.8565234,"east":2.3634101,"west":2.3632058,"country":"France","state":"Ile-de-France","place":"Paris","country_adm_id":0,"gadm":null,"city_id":"5009811","city":"Paris","zoom":20},"description":null},{"id":28992627,"language_id":2,"language_iso":"fr","urlhtml":"<a class=\"wikimapia-link\" href=\"http://wikimapia.org/28992627/fr/Rue-Sainte-Anastase-16\">Rue Sainte-Anastase, 16</a>","title":null,"tags":null,"wikipedia":null,"is_building":true,"is_region":false,"is_deleted":false,"parent_id":"0","polygon":[{"x":2.3634549,"y":48.859773},{"x":2.3633711,"y":48.8597959},{"x":2.3633252,"y":48.8598092},{"x":2.3633989,"y":48.8599154},{"x":2.3635004,"y":48.8599271},{"x":2.3635186,"y":48.8599286},{"x":2.3635385,"y":48.8599225},{"x":2.3635441,"y":48.8599211}],"location":{"lon":2.3634346,"lat":48.8598508,"north":48.8599286,"south":48.859773,"east":2.3635441,"west":2.3633252,"country":"France","state":"Ile-de-France","place":"Paris","country_adm_id":0,"gadm":null,"city_id":"5009811","city":"Paris","zoom":20},"description":null},{"id":28992656,"language_id":2,"language_iso":"fr","urlhtml":"<a class=\"wikimapia-link\" href=\"http://wikimapia.org/28992656/fr/Rue-de-Turenne-89\">Rue de Turenne, 89</a>","title":null,"tags":null,"wikipedia":null,"is_building":true,"is_region":false,"is_deleted":false,"parent_id":"0","polygon":[{"x":2.3641465,"y":48.8607659},{"x":2.3641722,"y":48.8607806},{"x":2.3642148,"y":48.8607804},{"x":2.3642435,"y":48.8607817},{"x":2.3642443,"y":48.8607328},{"x":2.3643246,"y":48.8607312},{"x":2.3643336,"y":48.8607423},{"x":2.3643378,"y":48.8607419},{"x":2.3643377,"y":48.8607847},{"x":2.3644841,"y":48.8607875},{"x":2.3644819,"y":48.8607486},{"x":2.3644808,"y":48.860707},{"x":2.3642213,"y":48.8606999}],"location":{"lon":2.3643153,"lat":48.8607437,"north":48.8607875,"south":48.8606999,"east":2.3644841,"west":2.3641465,"country":"France","state":"Ile-de-France","place":"Paris","country_adm_id":0,"gadm":null,"city_id":"5009811","city":"Paris","zoom":20},"description":null},{"id":29004112,"language_id":0,"language_iso":"en","urlhtml":"<a class=\"wikimapia-link\" href=\"http://wikimapia.org/29004112/Rue-Saint-Denis-73\">Rue Saint-Denis, 73</a>","title":null,"tags":[{"id":109,"title":"building"}],"wikipedia":null,"is_building":true,"is_region":false,"is_deleted":false,"parent_id":"0","polygon":[{"x":2.3487754,"y":48.8617274},{"x":2.3490581,"y":48.8616636},{"x":2.349023,"y":48.8615971},{"x":2.3487466,"y":48.861667}],"location":{"lon":2.3489023,"lat":48.8616622,"north":48.8617274,"south":48.8615971,"east":2.3490581,"west":2.3487466,"country":"France","state":"Ile-de-France","place":"Paris","country_adm_id":0,"gadm":null,"city_id":"5009811","city":"Paris","zoom":20},"description":null},{"id":29005472,"language_id":2,"language_iso":"fr","urlhtml":"<a class=\"wikimapia-link\" href=\"http://wikimapia.org/29005472/fr/rue-du-Saint-Martin-181\">rue du Saint-Martin, 181</a>","title":null,"tags":null,"wikipedia":null,"is_building":true,"is_region":false,"is_deleted":false,"parent_id":"0","polygon":[{"x":2.3522271,"y":48.8628183},{"x":2.3522161,"y":48.8627905},{"x":2.3522043,"y":48.862765},{"x":2.3518685,"y":48.8628561},{"x":2.351899,"y":48.8628976},{"x":2.3519063,"y":48.862912},{"x":2.3519761,"y":48.862885}],"location":{"lon":2.3520478,"lat":48.8628385,"north":48.862912,"south":48.862765,"east":2.3522271,"west":2.3518685,"country":"France","state":"Ile-de-France","place":"Paris","country_adm_id":0,"gadm":null,"city_id":"5009811","city":"Paris","zoom":19},"description":null},{"id":29005647,"language_id":2,"language_iso":"fr","urlhtml":"<a class=\"wikimapia-link\" href=\"http://wikimapia.org/29005647/fr/Rue-du-Bourg-l-Abb%C3%A9-4\">Rue du Bourg l'Abbé, 4</a>","title":null,"tags":null,"wikipedia":null,"is_building":true,"is_region":false,"is_deleted":false,"parent_id":"0","polygon":[{"x":2.3523211,"y":48.864105},{"x":2.3523967,"y":48.8640845},{"x":2.3523914,"y":48.8640729},{"x":2.3523624,"y":48.8640806},{"x":2.3523462,"y":48.8640801},{"x":2.3523212,"y":48.864041},{"x":2.352373,"y":48.8640264},{"x":2.3524092,"y":48.8640791},{"x":2.3524579,"y":48.8640651},{"x":2.3523916,"y":48.8639618},{"x":2.3523666,"y":48.8639268},{"x":2.3522858,"y":48.8639493},{"x":2.3522315,"y":48.8639622}],"location":{"lon":2.3523447,"lat":48.8640159,"north":48.864105,"south":48.8639268,"east":2.3524579,"west":2.3522315,"country":"France","state":"Ile-de-France","place":"Paris","country_adm_id":0,"gadm":null,"city_id":"5009811","city":"Paris","zoom":19},"description":null},{"id":29005653,"language_id":2,"language_iso":"fr","urlhtml":"<a class=\"wikimapia-link\" href=\"http://wikimapia.org/29005653/fr/Rue-Turbigo-26\">Rue Turbigo, 26</a>","title":null,"tags":null,"wikipedia":null,"is_building":true,"is_region":false,"is_deleted":false,"parent_id":"0","polygon":[{"x":2.3518207,"y":48.8644008},{"x":2.3518638,"y":48.8643167},{"x":2.3518419,"y":48.8643116},{"x":2.3518437,"y":48.8643065},{"x":2.3518098,"y":48.864253},{"x":2.3518173,"y":48.8642502},{"x":2.3518259,"y":48.8642562},{"x":2.351855,"y":48.8642515},{"x":2.3518522,"y":48.8642375},{"x":2.351775,"y":48.8642557},{"x":2.351661,"y":48.8642804},{"x":2.351691,"y":48.8643361},{"x":2.3517174,"y":48.8643774},{"x":2.3517645,"y":48.8643889}],"location":{"lon":2.3517624,"lat":48.8643191,"north":48.8644008,"south":48.8642375,"east":2.3518638,"west":2.351661,"country":"France","state":"Ile-de-France","place":"Paris","country_adm_id":0,"gadm":null,"city_id":"5009811","city":"Paris","zoom":20},"description":null},{"id":29006012,"language_id":2,"language_iso":"fr","urlhtml":"<a class=\"wikimapia-link\" href=\"http://wikimapia.org/29006012/fr/Rue-Chapon-54\">Rue Chapon, 54</a>","title":null,"tags":null,"wikipedia":null,"is_building":true,"is_region":false,"is_deleted":false,"parent_id":"0","polygon":[{"x":2.3538982,"y":48.8640655},{"x":2.3538643,"y":48.8640767},{"x":2.3538244,"y":48.8640876},{"x":2.3538729,"y":48.8641586},{"x":2.3539184,"y":48.864235},{"x":2.3539731,"y":48.8643175},{"x":2.3540452,"y":48.8642995}],"location":{"lon":2.3539348,"lat":48.8641915,"north":48.8643175,"south":48.8640655,"east":2.3540452,"west":2.3538244,"country":"France","state":"Ile-de-France","place":"Paris","country_adm_id":0,"gadm":null,"city_id":"5009811","city":"Paris","zoom":20},"description":null},{"id":29006538,"language_id":0,"language_iso":"en","urlhtml":"<a class=\"wikimapia-link\" href=\"http://wikimapia.org/29006538/Rue-du-Temple-155\">Rue du Temple, 155</a>","title":null,"tags":[{"id":109,"title":"building"}],"wikipedia":null,"is_building":true,"is_region":false,"is_deleted":false,"parent_id":"0","polygon":[{"x":2.3590578,"y":48.8642531},{"x":2.3590356,"y":48.8642301},{"x":2.3590123,"y":48.8642098},{"x":2.3588361,"y":48.864275},{"x":2.3588608,"y":48.864303},{"x":2.3587965,"y":48.8643271},{"x":2.3587881,"y":48.8643124},{"x":2.3587192,"y":48.8643389},{"x":2.3587295,"y":48.864351},{"x":2.3587034,"y":48.8643633},{"x":2.3586794,"y":48.8643377},{"x":2.3586259,"y":48.8643586},{"x":2.3586596,"y":48.8643944},{"x":2.3586686,"y":48.8644028}],"location":{"lon":2.3588418,"lat":48.8643063,"north":48.8644028,"south":48.8642098,"east":2.3590578,"west":2.3586259,"country":"France","state":"Ile-de-France","place":"Paris","country_adm_id":0,"gadm":null,"city_id":"5009811","city":"Paris","zoom":19},"description":null},{"id":29008354,"language_id":2,"language_iso":"fr","urlhtml":"<a class=\"wikimapia-link\" href=\"http://wikimapia.org/29008354/fr/Rue-de-Saintonge-63\">Rue de Saintonge, 63</a>","title":null,"tags":null,"wikipedia":null,"is_building":true,"is_region":false,"is_deleted":false,"parent_id":"0","polygon":[{"x":2.3654985,"y":48.8644023},{"x":2.3654491,"y":48.8643577},{"x":2.365418,"y":48.8643307},{"x":2.3652942,"y":48.8643705},{"x":2.365201,"y":48.8644},{"x":2.365221,"y":48.8644304},{"x":2.3652572,"y":48.864479},{"x":2.3652663,"y":48.8644751},{"x":2.365324,"y":48.8644573},{"x":2.3653161,"y":48.8644475},{"x":2.3653039,"y":48.8644528},{"x":2.3652672,"y":48.8644022},{"x":2.3652901,"y":48.864394},{"x":2.3652977,"y":48.8644016},{"x":2.3653003,"y":48.8644007},{"x":2.365312,"y":48.8644185},{"x":2.3653364,"y":48.8644092},{"x":2.3653544,"y":48.864435},{"x":2.365343,"y":48.8644397},{"x":2.3653455,"y":48.8644422},{"x":2.3653331,"y":48.8644433},{"x":2.3653386,"y":48.8644546}],"location":{"lon":2.3653497,"lat":48.8644048,"north":48.864479,"south":48.8643307,"east":2.3654985,"west":2.365201,"country":"France","state":"Ile-de-France","place":"Paris","country_adm_id":0,"gadm":null,"city_id":"5009811","city":"Paris","zoom":20},"description":null},{"id":29008681,"language_id":2,"language_iso":"fr","urlhtml":"<a class=\"wikimapia-link\" href=\"http://wikimapia.org/29008681/fr/rue-Charlot-29\">rue Charlot, 29</a>","title":null,"tags":null,"wikipedia":null,"is_building":true,"is_region":false,"is_deleted":false,"parent_id":"0","polygon":[{"x":2.3618571,"y":48.862324},{"x":2.3618164,"y":48.862288},{"x":2.3617905,"y":48.8622636},{"x":2.361682,"y":48.8623177},{"x":2.3616568,"y":48.8623289},{"x":2.361667,"y":48.8623373},{"x":2.3616828,"y":48.8623396},{"x":2.3616965,"y":48.8623332},{"x":2.3617268,"y":48.8623557},{"x":2.3616669,"y":48.8623855},{"x":2.3616216,"y":48.8623458},{"x":2.3615986,"y":48.8623562},{"x":2.3615477,"y":48.8623843},{"x":2.3616163,"y":48.8624439}],"location":{"lon":2.3617024,"lat":48.8623537,"north":48.8624439,"south":48.8622636,"east":2.3618571,"west":2.3615477,"country":"France","state":"Ile-de-France","place":"Paris","country_adm_id":0,"gadm":null,"city_id":"5009811","city":"Paris","zoom":19},"description":null},{"id":29009936,"language_id":2,"language_iso":"fr","urlhtml":"<a class=\"wikimapia-link\" href=\"http://wikimapia.org/29009936/fr/Rue-Amelot-133\">Rue Amelot, 133</a>","title":null,"tags":null,"wikipedia":null,"is_building":true,"is_region":false,"is_deleted":false,"parent_id":"0","polygon":[{"x":2.3666188,"y":48.8644658},{"x":2.3665227,"y":48.864442},{"x":2.3665326,"y":48.8644307},{"x":2.3665087,"y":48.8644239},{"x":2.3665168,"y":48.8644053},{"x":2.3664624,"y":48.8643916},{"x":2.3664533,"y":48.8644096},{"x":2.3664404,"y":48.8644061},{"x":2.3664325,"y":48.8644206},{"x":2.3662484,"y":48.8643733},{"x":2.3662588,"y":48.8643557},{"x":2.3662812,"y":48.8643238},{"x":2.3666411,"y":48.864408},{"x":2.3666306,"y":48.8644332}],"location":{"lon":2.3664447,"lat":48.8643948,"north":48.8644658,"south":48.8643238,"east":2.3666411,"west":2.3662484,"country":"France","state":"Ile-de-France","place":"Paris","country_adm_id":0,"gadm":null,"city_id":"5009811","city":"Paris","zoom":20},"description":null},{"id":29009952,"language_id":2,"language_iso":"fr","urlhtml":"<a class=\"wikimapia-link\" href=\"http://wikimapia.org/29009952/fr/Rue-Amelot-153\">Rue Amelot, 153</a>","title":null,"tags":null,"wikipedia":null,"is_building":true,"is_region":false,"is_deleted":false,"parent_id":"0","polygon":[{"x":2.3661428,"y":48.8655894},{"x":2.3660258,"y":48.865567},{"x":2.3659827,"y":48.8655602},{"x":2.3659978,"y":48.8655219},{"x":2.3660427,"y":48.8655293},{"x":2.366046,"y":48.8655174},{"x":2.3659372,"y":48.8654985},{"x":2.3659166,"y":48.8655478},{"x":2.365861,"y":48.8655381},{"x":2.3658627,"y":48.8655342},{"x":2.3658739,"y":48.8654932},{"x":2.365891,"y":48.865496},{"x":2.3659226,"y":48.8654896},{"x":2.3660192,"y":48.86547},{"x":2.3661795,"y":48.8655019},{"x":2.3661574,"y":48.865559}],"location":{"lon":2.3660202,"lat":48.8655297,"north":48.8655894,"south":48.86547,"east":2.3661795,"west":2.365861,"country":"France","state":"Ile-de-France","place":"Paris","country_adm_id":0,"gadm":null,"city_id":"5009811","city":"Paris","zoom":20},"description":null},{"id":29016574,"language_id":2,"language_iso":"fr","urlhtml":"<a class=\"wikimapia-link\" href=\"http://wikimapia.org/29016574/fr/Rue-L%C3%A9opold-Bellan-1\">Rue Léopold Bellan, 1</a>","title":null,"tags":null,"wikipedia":null,"is_building":true,"is_region":false,"is_deleted":false,"parent_id":"0","polygon":[{"x":2.3467403,"y":48.8663686},{"x":2.3467921,"y":48.8663594},{"x":2.3468702,"y":48.8663451},{"x":2.3468865,"y":48.8663849},{"x":2.3469874,"y":48.8663658},{"x":2.3471107,"y":48.8663428},{"x":2.3471175,"y":48.8663365},{"x":2.3471084,"y":48.8662996},{"x":2.3471023,"y":48.8662707},{"x":2.3469485,"y":48.8662971},{"x":2.346961,"y":48.8663389},{"x":2.3469428,"y":48.8663424},{"x":2.3469381,"y":48.8663285},{"x":2.3468888,"y":48.866335},{"x":2.3468589,"y":48.8663352},{"x":2.3468525,"y":48.8663149},{"x":2.3467229,"y":48.8663359}],"location":{"lon":2.3469202,"lat":48.8663278,"north":48.8663849,"south":48.8662707,"east":2.3471175,"west":2.3467229,"country":"France","state":"Ile-de-France","place":"Paris","country_adm_id":0,"gadm":null,"city_id":"5009811","city":"Paris","zoom":20},"description":null},{"id":29016748,"language_id":2,"language_iso":"fr","urlhtml":"<a class=\"wikimapia-link\" href=\"http://wikimapia.org/29016748/fr/Rue-du-Caire-11\">Rue du Caire, 11</a>","title":null,"tags":null,"wikipedia":null,"is_building":true,"is_region":false,"is_deleted":false,"parent_id":"0","polygon":[{"x":2.3520032,"y":48.8672044},{"x":2.352102,"y":48.8671832},{"x":2.3522048,"y":48.8671582},{"x":2.3521484,"y":48.8670531},{"x":2.3521364,"y":48.8670565},{"x":2.3521429,"y":48.8670711},{"x":2.3521126,"y":48.8670824},{"x":2.3521036,"y":48.8670629},{"x":2.3520335,"y":48.8670785},{"x":2.3520523,"y":48.8671116},{"x":2.3520015,"y":48.867127},{"x":2.3519737,"y":48.8671476}],"location":{"lon":2.3520892,"lat":48.8671287,"north":48.8672044,"south":48.8670531,"east":2.3522048,"west":2.3519737,"country":"France","state":"Ile-de-France","place":"Paris","country_adm_id":0,"gadm":null,"city_id":"5009811","city":"Paris","zoom":19},"description":null},{"id":29016827,"language_id":0,"language_iso":"en","urlhtml":"<a class=\"wikimapia-link\" href=\"http://wikimapia.org/29016827/Rue-Saint-Denis-234-234\">Rue Saint-Denis, 234, 234</a>","title":null,"tags":[{"id":109,"title":"building"}],"wikipedia":null,"is_building":true,"is_region":false,"is_deleted":false,"parent_id":"0","polygon":[{"x":2.3522171,"y":48.8687253},{"x":2.3522231,"y":48.8687388},{"x":2.352242,"y":48.8687819},{"x":2.3522558,"y":48.8688154},{"x":2.352477,"y":48.8687624},{"x":2.3524964,"y":48.8687579},{"x":2.35248,"y":48.8687215},{"x":2.3524464,"y":48.8687301},{"x":2.3524265,"y":48.8687213},{"x":2.3523942,"y":48.8687271},{"x":2.3523755,"y":48.8686878},{"x":2.3523798,"y":48.8686872},{"x":2.352379,"y":48.8686841}],"location":{"lon":2.3523567,"lat":48.8687497,"north":48.8688154,"south":48.8686841,"east":2.3524964,"west":2.3522171,"country":"France","state":"Ile-de-France","place":"Paris","country_adm_id":0,"gadm":null,"city_id":"5009811","city":"Paris","zoom":20},"description":null},{"id":29016854,"language_id":2,"language_iso":"fr","urlhtml":"<a class=\"wikimapia-link\" href=\"http://wikimapia.org/29016854/fr/Boulevard-de-S%C3%A9bastopol-127\">Boulevard de Sébastopol, 127</a>","title":null,"tags":null,"wikipedia":null,"is_building":true,"is_region":false,"is_deleted":false,"parent_id":"0","polygon":[{"x":2.3531067,"y":48.8679336},{"x":2.3531675,"y":48.8679224},{"x":2.3532198,"y":48.8679136},{"x":2.3532368,"y":48.8678873},{"x":2.3532007,"y":48.867827},{"x":2.3531706,"y":48.8677698},{"x":2.3530439,"y":48.8677989}],"location":{"lon":2.3531403,"lat":48.8678517,"north":48.8679336,"south":48.8677698,"east":2.3532368,"west":2.3530439,"country":"France","state":"Ile-de-France","place":"Paris","country_adm_id":0,"gadm":null,"city_id":"5009811","city":"Paris","zoom":20},"description":null},{"id":29016902,"language_id":2,"language_iso":"fr","urlhtml":"<a class=\"wikimapia-link\" href=\"http://wikimapia.org/29016902/fr/Rue-Blondel-32\">Rue Blondel, 32</a>","title":null,"tags":null,"wikipedia":null,"is_building":true,"is_region":false,"is_deleted":false,"parent_id":"0","polygon":[{"x":2.3526508,"y":48.8689089},{"x":2.3525962,"y":48.8689218},{"x":2.352602,"y":48.8689363},{"x":2.3525501,"y":48.8689461},{"x":2.3525687,"y":48.8689842},{"x":2.3525749,"y":48.8690035},{"x":2.352606,"y":48.8689987},{"x":2.352622,"y":48.8690255},{"x":2.3525918,"y":48.8690313},{"x":2.3526117,"y":48.8690662},{"x":2.3526295,"y":48.8691106},{"x":2.3527461,"y":48.8690899},{"x":2.3527096,"y":48.8690174},{"x":2.3526771,"y":48.8690222},{"x":2.352669,"y":48.8689997},{"x":2.3526977,"y":48.8689942}],"location":{"lon":2.3526481,"lat":48.8690097,"north":48.8691106,"south":48.8689089,"east":2.3527461,"west":2.3525501,"country":"France","state":"Ile-de-France","place":"Paris","country_adm_id":0,"gadm":null,"city_id":"5009811","city":"Paris","zoom":20},"description":null},{"id":29016973,"language_id":2,"language_iso":"fr","urlhtml":"<a class=\"wikimapia-link\" href=\"http://wikimapia.org/29016973/fr/Rue-d-Alexandrie-31\">Rue d'Alexandrie, 31</a>","title":null,"tags":null,"wikipedia":null,"is_building":true,"is_region":false,"is_deleted":false,"parent_id":"0","polygon":[{"x":2.3499176,"y":48.8680415},{"x":2.3499037,"y":48.8680611},{"x":2.3498731,"y":48.8681017},{"x":2.3498432,"y":48.8681413},{"x":2.3498176,"y":48.8681822},{"x":2.3498,"y":48.8682037},{"x":2.349902,"y":48.868235},{"x":2.3499604,"y":48.8681583},{"x":2.349954,"y":48.8681552},{"x":2.3499706,"y":48.8681343},{"x":2.3500008,"y":48.8680928},{"x":2.3499907,"y":48.8680652}],"location":{"lon":2.3499004,"lat":48.8681382,"north":48.868235,"south":48.8680415,"east":2.3500008,"west":2.3498,"country":"France","state":"Ile-de-France","place":"Paris","country_adm_id":0,"gadm":null,"city_id":"5009811","city":"Paris","zoom":20},"description":null},{"id":29018345,"language_id":2,"language_iso":"fr","urlhtml":"<a class=\"wikimapia-link\" href=\"http://wikimapia.org/29018345/fr/Rue-Volta-50\">Rue Volta, 50</a>","title":null,"tags":null,"wikipedia":null,"is_building":true,"is_region":false,"is_deleted":false,"parent_id":"0","polygon":[{"x":2.3581321,"y":48.8666704},{"x":2.3581513,"y":48.8667034},{"x":2.3581739,"y":48.8667391},{"x":2.3582605,"y":48.8667239},{"x":2.3583084,"y":48.8667153},{"x":2.3583749,"y":48.8667009},{"x":2.3583405,"y":48.8666449},{"x":2.3583889,"y":48.8666309},{"x":2.3583606,"y":48.8665741},{"x":2.3583085,"y":48.8665845},{"x":2.3583286,"y":48.8666267}],"location":{"lon":2.3582605,"lat":48.8666566,"north":48.8667391,"south":48.8665741,"east":2.3583889,"west":2.3581321,"country":"France","state":"Ile-de-France","place":"Paris","country_adm_id":0,"gadm":null,"city_id":"5009811","city":"Paris","zoom":19},"description":null},{"id":29020082,"language_id":2,"language_iso":"fr","urlhtml":"<a class=\"wikimapia-link\" href=\"http://wikimapia.org/29020082/fr/Hippopotamus\">Hippopotamus</a>","title":"Hippopotamus","tags":[{"id":74,"title":"restaurant, restauration"}],"wikipedia":null,"is_building":false,"is_region":false,"is_deleted":false,"parent_id":"0","polygon":[{"x":2.3624644,"y":48.8675644},{"x":2.3624898,"y":48.8675486},{"x":2.362516,"y":48.8675339},{"x":2.3625663,"y":48.8675055},{"x":2.3624641,"y":48.8674304},{"x":2.3624407,"y":48.8674105},{"x":2.3622964,"y":48.8674361}],"location":{"lon":2.3624313,"lat":48.8674874,"north":48.8675644,"south":48.8674105,"east":2.3625663,"west":2.3622964,"country":"France","state":"Ile-de-France","place":"Paris","country_adm_id":0,"gadm":null,"city_id":"5009811","city":"Paris","zoom":20},"description":null},{"id":29020816,"language_id":2,"language_iso":"fr","urlhtml":"<a class=\"wikimapia-link\" href=\"http://wikimapia.org/29020816/fr/Rue-Jacques-Louvel-Tessier-8\">Rue Jacques Louvel-Tessier, 8</a>","title":null,"tags":null,"wikipedia":null,"is_building":true,"is_region":false,"is_deleted":false,"parent_id":"0","polygon":[{"x":2.3689801,"y":48.8708416},{"x":2.3690318,"y":48.8707586},{"x":2.3691068,"y":48.8707806},{"x":2.3691506,"y":48.8707256},{"x":2.3692211,"y":48.8707474},{"x":2.3691734,"y":48.8708176},{"x":2.3691252,"y":48.8708859},{"x":2.3690571,"y":48.8708662}],"location":{"lon":2.3691006,"lat":48.8708057,"north":48.8708859,"south":48.8707256,"east":2.3692211,"west":2.3689801,"country":"France","state":"Ile-de-France","place":"Le Pre-Saint-Gervais","country_adm_id":0,"gadm":null,"city_id":"5009811","city":"Paris","zoom":20},"description":null},{"id":29021576,"language_id":2,"language_iso":"fr","urlhtml":"<a class=\"wikimapia-link\" href=\"http://wikimapia.org/29021576/fr/Auberge-Pyr%C3%A9n%C3%A9es-C%C3%A9vennes\">Auberge Pyrénées Cévennes</a>","title":"Auberge Pyrénées Cévennes","tags":[{"id":74,"title":"restaurant, restauration"}],"wikipedia":null,"is_building":true,"is_region":false,"is_deleted":false,"parent_id":"0","polygon":[{"x":2.3687368,"y":48.8678952},{"x":2.3687831,"y":48.8678322},{"x":2.3688312,"y":48.8677672},{"x":2.3689618,"y":48.8677965},{"x":2.3688688,"y":48.8679252},{"x":2.3688596,"y":48.8679231}],"location":{"lon":2.3688493,"lat":48.8678462,"north":48.8679252,"south":48.8677672,"east":2.3689618,"west":2.3687368,"country":"France","state":"Ile-de-France","place":"Paris","country_adm_id":0,"gadm":null,"city_id":"5009811","city":"Paris","zoom":20},"description":null},{"id":29025522,"language_id":2,"language_iso":"fr","urlhtml":"<a class=\"wikimapia-link\" href=\"http://wikimapia.org/29025522/fr/Rue-Berg%C3%A8re-24\">Rue Bergère, 24</a>","title":null,"tags":null,"wikipedia":null,"is_building":true,"is_region":false,"is_deleted":false,"parent_id":"0","polygon":[{"x":2.344908,"y":48.8726452},{"x":2.3447839,"y":48.8726576},{"x":2.3447756,"y":48.8726254},{"x":2.3448,"y":48.8726207},{"x":2.3447939,"y":48.8725929},{"x":2.3447839,"y":48.872595},{"x":2.3447744,"y":48.8725917},{"x":2.3447696,"y":48.8725869},{"x":2.344761,"y":48.8725841},{"x":2.3447388,"y":48.8725026},{"x":2.3448078,"y":48.8724921},{"x":2.3448425,"y":48.8724858},{"x":2.3448742,"y":48.8725016}],"location":{"lon":2.3448234,"lat":48.8725717,"north":48.8726576,"south":48.8724858,"east":2.344908,"west":2.3447388,"country":"France","state":"Ile-de-France","place":"Paris","country_adm_id":0,"gadm":null,"city_id":"5009811","city":"Paris","zoom":20},"description":null},{"id":29027178,"language_id":2,"language_iso":"fr","urlhtml":"<a class=\"wikimapia-link\" href=\"http://wikimapia.org/29027178/fr/Rue-du-Ch%C3%A2teau-d-Eau-76\">Rue du Château d'Eau, 76</a>","title":null,"tags":null,"wikipedia":null,"is_building":true,"is_region":false,"is_deleted":false,"parent_id":"0","polygon":[{"x":2.3550028,"y":48.872767},{"x":2.3548606,"y":48.872823},{"x":2.3548108,"y":48.8727674},{"x":2.354942,"y":48.8727138},{"x":2.3550754,"y":48.8726596},{"x":2.355129,"y":48.8727169},{"x":2.3550665,"y":48.8727408},{"x":2.3550491,"y":48.8727232},{"x":2.3550157,"y":48.872738},{"x":2.3550298,"y":48.8727545}],"location":{"lon":2.3549699,"lat":48.8727413,"north":48.872823,"south":48.8726596,"east":2.355129,"west":2.3548108,"country":"France","state":"Ile-de-France","place":"Paris","country_adm_id":0,"gadm":null,"city_id":"5009811","city":"Paris","zoom":19},"description":null},{"id":29029643,"language_id":2,"language_iso":"fr","urlhtml":"<a class=\"wikimapia-link\" href=\"http://wikimapia.org/29029643/fr/Rue-Arthur-Groussier-3\">Rue Arthur Groussier, 3</a>","title":null,"tags":null,"wikipedia":null,"is_building":true,"is_region":false,"is_deleted":false,"parent_id":"0","polygon":[{"x":2.3701639,"y":48.8719876},{"x":2.3701459,"y":48.8720094},{"x":2.3700944,"y":48.871993},{"x":2.3701195,"y":48.8719578},{"x":2.3700992,"y":48.8719415},{"x":2.3700952,"y":48.8719439},{"x":2.3700842,"y":48.8719409},{"x":2.3700881,"y":48.8719337},{"x":2.3700468,"y":48.8719221},{"x":2.3700305,"y":48.8719473},{"x":2.370086,"y":48.8719672},{"x":2.3700756,"y":48.8719855},{"x":2.3699964,"y":48.8719621},{"x":2.3700695,"y":48.8718592},{"x":2.3700832,"y":48.8718426},{"x":2.3701563,"y":48.8718631},{"x":2.3702356,"y":48.8718906},{"x":2.3701703,"y":48.8719789}],"location":{"lon":2.370116,"lat":48.871926,"north":48.8720094,"south":48.8718426,"east":2.3702356,"west":2.3699964,"country":"France","state":"Ile-de-France","place":"Le Pre-Saint-Gervais","country_adm_id":0,"gadm":null,"city_id":"5009811","city":"Paris","zoom":19},"description":null},{"id":25810107,"language_id":2,"language_iso":"fr","urlhtml":"<a class=\"wikimapia-link\" href=\"http://wikimapia.org/25810107/fr/H%C3%B4tel-de-Tresmes\">Hôtel de Tresmes</a>","title":"Hôtel de Tresmes","tags":null,"wikipedia":null,"is_building":true,"is_region":false,"is_deleted":false,"parent_id":"0","polygon":[{"x":2.3661638,"y":48.8561739},{"x":2.3661825,"y":48.856233},{"x":2.3664937,"y":48.8561827},{"x":2.3664776,"y":48.8561227}],"location":{"lon":2.3663287,"lat":48.8561778,"north":48.856233,"south":48.8561227,"east":2.3664937,"west":2.3661638,"country":"France","state":"Ile-de-France","place":"Paris","country_adm_id":0,"gadm":null,"city_id":"5009811","city":"Paris","zoom":20},"description":null},{"id":28973816,"language_id":2,"language_iso":"fr","urlhtml":"<a class=\"wikimapia-link\" href=\"http://wikimapia.org/28973816/fr/rue-d-Arcole-15\">rue d'Arcole, 15</a>","title":null,"tags":null,"wikipedia":null,"is_building":true,"is_region":false,"is_deleted":false,"parent_id":"0","polygon":[{"x":2.3495897,"y":48.8539765},{"x":2.349623,"y":48.8540201},{"x":2.3496592,"y":48.854064},{"x":2.3498343,"y":48.8540097},{"x":2.349823,"y":48.8539928},{"x":2.3498208,"y":48.853989},{"x":2.3497771,"y":48.8540028},{"x":2.3497613,"y":48.8539816},{"x":2.3498132,"y":48.853966},{"x":2.3497842,"y":48.8539135},{"x":2.349733,"y":48.8539303},{"x":2.3496906,"y":48.8539442}],"location":{"lon":2.349712,"lat":48.8539887,"north":48.854064,"south":48.8539135,"east":2.3498343,"west":2.3495897,"country":"France","state":"Ile-de-France","place":"Paris","country_adm_id":0,"gadm":null,"city_id":"5009811","city":"Paris","zoom":20},"description":null},{"id":28974401,"language_id":2,"language_iso":"fr","urlhtml":"<a class=\"wikimapia-link\" href=\"http://wikimapia.org/28974401/ru/rue-de-Pont-Louis-Phillipe-7\">rue de Pont Louis-Phillipe, 7</a>","title":null,"tags":null,"wikipedia":null,"is_building":true,"is_region":false,"is_deleted":false,"parent_id":"0","polygon":[{"x":2.3551988,"y":48.8550329},{"x":2.3552203,"y":48.8550762},{"x":2.3552416,"y":48.8551155},{"x":2.3553178,"y":48.8550985},{"x":2.3553061,"y":48.8550647},{"x":2.3553299,"y":48.8550619},{"x":2.3553418,"y":48.8550965},{"x":2.355494,"y":48.8550736},{"x":2.3554515,"y":48.8550265},{"x":2.3554203,"y":48.8549956},{"x":2.3553131,"y":48.8550143},{"x":2.3553199,"y":48.8550324},{"x":2.3553141,"y":48.8550377},{"x":2.3553098,"y":48.8550367},{"x":2.3552945,"y":48.8550394},{"x":2.3552824,"y":48.8550359},{"x":2.3552777,"y":48.8550199}],"location":{"lon":2.3553464,"lat":48.8550555,"north":48.8551155,"south":48.8549956,"east":2.355494,"west":2.3551988,"country":"France","state":"Ile-de-France","place":"Paris","country_adm_id":0,"gadm":null,"city_id":"5009811","city":"Paris","zoom":20},"description":null},{"id":28975761,"language_id":2,"language_iso":"fr","urlhtml":"<a class=\"wikimapia-link\" href=\"http://wikimapia.org/28975761/fr/Place-des-Vosges-4\">Place des Vosges, 4</a>","title":null,"tags":null,"wikipedia":null,"is_building":true,"is_region":false,"is_deleted":false,"parent_id":"0","polygon":[{"x":2.3630068,"y":48.8553437},{"x":2.3630404,"y":48.8553966},{"x":2.3630847,"y":48.8554698},{"x":2.3630866,"y":48.8554727},{"x":2.3632182,"y":48.8554335},{"x":2.3631755,"y":48.8553715},{"x":2.3631379,"y":48.8553092}],"location":{"lon":2.3631125,"lat":48.8553909,"north":48.8554727,"south":48.8553092,"east":2.3632182,"west":2.3630068,"country":"France","state":"Ile-de-France","place":"Paris","country_adm_id":0,"gadm":null,"city_id":"5009811","city":"Paris","zoom":20},"description":null},{"id":28975969,"language_id":2,"language_iso":"fr","urlhtml":"<a class=\"wikimapia-link\" href=\"http://wikimapia.org/28975969/fr/Chris-Matthioux\">Chris Matthioux</a>","title":"Chris Matthioux","tags":[{"id":17,"title":"magasin"}],"wikipedia":null,"is_building":true,"is_region":false,"is_deleted":false,"parent_id":"0","polygon":[{"x":2.3650894,"y":48.8542898},{"x":2.3651101,"y":48.8543432},{"x":2.365137,"y":48.8544083},{"x":2.365288,"y":48.8543794},{"x":2.3652596,"y":48.8543112},{"x":2.3652327,"y":48.854258}],"location":{"lon":2.3651887,"lat":48.8543331,"north":48.8544083,"south":48.854258,"east":2.365288,"west":2.3650894,"country":"France","state":"Ile-de-France","place":"Paris","country_adm_id":0,"gadm":null,"city_id":"5009811","city":"Paris","zoom":20},"description":null},{"id":28976087,"language_id":2,"language_iso":"fr","urlhtml":"<a class=\"wikimapia-link\" href=\"http://wikimapia.org/28976087/fr/Rue-Jean-Beausire-12\">Rue Jean Beausire, 12</a>","title":null,"tags":null,"wikipedia":null,"is_building":true,"is_region":false,"is_deleted":false,"parent_id":"0","polygon":[{"x":2.3685367,"y":48.8545661},{"x":2.3685429,"y":48.8545399},{"x":2.3685462,"y":48.8545262},{"x":2.3685504,"y":48.8545095},{"x":2.3683618,"y":48.854503},{"x":2.3683586,"y":48.8545347},{"x":2.3683051,"y":48.8545326},{"x":2.3682969,"y":48.8545216},{"x":2.368308,"y":48.8545211},{"x":2.3683168,"y":48.8545147},{"x":2.3683169,"y":48.8545014},{"x":2.368285,"y":48.8544999},{"x":2.3682653,"y":48.854499},{"x":2.3681805,"y":48.8544962},{"x":2.3681791,"y":48.8545306},{"x":2.3681783,"y":48.8545545}],"location":{"lon":2.3683643,"lat":48.8545311,"north":48.8545661,"south":48.8544962,"east":2.3685504,"west":2.3681783,"country":"France","state":"Ile-de-France","place":"Paris","country_adm_id":0,"gadm":null,"city_id":"5009811","city":"Paris","zoom":21},"description":null},{"id":28976163,"language_id":2,"language_iso":"fr","urlhtml":"<a class=\"wikimapia-link\" href=\"http://wikimapia.org/28976163/fr/Rue-des-Tournelles-42\">Rue des Tournelles, 42</a>","title":null,"tags":null,"wikipedia":null,"is_building":true,"is_region":false,"is_deleted":false,"parent_id":"0","polygon":[{"x":2.3673547,"y":48.8556889},{"x":2.3673567,"y":48.8557264},{"x":2.3673568,"y":48.8557477},{"x":2.3675004,"y":48.8557572},{"x":2.3676345,"y":48.855762},{"x":2.3676636,"y":48.8557639},{"x":2.3676793,"y":48.8557645},{"x":2.3676749,"y":48.8556986},{"x":2.3676155,"y":48.8556991},{"x":2.3675209,"y":48.8556984}],"location":{"lon":2.367517,"lat":48.8557267,"north":48.8557645,"south":48.8556889,"east":2.3676793,"west":2.3673547,"country":"France","state":"Ile-de-France","place":"Paris","country_adm_id":0,"gadm":null,"city_id":"5009811","city":"Paris","zoom":21},"description":null},{"id":28976222,"language_id":2,"language_iso":"fr","urlhtml":"<a class=\"wikimapia-link\" href=\"http://wikimapia.org/28976222/fr/Passage-Saint-Paul-45\">Passage Saint-Paul, 45</a>","title":null,"tags":null,"wikipedia":null,"is_building":true,"is_region":false,"is_deleted":false,"parent_id":"0","polygon":[{"x":2.3623938,"y":48.8543815},{"x":2.3623748,"y":48.8543609},{"x":2.3623613,"y":48.8543446},{"x":2.3623528,"y":48.8543483},{"x":2.3623369,"y":48.8543306},{"x":2.3623178,"y":48.8543121},{"x":2.3622028,"y":48.8543546},{"x":2.3622326,"y":48.8543886},{"x":2.3622035,"y":48.8543999},{"x":2.36219,"y":48.8543846},{"x":2.3621632,"y":48.854394},{"x":2.3621487,"y":48.8543786},{"x":2.3620583,"y":48.8544127},{"x":2.362082,"y":48.8544369},{"x":2.3620852,"y":48.8544387},{"x":2.3621842,"y":48.8544135},{"x":2.3622119,"y":48.8544324},{"x":2.3622212,"y":48.8544492},{"x":2.3622437,"y":48.8544431},{"x":2.362261,"y":48.8544362}],"location":{"lon":2.362226,"lat":48.8543806,"north":48.8544492,"south":48.8543121,"east":2.3623938,"west":2.3620583,"country":"France","state":"Ile-de-France","place":"Paris","country_adm_id":0,"gadm":null,"city_id":"5009811","city":"Paris","zoom":20},"description":null},{"id":28990464,"language_id":2,"language_iso":"fr","urlhtml":"<a class=\"wikimapia-link\" href=\"http://wikimapia.org/28990464/fr/Rue-Sainte-Croix-de-la-Bretonnerie-42\">Rue Sainte-Croix-de-la-Bretonnerie, 42</a>","title":null,"tags":null,"wikipedia":null,"is_building":true,"is_region":false,"is_deleted":false,"parent_id":"0","polygon":[{"x":2.3546757,"y":48.8587291},{"x":2.3546691,"y":48.8587196},{"x":2.354626,"y":48.8587326},{"x":2.3545746,"y":48.8587487},{"x":2.3546969,"y":48.8589165},{"x":2.354788,"y":48.8588869},{"x":2.3547791,"y":48.8588703}],"location":{"lon":2.3546813,"lat":48.858818,"north":48.8589165,"south":48.8587196,"east":2.354788,"west":2.3545746,"country":"France","state":"Ile-de-France","place":"Paris","country_adm_id":0,"gadm":null,"city_id":"5009811","city":"Paris","zoom":20},"description":null},{"id":28990807,"language_id":0,"language_iso":"en","urlhtml":"<a class=\"wikimapia-link\" href=\"http://wikimapia.org/28990807/Rue-Vieille-du-Temple-49-51\">Rue Vieille-du-Temple, 49,51</a>","title":null,"tags":null,"wikipedia":null,"is_building":true,"is_region":false,"is_deleted":false,"parent_id":"0","polygon":[{"x":2.3581112,"y":48.858366},{"x":2.3581298,"y":48.8583583},{"x":2.3582533,"y":48.8582938},{"x":2.3582239,"y":48.8582676},{"x":2.3581725,"y":48.858224},{"x":2.3581448,"y":48.8582027},{"x":2.3580589,"y":48.8582547},{"x":2.3580761,"y":48.8582691},{"x":2.3580736,"y":48.8582694},{"x":2.3580836,"y":48.8582793},{"x":2.3580692,"y":48.8582863},{"x":2.3580564,"y":48.8582853},{"x":2.3580345,"y":48.8582663},{"x":2.3580102,"y":48.8582828},{"x":2.358038,"y":48.858303}],"location":{"lon":2.3581317,"lat":48.8582843,"north":48.858366,"south":48.8582027,"east":2.3582533,"west":2.3580102,"country":"France","state":"Ile-de-France","place":"Paris","country_adm_id":0,"gadm":null,"city_id":"5009811","city":"Paris","zoom":19},"description":null},{"id":28991148,"language_id":2,"language_iso":"fr","urlhtml":"<a class=\"wikimapia-link\" href=\"http://wikimapia.org/28991148/fr/Rue-des-Rosiers-29\">Rue des Rosiers, 29</a>","title":null,"tags":null,"wikipedia":null,"is_building":true,"is_region":false,"is_deleted":false,"parent_id":"0","polygon":[{"x":2.358165,"y":48.8577287},{"x":2.3582207,"y":48.8577039},{"x":2.358282,"y":48.8576783},{"x":2.358171,"y":48.8575555},{"x":2.3580586,"y":48.8575942}],"location":{"lon":2.3581703,"lat":48.8576421,"north":48.8577287,"south":48.8575555,"east":2.358282,"west":2.3580586,"country":"France","state":"Ile-de-France","place":"Paris","country_adm_id":0,"gadm":null,"city_id":"5009811","city":"Paris","zoom":20},"description":null},{"id":28991156,"language_id":2,"language_iso":"fr","urlhtml":"<a class=\"wikimapia-link\" href=\"http://wikimapia.org/28991156/fr/rue-du-Tr%C3%A9sor-3\">rue du Trésor, 3</a>","title":null,"tags":null,"wikipedia":null,"is_building":true,"is_region":false,"is_deleted":false,"parent_id":"0","polygon":[{"x":2.3581039,"y":48.8568843},{"x":2.3581727,"y":48.8568562},{"x":2.3582719,"y":48.8568118},{"x":2.3582818,"y":48.8568125},{"x":2.358202,"y":48.8567221},{"x":2.358159,"y":48.8567382},{"x":2.3581026,"y":48.8567549},{"x":2.3581257,"y":48.8567809},{"x":2.3580757,"y":48.856801},{"x":2.3580421,"y":48.8568141}],"location":{"lon":2.3581619,"lat":48.8568032,"north":48.8568843,"south":48.8567221,"east":2.3582818,"west":2.3580421,"country":"France","state":"Ile-de-France","place":"Paris","country_adm_id":0,"gadm":null,"city_id":"5009811","city":"Paris","zoom":20},"description":null},{"id":28992111,"language_id":2,"language_iso":"fr","urlhtml":"<a class=\"wikimapia-link\" href=\"http://wikimapia.org/28992111/fr/Rue-Elz%C3%A9vir-5\">Rue Elzévir, 5</a>","title":null,"tags":null,"wikipedia":null,"is_building":true,"is_region":false,"is_deleted":false,"parent_id":"0","polygon":[{"x":2.3613693,"y":48.8582258},{"x":2.3613215,"y":48.8581861},{"x":2.3612793,"y":48.8581505},{"x":2.361268,"y":48.8581564},{"x":2.3611193,"y":48.8582362},{"x":2.3611416,"y":48.8582561},{"x":2.3612062,"y":48.8583099}],"location":{"lon":2.3612443,"lat":48.8582302,"north":48.8583099,"south":48.8581505,"east":2.3613693,"west":2.3611193,"country":"France","state":"Ile-de-France","place":"Paris","country_adm_id":0,"gadm":null,"city_id":"5009811","city":"Paris","zoom":20},"description":null},{"id":28993575,"language_id":2,"language_iso":"fr","urlhtml":"<a class=\"wikimapia-link\" href=\"http://wikimapia.org/28993575/Rue-de-Turenne-28\">Rue de Turenne, 28</a>","title":null,"tags":null,"wikipedia":null,"is_building":true,"is_region":false,"is_deleted":false,"parent_id":"0","polygon":[{"x":2.3645192,"y":48.8567584},{"x":2.3646363,"y":48.8567538},{"x":2.3646376,"y":48.8567609},{"x":2.3646424,"y":48.856807},{"x":2.3646488,"y":48.8568482},{"x":2.3646543,"y":48.8568793},{"x":2.3646571,"y":48.8569119},{"x":2.3645304,"y":48.856915},{"x":2.3645248,"y":48.8568388}],"location":{"lon":2.3645881,"lat":48.8568344,"north":48.856915,"south":48.8567538,"east":2.3646571,"west":2.3645192,"country":"France","state":"Ile-de-France","place":"Paris","country_adm_id":0,"gadm":null,"city_id":"5009811","city":"Paris","zoom":20},"description":null},{"id":28994081,"language_id":0,"language_iso":"en","urlhtml":"<a class=\"wikimapia-link\" href=\"http://wikimapia.org/28994081/Rue-Saint-Sabin-54\">Rue Saint-Sabin, 54</a>","title":null,"tags":[{"id":109,"title":"building"}],"wikipedia":null,"is_building":true,"is_region":false,"is_deleted":false,"parent_id":"0","polygon":[{"x":2.3691807,"y":48.8588823},{"x":2.3691606,"y":48.8589147},{"x":2.369108,"y":48.8589044},{"x":2.3691147,"y":48.8588867},{"x":2.3689387,"y":48.8588481},{"x":2.3689403,"y":48.858847},{"x":2.3689883,"y":48.8587445},{"x":2.3690516,"y":48.8587579},{"x":2.3690392,"y":48.8587819},{"x":2.3690536,"y":48.8587846},{"x":2.3690429,"y":48.858804},{"x":2.3690701,"y":48.8588104},{"x":2.3690788,"y":48.8587921},{"x":2.3691117,"y":48.8588003},{"x":2.3692126,"y":48.8588254},{"x":2.3692002,"y":48.8588475},{"x":2.3691267,"y":48.8588298},{"x":2.369106,"y":48.858864}],"location":{"lon":2.3690756,"lat":48.8588296,"north":48.8589147,"south":48.8587445,"east":2.3692126,"west":2.3689387,"country":"France","state":"Ile-de-France","place":"Paris","country_adm_id":0,"gadm":null,"city_id":"5009811","city":"Paris","zoom":19},"description":null},{"id":28995026,"language_id":0,"language_iso":"en","urlhtml":"<a class=\"wikimapia-link\" href=\"http://wikimapia.org/28995026/Rue-Vieille-du-Temple-116\">Rue Vieille-du-Temple, 116</a>","title":null,"tags":null,"wikipedia":null,"is_building":true,"is_region":false,"is_deleted":false,"parent_id":"0","polygon":[{"x":2.3634037,"y":48.8612877},{"x":2.3634434,"y":48.861312},{"x":2.3634784,"y":48.861331},{"x":2.3635985,"y":48.8612329},{"x":2.3635635,"y":48.8612141},{"x":2.3635342,"y":48.8612438},{"x":2.3635208,"y":48.8612377},{"x":2.3635997,"y":48.8611729},{"x":2.3636058,"y":48.8611588},{"x":2.3636523,"y":48.8611872},{"x":2.3637024,"y":48.8611477},{"x":2.3636948,"y":48.8611411},{"x":2.3636913,"y":48.8611462},{"x":2.3636247,"y":48.8611047}],"location":{"lon":2.363553,"lat":48.8612178,"north":48.861331,"south":48.8611047,"east":2.3637024,"west":2.3634037,"country":"France","state":"Ile-de-France","place":"Paris","country_adm_id":0,"gadm":null,"city_id":"5009811","city":"Paris","zoom":19},"description":null},{"id":29004142,"language_id":2,"language_iso":"fr","urlhtml":"<a class=\"wikimapia-link\" href=\"http://wikimapia.org/29004142/fr/Rue-des-Pr%C3%AAcheurs-3\">Rue des Prêcheurs, 3</a>","title":null,"tags":null,"wikipedia":null,"is_building":true,"is_region":false,"is_deleted":false,"parent_id":"0","polygon":[{"x":2.3488449,"y":48.8619426},{"x":2.3489444,"y":48.8619203},{"x":2.3489743,"y":48.8619124},{"x":2.3489598,"y":48.8618863},{"x":2.3489668,"y":48.8618863},{"x":2.3489705,"y":48.8618866},{"x":2.3489756,"y":48.8618834},{"x":2.3489798,"y":48.8618882},{"x":2.3489776,"y":48.8618911},{"x":2.3489872,"y":48.8619072},{"x":2.3489841,"y":48.8619083},{"x":2.3489886,"y":48.8619104},{"x":2.3491685,"y":48.8618694},{"x":2.3491527,"y":48.8618396},{"x":2.3491404,"y":48.8618167},{"x":2.3488117,"y":48.8618864}],"location":{"lon":2.3489901,"lat":48.8618796,"north":48.8619426,"south":48.8618167,"east":2.3491685,"west":2.3488117,"country":"France","state":"Ile-de-France","place":"Paris","country_adm_id":0,"gadm":null,"city_id":"5009811","city":"Paris","zoom":20},"description":null},{"id":29006161,"language_id":2,"language_iso":"fr","urlhtml":"<a class=\"wikimapia-link\" href=\"http://wikimapia.org/29006161/fr/Le-Week-end\">Le Week-end</a>","title":"Le Week-end","tags":[{"id":108,"title":"café, bar, brasserie"}],"wikipedia":null,"is_building":true,"is_region":false,"is_deleted":false,"parent_id":"0","polygon":[{"x":2.3572436,"y":48.8658198},{"x":2.3571299,"y":48.8657953},{"x":2.3570354,"y":48.8657719},{"x":2.3569907,"y":48.8658054},{"x":2.3570261,"y":48.86586},{"x":2.3570568,"y":48.8659062},{"x":2.3571439,"y":48.8658853},{"x":2.3571301,"y":48.8658672},{"x":2.3571411,"y":48.865861},{"x":2.3571615,"y":48.8658654},{"x":2.3571598,"y":48.8658805},{"x":2.3571952,"y":48.8658694},{"x":2.3572155,"y":48.8658662}],"location":{"lon":2.3571171,"lat":48.865839,"north":48.8659062,"south":48.8657719,"east":2.3572436,"west":2.3569907,"country":"France","state":"Ile-de-France","place":"Paris","country_adm_id":0,"gadm":null,"city_id":"5009811","city":"Paris","zoom":20},"description":null},{"id":29006788,"language_id":2,"language_iso":"fr","urlhtml":"<a class=\"wikimapia-link\" href=\"http://wikimapia.org/29006788/fr/Rue-des-Gravilliers-5\">Rue des Gravilliers, 5</a>","title":null,"tags":null,"wikipedia":null,"is_building":true,"is_region":false,"is_deleted":false,"parent_id":"0","polygon":[{"x":2.3576575,"y":48.8634948},{"x":2.3577245,"y":48.8634758},{"x":2.3577794,"y":48.8634604},{"x":2.3577388,"y":48.8634093},{"x":2.357678,"y":48.8633243},{"x":2.3575628,"y":48.8633615},{"x":2.3575862,"y":48.8633979}],"location":{"lon":2.3576711,"lat":48.8634095,"north":48.8634948,"south":48.8633243,"east":2.3577794,"west":2.3575628,"country":"France","state":"Ile-de-France","place":"Paris","country_adm_id":0,"gadm":null,"city_id":"5009811","city":"Paris","zoom":20},"description":null},{"id":29008620,"language_id":2,"language_iso":"fr","urlhtml":"<a class=\"wikimapia-link\" href=\"http://wikimapia.org/29008620/fr/Rue-de-Saintonge-48\">Rue de Saintonge, 48</a>","title":null,"tags":null,"wikipedia":null,"is_building":true,"is_region":false,"is_deleted":false,"parent_id":"0","polygon":[{"x":2.3639078,"y":48.8629279},{"x":2.3639201,"y":48.862938},{"x":2.3639578,"y":48.8629696},{"x":2.3639734,"y":48.8629841},{"x":2.3641199,"y":48.8629085},{"x":2.3641821,"y":48.8628721},{"x":2.3641075,"y":48.8628179}],"location":{"lon":2.3640449,"lat":48.862901,"north":48.8629841,"south":48.8628179,"east":2.3641821,"west":2.3639078,"country":"France","state":"Ile-de-France","place":"Paris","country_adm_id":0,"gadm":null,"city_id":"5009811","city":"Paris","zoom":19},"description":null},{"id":29009152,"language_id":2,"language_iso":"fr","urlhtml":"<a class=\"wikimapia-link\" href=\"http://wikimapia.org/29009152/fr/Rue-Commines-9\">Rue Commines, 9</a>","title":null,"tags":null,"wikipedia":null,"is_building":true,"is_region":false,"is_deleted":false,"parent_id":"0","polygon":[{"x":2.365695,"y":48.8619997},{"x":2.3656283,"y":48.8619695},{"x":2.3655825,"y":48.8619484},{"x":2.3655274,"y":48.8620166},{"x":2.3655816,"y":48.8620397},{"x":2.3655474,"y":48.8620812},{"x":2.3654888,"y":48.8620564},{"x":2.3654544,"y":48.8620939},{"x":2.3655641,"y":48.8621455}],"location":{"lon":2.3655747,"lat":48.8620469,"north":48.8621455,"south":48.8619484,"east":2.365695,"west":2.3654544,"country":"France","state":"Ile-de-France","place":"Paris","country_adm_id":0,"gadm":null,"city_id":"5009811","city":"Paris","zoom":20},"description":null},{"id":29009282,"language_id":2,"language_iso":"fr","urlhtml":"<a class=\"wikimapia-link\" href=\"http://wikimapia.org/29009282/fr/Rue-du-Pont-aux-Choux-12\">Rue du Pont aux Choux, 12</a>","title":null,"tags":null,"wikipedia":null,"is_building":true,"is_region":false,"is_deleted":false,"parent_id":"0","polygon":[{"x":2.3657917,"y":48.8612061},{"x":2.3657211,"y":48.8612136},{"x":2.3656874,"y":48.8612194},{"x":2.3657003,"y":48.861273},{"x":2.3655985,"y":48.8612888},{"x":2.3656168,"y":48.8613533},{"x":2.3658114,"y":48.8613268},{"x":2.3657936,"y":48.8612653},{"x":2.3658089,"y":48.8612606},{"x":2.365811,"y":48.8612612}],"location":{"lon":2.3657049,"lat":48.8612797,"north":48.8613533,"south":48.8612061,"east":2.3658114,"west":2.3655985,"country":"France","state":"Ile-de-France","place":"Paris","country_adm_id":0,"gadm":null,"city_id":"5009811","city":"Paris","zoom":20},"description":null},{"id":29009317,"language_id":2,"language_iso":"fr","urlhtml":"<a class=\"wikimapia-link\" href=\"http://wikimapia.org/29009317/fr/Rue-du-Pont-aux-Choux-14\">Rue du Pont aux Choux, 14</a>","title":null,"tags":null,"wikipedia":null,"is_building":true,"is_region":false,"is_deleted":false,"parent_id":"0","polygon":[{"x":2.3656846,"y":48.8612182},{"x":2.3656854,"y":48.8612132},{"x":2.3655679,"y":48.8612299},{"x":2.3655014,"y":48.8612386},{"x":2.3655152,"y":48.8612977},{"x":2.3655179,"y":48.8613004},{"x":2.3655465,"y":48.8612962},{"x":2.3655522,"y":48.8613166},{"x":2.3655081,"y":48.8613243},{"x":2.3655008,"y":48.8613012},{"x":2.3654911,"y":48.8613009},{"x":2.3655145,"y":48.8613841},{"x":2.365619,"y":48.8613732},{"x":2.3656156,"y":48.8613527},{"x":2.3655969,"y":48.8612881},{"x":2.3657005,"y":48.861271}],"location":{"lon":2.3655958,"lat":48.8612986,"north":48.8613841,"south":48.8612132,"east":2.3657005,"west":2.3654911,"country":"France","state":"Ile-de-France","place":"Paris","country_adm_id":0,"gadm":null,"city_id":"5009811","city":"Paris","zoom":20},"description":null},{"id":29015978,"language_id":2,"language_iso":"fr","urlhtml":"<a class=\"wikimapia-link\" href=\"http://wikimapia.org/29015978/fr/Rue-d-Aboukir-52\">Rue d'Aboukir, 52</a>","title":null,"tags":null,"wikipedia":null,"is_building":true,"is_region":false,"is_deleted":false,"parent_id":"0","polygon":[{"x":2.3456482,"y":48.8673154},{"x":2.3456994,"y":48.8673291},{"x":2.3457566,"y":48.8673464},{"x":2.3457669,"y":48.8673356},{"x":2.3458594,"y":48.8672008},{"x":2.3457519,"y":48.867168},{"x":2.345737,"y":48.867188}],"location":{"lon":2.3457538,"lat":48.8672572,"north":48.8673464,"south":48.867168,"east":2.3458594,"west":2.3456482,"country":"France","state":"Ile-de-France","place":"Paris","country_adm_id":0,"gadm":null,"city_id":"5009811","city":"Paris","zoom":20},"description":null},{"id":29016695,"language_id":2,"language_iso":"fr","urlhtml":"<a class=\"wikimapia-link\" href=\"http://wikimapia.org/29016695/fr/Rue-R%C3%A9aumur-63\">Rue Réaumur, 63</a>","title":null,"tags":null,"wikipedia":null,"is_building":true,"is_region":false,"is_deleted":false,"parent_id":"0","polygon":[{"x":2.3505286,"y":48.8665179},{"x":2.3505342,"y":48.8665202},{"x":2.3506637,"y":48.8664939},{"x":2.3508222,"y":48.866463},{"x":2.3508404,"y":48.8664607},{"x":2.3509249,"y":48.8664454},{"x":2.3509788,"y":48.8664355},{"x":2.3509821,"y":48.8664337},{"x":2.3509811,"y":48.8664286},{"x":2.3509738,"y":48.866416},{"x":2.3509623,"y":48.8663964},{"x":2.3509613,"y":48.8663936},{"x":2.3505144,"y":48.8664805}],"location":{"lon":2.3507482,"lat":48.8664569,"north":48.8665202,"south":48.8663936,"east":2.3509821,"west":2.3505144,"country":"France","state":"Ile-de-France","place":"Paris","country_adm_id":0,"gadm":null,"city_id":"5009811","city":"Paris","zoom":20},"description":null},{"id":29017274,"language_id":2,"language_iso":"fr","urlhtml":"<a class=\"wikimapia-link\" href=\"http://wikimapia.org/29017274/fr/Rue-d-Aboukir-126\">Rue d'Aboukir, 126</a>","title":null,"tags":null,"wikipedia":null,"is_building":true,"is_region":false,"is_deleted":false,"parent_id":"0","polygon":[{"x":2.3511758,"y":48.8689658},{"x":2.3512778,"y":48.8688},{"x":2.3512197,"y":48.8687846},{"x":2.3511753,"y":48.8687736},{"x":2.3510753,"y":48.8689348},{"x":2.3511282,"y":48.8689507}],"location":{"lon":2.3511765,"lat":48.8688697,"north":48.8689658,"south":48.8687736,"east":2.3512778,"west":2.3510753,"country":"France","state":"Ile-de-France","place":"Paris","country_adm_id":0,"gadm":null,"city_id":"5009811","city":"Paris","zoom":20},"description":null},{"id":29017840,"language_id":2,"language_iso":"fr","urlhtml":"<a class=\"wikimapia-link\" href=\"http://wikimapia.org/29017840/fr/Rue-Blondel-7\">Rue Blondel, 7</a>","title":null,"tags":null,"wikipedia":null,"is_building":true,"is_region":false,"is_deleted":false,"parent_id":"0","polygon":[{"x":2.3542457,"y":48.8685625},{"x":2.3543238,"y":48.8685497},{"x":2.3543942,"y":48.8685387},{"x":2.3543241,"y":48.8684059},{"x":2.3542663,"y":48.8684194},{"x":2.3541935,"y":48.8684327},{"x":2.3542103,"y":48.8684651}],"location":{"lon":2.3542938,"lat":48.8684842,"north":48.8685625,"south":48.8684059,"east":2.3543942,"west":2.3541935,"country":"France","state":"Ile-de-France","place":"Paris","country_adm_id":0,"gadm":null,"city_id":"5009811","city":"Paris","zoom":20},"description":null},{"id":29018304,"language_id":2,"language_iso":"fr","urlhtml":"<a class=\"wikimapia-link\" href=\"http://wikimapia.org/29018304/fr/Rue-du-Vertbois-22\">Rue du Vertbois, 22</a>","title":null,"tags":null,"wikipedia":null,"is_building":true,"is_region":false,"is_deleted":false,"parent_id":"0","polygon":[{"x":2.3588975,"y":48.8668422},{"x":2.3588319,"y":48.8668582},{"x":2.3587699,"y":48.8668691},{"x":2.3588295,"y":48.8669736},{"x":2.3588495,"y":48.8670035},{"x":2.3589091,"y":48.8669917},{"x":2.3589768,"y":48.8669797}],"location":{"lon":2.3588733,"lat":48.8669228,"north":48.8670035,"south":48.8668422,"east":2.3589768,"west":2.3587699,"country":"France","state":"Ile-de-France","place":"Paris","country_adm_id":0,"gadm":null,"city_id":"5009811","city":"Paris","zoom":20},"description":null},{"id":29018679,"language_id":2,"language_iso":"fr","urlhtml":"<a class=\"wikimapia-link\" href=\"http://wikimapia.org/29018679/fr/Boulevard-Saint-Martin-35\">Boulevard Saint-Martin, 35</a>","title":null,"tags":null,"wikipedia":null,"is_building":true,"is_region":false,"is_deleted":false,"parent_id":"0","polygon":[{"x":2.3563101,"y":48.8705042},{"x":2.3562162,"y":48.870527},{"x":2.3560204,"y":48.8705664},{"x":2.3559863,"y":48.8705089},{"x":2.3562742,"y":48.8704476},{"x":2.3562783,"y":48.8704482},{"x":2.3562958,"y":48.8704784}],"location":{"lon":2.3561482,"lat":48.870507,"north":48.8705664,"south":48.8704476,"east":2.3563101,"west":2.3559863,"country":"France","state":"Ile-de-France","place":"Paris","country_adm_id":0,"gadm":null,"city_id":"5009811","city":"Paris","zoom":20},"description":null},{"id":29018964,"language_id":2,"language_iso":"fr","urlhtml":"<a class=\"wikimapia-link\" href=\"http://wikimapia.org/29018964/fr/Rue-de-Mazagran-16\">Rue de Mazagran, 16</a>","title":null,"tags":null,"wikipedia":null,"is_building":true,"is_region":false,"is_deleted":false,"parent_id":"0","polygon":[{"x":2.3520941,"y":48.8707516},{"x":2.3519629,"y":48.8707855},{"x":2.3519041,"y":48.870737},{"x":2.3518484,"y":48.8706912},{"x":2.351912,"y":48.8706587},{"x":2.3519217,"y":48.8706677},{"x":2.3520439,"y":48.8706513},{"x":2.3520625,"y":48.8706931},{"x":2.3520265,"y":48.8706994},{"x":2.3520339,"y":48.8707163},{"x":2.3520718,"y":48.8707098}],"location":{"lon":2.3519712,"lat":48.8707184,"north":48.8707855,"south":48.8706513,"east":2.3520941,"west":2.3518484,"country":"France","state":"Ile-de-France","place":"Paris","country_adm_id":0,"gadm":null,"city_id":"5009811","city":"Paris","zoom":20},"description":null},{"id":29019655,"language_id":2,"language_iso":"fr","urlhtml":"<a class=\"wikimapia-link\" href=\"http://wikimapia.org/29019655/fr/Rue-du-Caire-82\">Rue du Caire, 82</a>","title":null,"tags":null,"wikipedia":null,"is_building":true,"is_region":false,"is_deleted":false,"parent_id":"0","polygon":[{"x":2.3493139,"y":48.8682002},{"x":2.3493638,"y":48.8682147},{"x":2.3494152,"y":48.8682271},{"x":2.3494652,"y":48.8682432},{"x":2.3495306,"y":48.8682614},{"x":2.3495628,"y":48.8682699},{"x":2.3496044,"y":48.8682037},{"x":2.3494921,"y":48.8681739},{"x":2.3494722,"y":48.8681398},{"x":2.3493943,"y":48.8681571},{"x":2.3493899,"y":48.8681487},{"x":2.3493403,"y":48.8681622}],"location":{"lon":2.3494591,"lat":48.8682048,"north":48.8682699,"south":48.8681398,"east":2.3496044,"west":2.3493139,"country":"France","state":"Ile-de-France","place":"Paris","country_adm_id":0,"gadm":null,"city_id":"5009811","city":"Paris","zoom":20},"description":null},{"id":29019788,"language_id":2,"language_iso":"fr","urlhtml":"<a class=\"wikimapia-link\" href=\"http://wikimapia.org/29019788/fr/Rue-du-Ch%C3%A2teau-d-Eau-37\">Rue du Château d'Eau, 37</a>","title":null,"tags":null,"wikipedia":null,"is_building":true,"is_region":false,"is_deleted":false,"parent_id":"0","polygon":[{"x":2.3578378,"y":48.8713301},{"x":2.3578161,"y":48.871309},{"x":2.3577262,"y":48.8711688},{"x":2.3578195,"y":48.871142},{"x":2.3578389,"y":48.8711342},{"x":2.3578496,"y":48.8711467},{"x":2.3578568,"y":48.8711607},{"x":2.357813,"y":48.871174},{"x":2.3578134,"y":48.8711811},{"x":2.3578119,"y":48.8711844},{"x":2.3578067,"y":48.8711873},{"x":2.3578001,"y":48.8711907},{"x":2.3578176,"y":48.8712102},{"x":2.3578775,"y":48.8711917},{"x":2.3578841,"y":48.8711955},{"x":2.3579007,"y":48.8712227},{"x":2.3579511,"y":48.8712685},{"x":2.3578878,"y":48.8713018}],"location":{"lon":2.3578386,"lat":48.8712321,"north":48.8713301,"south":48.8711342,"east":2.3579511,"west":2.3577262,"country":"France","state":"Ile-de-France","place":"Paris","country_adm_id":0,"gadm":null,"city_id":"5009811","city":"Paris","zoom":20},"description":null},{"id":29020141,"language_id":2,"language_iso":"fr","urlhtml":"<a class=\"wikimapia-link\" href=\"http://wikimapia.org/29020141/fr/Boulevard-Magenta-14\">Boulevard Magenta, 14</a>","title":null,"tags":null,"wikipedia":null,"is_building":true,"is_region":false,"is_deleted":false,"parent_id":"0","polygon":[{"x":2.3625459,"y":48.8698909},{"x":2.3621839,"y":48.8697008},{"x":2.3621957,"y":48.8696905},{"x":2.3622229,"y":48.8696563},{"x":2.362359,"y":48.8697334},{"x":2.3623435,"y":48.8697495},{"x":2.3623473,"y":48.8697624},{"x":2.3623771,"y":48.8697773},{"x":2.3623832,"y":48.8697719},{"x":2.3623944,"y":48.8697742},{"x":2.36241,"y":48.8697621},{"x":2.3625846,"y":48.8698624},{"x":2.3625646,"y":48.8698801}],"location":{"lon":2.3623842,"lat":48.8697736,"north":48.8698909,"south":48.8696563,"east":2.3625846,"west":2.3621839,"country":"France","state":"Ile-de-France","place":"Paris","country_adm_id":0,"gadm":null,"city_id":"5009811","city":"Paris","zoom":19},"description":null},{"id":29020437,"language_id":2,"language_iso":"fr","urlhtml":"<a class=\"wikimapia-link\" href=\"http://wikimapia.org/29020437/fr/Rue-Beaurepaire-14\">Rue Beaurepaire, 14</a>","title":null,"tags":null,"wikipedia":null,"is_building":true,"is_region":false,"is_deleted":false,"parent_id":"0","polygon":[{"x":2.3639741,"y":48.8702082},{"x":2.3638698,"y":48.8702286},{"x":2.3638477,"y":48.8701761},{"x":2.363824,"y":48.8701195},{"x":2.3639137,"y":48.8700792},{"x":2.3639762,"y":48.870112},{"x":2.3640455,"y":48.8701457},{"x":2.3639854,"y":48.870199},{"x":2.3639744,"y":48.870179},{"x":2.3639655,"y":48.870186}],"location":{"lon":2.3639347,"lat":48.8701539,"north":48.8702286,"south":48.8700792,"east":2.3640455,"west":2.363824,"country":"France","state":"Ile-de-France","place":"Paris","country_adm_id":0,"gadm":null,"city_id":"5009811","city":"Paris","zoom":20},"description":null},{"id":29027354,"language_id":2,"language_iso":"fr","urlhtml":"<a class=\"wikimapia-link\" href=\"http://wikimapia.org/29027354/fr/Rue-de-l-%C3%89chiquier-44\">Rue de l'Échiquier, 44</a>","title":null,"tags":null,"wikipedia":null,"is_building":true,"is_region":false,"is_deleted":false,"parent_id":"0","polygon":[{"x":2.3486738,"y":48.8720946},{"x":2.3485585,"y":48.8721151},{"x":2.3484736,"y":48.8719287},{"x":2.3485369,"y":48.8719207},{"x":2.3485922,"y":48.8719084},{"x":2.3486382,"y":48.8720172},{"x":2.3486059,"y":48.8720237},{"x":2.3485953,"y":48.8719991},{"x":2.3485948,"y":48.8719976},{"x":2.3485421,"y":48.8720052},{"x":2.3485679,"y":48.872057},{"x":2.3486523,"y":48.872044}],"location":{"lon":2.3485737,"lat":48.8720117,"north":48.8721151,"south":48.8719084,"east":2.3486738,"west":2.3484736,"country":"France","state":"Ile-de-France","place":"Paris","country_adm_id":0,"gadm":null,"city_id":"5009811","city":"Paris","zoom":20},"description":null},{"id":29027870,"language_id":2,"language_iso":"fr","urlhtml":"<a class=\"wikimapia-link\" href=\"http://wikimapia.org/29027870/fr/Rue-des-Petites-Ecuries-19\">Rue des Petites Ecuries, 19</a>","title":null,"tags":null,"wikipedia":null,"is_building":true,"is_region":false,"is_deleted":false,"parent_id":"0","polygon":[{"x":2.3518044,"y":48.8722708},{"x":2.3518134,"y":48.8722857},{"x":2.351778,"y":48.8722939},{"x":2.3517859,"y":48.8723085},{"x":2.3518204,"y":48.8723006},{"x":2.3518705,"y":48.8723825},{"x":2.3517474,"y":48.8724154},{"x":2.3517183,"y":48.8724217},{"x":2.3516781,"y":48.8723593},{"x":2.3516469,"y":48.8723088},{"x":2.351762,"y":48.8722811}],"location":{"lon":2.3517587,"lat":48.8723462,"north":48.8724217,"south":48.8722708,"east":2.3518705,"west":2.3516469,"country":"France","state":"Ile-de-France","place":"Paris","country_adm_id":0,"gadm":null,"city_id":"5009811","city":"Paris","zoom":20},"description":null},{"id":29027919,"language_id":2,"language_iso":"fr","urlhtml":"<a class=\"wikimapia-link\" href=\"http://wikimapia.org/29027919/fr/Rue-du-Faubourg-Saint-Denis-44\">Rue du Faubourg Saint-Denis, 44</a>","title":null,"tags":null,"wikipedia":null,"is_building":true,"is_region":false,"is_deleted":false,"parent_id":"0","polygon":[{"x":2.3538862,"y":48.8714843},{"x":2.3537474,"y":48.8715177},{"x":2.3537384,"y":48.8715193},{"x":2.3537288,"y":48.8715042},{"x":2.3537163,"y":48.871483},{"x":2.3538694,"y":48.8714464},{"x":2.3540154,"y":48.8714119},{"x":2.3541501,"y":48.8713782},{"x":2.3541689,"y":48.8713742},{"x":2.3542123,"y":48.8713631},{"x":2.3542162,"y":48.8713621},{"x":2.3542326,"y":48.8713855},{"x":2.3542411,"y":48.8713812},{"x":2.354225,"y":48.8713586},{"x":2.3542653,"y":48.8713548},{"x":2.35429,"y":48.8713891},{"x":2.3542407,"y":48.8714006},{"x":2.3540514,"y":48.8714483},{"x":2.3540396,"y":48.871427},{"x":2.3540419,"y":48.8714273},{"x":2.3540361,"y":48.8714173},{"x":2.3540039,"y":48.8714246},{"x":2.3540082,"y":48.8714335},{"x":2.3538735,"y":48.8714644}],"location":{"lon":2.3540031,"lat":48.871437,"north":48.8715193,"south":48.8713548,"east":2.35429,"west":2.3537163,"country":"France","state":"Ile-de-France","place":"Paris","country_adm_id":0,"gadm":null,"city_id":"5009811","city":"Paris","zoom":19},"description":null},{"id":29029677,"language_id":2,"language_iso":"fr","urlhtml":"<a class=\"wikimapia-link\" href=\"http://wikimapia.org/29029677/fr/Rue-Arthur-Groussier-12\">Rue Arthur Groussier, 12</a>","title":null,"tags":null,"wikipedia":null,"is_building":true,"is_region":false,"is_deleted":false,"parent_id":"0","polygon":[{"x":2.3707305,"y":48.8719457},{"x":2.3708064,"y":48.8718454},{"x":2.370852,"y":48.8718583},{"x":2.3708281,"y":48.8718907},{"x":2.3708925,"y":48.8719111},{"x":2.3709159,"y":48.8718784},{"x":2.3709551,"y":48.8718898},{"x":2.3709359,"y":48.8719169},{"x":2.3708738,"y":48.8720125},{"x":2.3708021,"y":48.8719869},{"x":2.3707187,"y":48.8719629}],"location":{"lon":2.3708369,"lat":48.8719289,"north":48.8720125,"south":48.8718454,"east":2.3709551,"west":2.3707187,"country":"France","state":"Ile-de-France","place":"Le Pre-Saint-Gervais","country_adm_id":0,"gadm":null,"city_id":"5009811","city":"Paris","zoom":19},"description":null},{"id":32443249,"language_id":0,"language_iso":"en","urlhtml":"<a class=\"wikimapia-link\" href=\"http://wikimapia.org/32443249/Rue-Saint-Denis-85-87\">Rue Saint-Denis, 85, 87</a>","title":null,"tags":[{"id":109,"title":"building"}],"wikipedia":null,"is_building":true,"is_region":false,"is_deleted":false,"parent_id":"0","polygon":[{"x":2.3490136,"y":48.8619629},{"x":2.349205,"y":48.8619175},{"x":2.3492533,"y":48.8620077},{"x":2.3490612,"y":48.8620516}],"location":{"lon":2.3491334,"lat":48.8619845,"north":48.8620516,"south":48.8619175,"east":2.3492533,"west":2.3490136,"country":"France","state":"Ile-de-France","place":"Paris","country_adm_id":0,"gadm":null,"city_id":"5009811","city":"Paris","zoom":20},"description":null},{"id":21040018,"language_id":2,"language_iso":"fr","urlhtml":"<a class=\"wikimapia-link\" href=\"http://wikimapia.org/21040018/fr/Shopi\">Shopi</a>","title":"Shopi","tags":[{"id":682,"title":"épicerie, superette"},{"id":33119,"title":"dépanneur, épicerie de quartier"}],"wikipedia":"","is_building":true,"is_region":false,"is_deleted":false,"parent_id":"0","polygon":[{"x":2.3542097,"y":48.8649371},{"x":2.3543653,"y":48.8649706},{"x":2.3544914,"y":48.8649406},{"x":2.3544618,"y":48.8648753},{"x":2.354376,"y":48.8648877},{"x":2.354266,"y":48.8648665}],"location":{"lon":2.3543505,"lat":48.8649185,"north":48.8649706,"south":48.8648665,"east":2.3544914,"west":2.3542097,"country":"France","state":"Ile-de-France","place":"Paris","country_adm_id":101071,"gadm":[{"id":"74","country":"74","level":"0","is_last_level":"0","name":"France","iso":null,"type":null,"translation":"France"},{"id":"1000","country":"0","level":"0","is_last_level":"0","name":"World","iso":null,"type":null,"translation":"Monde "},{"id":"60533","country":"74","level":"1","is_last_level":"0","name":"Île-de-France","iso":null,"type":null,"translation":null},{"id":"83881","country":"74","level":"2","is_last_level":"0","name":"Paris","iso":null,"type":null,"translation":"Paris"},{"id":"101069","country":"74","level":"3","is_last_level":"0","name":"Paris, 3e arrondissement","iso":null,"type":null,"translation":null},{"id":"101070","country":"74","level":"4","is_last_level":"0","name":"Paris, 3e arrondissement","iso":null,"type":null,"translation":null}],"city_id":"5009811","city":"Paris","zoom":20},"description":""},{"id":28976887,"language_id":2,"language_iso":"fr","urlhtml":"<a class=\"wikimapia-link\" href=\"http://wikimapia.org/28976887/fr/Rue-du-Pas-de-la-Mule-6\">Rue du Pas de la Mule, 6</a>","title":null,"tags":null,"wikipedia":null,"is_building":true,"is_region":false,"is_deleted":false,"parent_id":"0","polygon":[{"x":2.367002,"y":48.8560518},{"x":2.3670932,"y":48.8560359},{"x":2.3671994,"y":48.8560206},{"x":2.3672289,"y":48.8560353},{"x":2.3672306,"y":48.8560631},{"x":2.3672321,"y":48.8561194},{"x":2.3671249,"y":48.8561225},{"x":2.3671259,"y":48.8561152},{"x":2.3671376,"y":48.8561149},{"x":2.367131,"y":48.8560991},{"x":2.3670911,"y":48.8561079},{"x":2.3670924,"y":48.8561104},{"x":2.3670812,"y":48.8561191},{"x":2.3670142,"y":48.856132},{"x":2.3670102,"y":48.8561207},{"x":2.3670034,"y":48.8561068},{"x":2.3670022,"y":48.8560905},{"x":2.367014,"y":48.8560883}],"location":{"lon":2.367117,"lat":48.8560763,"north":48.856132,"south":48.8560206,"east":2.3672321,"west":2.367002,"country":"France","state":"Ile-de-France","place":"Paris","country_adm_id":0,"gadm":null,"city_id":"5009811","city":"Paris","zoom":20},"description":null},{"id":28990307,"language_id":2,"language_iso":"fr","urlhtml":"<a class=\"wikimapia-link\" href=\"http://wikimapia.org/28990307/fr/Rue-de-la-Verrerie-48\">Rue de la Verrerie, 48</a>","title":null,"tags":null,"wikipedia":null,"is_building":true,"is_region":false,"is_deleted":false,"parent_id":"0","polygon":[{"x":2.3527812,"y":48.858091},{"x":2.3527301,"y":48.8581104},{"x":2.3526795,"y":48.8581273},{"x":2.3528435,"y":48.858283},{"x":2.3529347,"y":48.8582419},{"x":2.3528758,"y":48.8581856},{"x":2.3528707,"y":48.8581797},{"x":2.352834,"y":48.8581942},{"x":2.3527965,"y":48.8581574},{"x":2.3528316,"y":48.8581417}],"location":{"lon":2.3528071,"lat":48.858187,"north":48.858283,"south":48.858091,"east":2.3529347,"west":2.3526795,"country":"France","state":"Ile-de-France","place":"Paris","country_adm_id":0,"gadm":null,"city_id":"5009811","city":"Paris","zoom":19},"description":null},{"id":28990997,"language_id":0,"language_iso":"en","urlhtml":"<a class=\"wikimapia-link\" href=\"http://wikimapia.org/28990997/Rue-Vieille-du-Temple-32\">Rue Vieille-du-Temple, 32</a>","title":null,"tags":[{"id":109,"title":"building"}],"wikipedia":null,"is_building":true,"is_region":false,"is_deleted":false,"parent_id":"0","polygon":[{"x":2.3575939,"y":48.8574708},{"x":2.357621,"y":48.8575023},{"x":2.3576468,"y":48.8575363},{"x":2.3578842,"y":48.8574516},{"x":2.3578466,"y":48.8574085},{"x":2.3578245,"y":48.8574163},{"x":2.3578061,"y":48.8573947},{"x":2.3577521,"y":48.8574143}],"location":{"lon":2.357739,"lat":48.8574655,"north":48.8575363,"south":48.8573947,"east":2.3578842,"west":2.3575939,"country":"France","state":"Ile-de-France","place":"Paris","country_adm_id":0,"gadm":null,"city_id":"5009811","city":"Paris","zoom":20},"description":null},{"id":28991521,"language_id":2,"language_iso":"fr","urlhtml":"<a class=\"wikimapia-link\" href=\"http://wikimapia.org/28991521/fr/Rue-des-Archives-43\">Rue des Archives, 43</a>","title":null,"tags":null,"wikipedia":null,"is_building":true,"is_region":false,"is_deleted":false,"parent_id":"0","polygon":[{"x":2.3569622,"y":48.8601612},{"x":2.3569105,"y":48.8601501},{"x":2.3568484,"y":48.86014},{"x":2.3567672,"y":48.8601661},{"x":2.3566954,"y":48.8601898},{"x":2.3567251,"y":48.8602301},{"x":2.3567664,"y":48.8602574},{"x":2.3567997,"y":48.8602816}],"location":{"lon":2.3568288,"lat":48.8602108,"north":48.8602816,"south":48.86014,"east":2.3569622,"west":2.3566954,"country":"France","state":"Ile-de-France","place":"Paris","country_adm_id":0,"gadm":null,"city_id":"5009811","city":"Paris","zoom":20},"description":null},{"id":28992784,"language_id":2,"language_iso":"fr","urlhtml":"<a class=\"wikimapia-link\" href=\"http://wikimapia.org/28992784/fr/Rue-Sainte-Anastase-9\">Rue Sainte-Anastase, 9</a>","title":null,"tags":null,"wikipedia":null,"is_building":true,"is_region":false,"is_deleted":false,"parent_id":"0","polygon":[{"x":2.3634651,"y":48.8596789},{"x":2.3635407,"y":48.8596558},{"x":2.3636622,"y":48.8596226},{"x":2.3636165,"y":48.8595552},{"x":2.3634729,"y":48.8595967},{"x":2.3634362,"y":48.8595421},{"x":2.3634247,"y":48.8595456},{"x":2.3634027,"y":48.8595543},{"x":2.363385,"y":48.8595587},{"x":2.3633977,"y":48.8595768}],"location":{"lon":2.3635236,"lat":48.8596105,"north":48.8596789,"south":48.8595421,"east":2.3636622,"west":2.363385,"country":"France","state":"Ile-de-France","place":"Paris","country_adm_id":0,"gadm":null,"city_id":"5009811","city":"Paris","zoom":20},"description":null},{"id":28992800,"language_id":2,"language_iso":"fr","urlhtml":"<a class=\"wikimapia-link\" href=\"http://wikimapia.org/28992800/fr/Rue-Sainte-Anastase-13\">Rue Sainte-Anastase, 13</a>","title":null,"tags":null,"wikipedia":null,"is_building":true,"is_region":false,"is_deleted":false,"parent_id":"0","polygon":[{"x":2.3631788,"y":48.8597622},{"x":2.363259,"y":48.8597392},{"x":2.3633563,"y":48.8597122},{"x":2.3632966,"y":48.8596244},{"x":2.3632368,"y":48.8596395},{"x":2.3632406,"y":48.859645},{"x":2.3631644,"y":48.8596633},{"x":2.3631543,"y":48.8596491},{"x":2.3631097,"y":48.8596628},{"x":2.3631105,"y":48.8596661}],"location":{"lon":2.363233,"lat":48.8596933,"north":48.8597622,"south":48.8596244,"east":2.3633563,"west":2.3631097,"country":"France","state":"Ile-de-France","place":"Paris","country_adm_id":0,"gadm":null,"city_id":"5009811","city":"Paris","zoom":20},"description":null},{"id":28993064,"language_id":2,"language_iso":"fr","urlhtml":"<a class=\"wikimapia-link\" href=\"http://wikimapia.org/28993064/fr/Rue-du-Pont-aux-Choux-3\">Rue du Pont aux Choux, 3</a>","title":null,"tags":null,"wikipedia":null,"is_building":true,"is_region":false,"is_deleted":false,"parent_id":"0","polygon":[{"x":2.3665032,"y":48.861009},{"x":2.3665874,"y":48.8609967},{"x":2.3666678,"y":48.860985},{"x":2.3666348,"y":48.8608589},{"x":2.3666043,"y":48.8608617},{"x":2.3666112,"y":48.8608882},{"x":2.3664997,"y":48.8609044},{"x":2.366489,"y":48.860875},{"x":2.3664636,"y":48.8608815}],"location":{"lon":2.3665657,"lat":48.8609339,"north":48.861009,"south":48.8608589,"east":2.3666678,"west":2.3664636,"country":"France","state":"Ile-de-France","place":"Paris","country_adm_id":0,"gadm":null,"city_id":"5009811","city":"Paris","zoom":20},"description":null},{"id":28994971,"language_id":0,"language_iso":"en","urlhtml":"<a class=\"wikimapia-link\" href=\"http://wikimapia.org/28994971/Rue-Vieille-du-Temple-114\">Rue Vieille-du-Temple, 114</a>","title":null,"tags":null,"wikipedia":null,"is_building":true,"is_region":false,"is_deleted":false,"parent_id":"0","polygon":[{"x":2.3633298,"y":48.8612508},{"x":2.3633701,"y":48.8612711},{"x":2.3634011,"y":48.8612881},{"x":2.363626,"y":48.8611083},{"x":2.3635503,"y":48.8610679},{"x":2.3634865,"y":48.8611219},{"x":2.3635253,"y":48.8611443},{"x":2.3634677,"y":48.8611904},{"x":2.3634293,"y":48.8611663}],"location":{"lon":2.3634779,"lat":48.861178,"north":48.8612881,"south":48.8610679,"east":2.363626,"west":2.3633298,"country":"France","state":"Ile-de-France","place":"Paris","country_adm_id":0,"gadm":null,"city_id":"5009811","city":"Paris","zoom":19},"description":null},{"id":29004677,"language_id":0,"language_iso":"en","urlhtml":"<a class=\"wikimapia-link\" href=\"http://wikimapia.org/29004677/Rue-Tiquetonne-38\">Rue Tiquetonne, 38</a>","title":null,"tags":null,"wikipedia":null,"is_building":true,"is_region":false,"is_deleted":false,"parent_id":"0","polygon":[{"x":2.3479081,"y":48.8647583},{"x":2.3478399,"y":48.8647627},{"x":2.3477709,"y":48.8647681},{"x":2.3478,"y":48.8649094},{"x":2.3478884,"y":48.8649033},{"x":2.3479289,"y":48.8648981},{"x":2.3479237,"y":48.8648747},{"x":2.3479208,"y":48.8648425}],"location":{"lon":2.3478499,"lat":48.8648338,"north":48.8649094,"south":48.8647583,"east":2.3479289,"west":2.3477709,"country":"France","state":"Ile-de-France","place":"Paris","country_adm_id":0,"gadm":null,"city_id":"5009811","city":"Paris","zoom":20},"description":null},{"id":29004991,"language_id":2,"language_iso":"fr","urlhtml":"<a class=\"wikimapia-link\" href=\"http://wikimapia.org/29004991/fr/Rue-Tiquetonne-18\">Rue Tiquetonne, 18</a>","title":null,"tags":null,"wikipedia":null,"is_building":true,"is_region":false,"is_deleted":false,"parent_id":"0","polygon":[{"x":2.3491486,"y":48.8645554},{"x":2.349093,"y":48.8645651},{"x":2.3490324,"y":48.8645788},{"x":2.349104,"y":48.8647308},{"x":2.3491559,"y":48.8647221},{"x":2.3492143,"y":48.8647107}],"location":{"lon":2.3491233,"lat":48.8646431,"north":48.8647308,"south":48.8645554,"east":2.3492143,"west":2.3490324,"country":"France","state":"Ile-de-France","place":"Paris","country_adm_id":0,"gadm":null,"city_id":"5009811","city":"Paris","zoom":20},"description":null},{"id":29005105,"language_id":2,"language_iso":"fr","urlhtml":"<a class=\"wikimapia-link\" href=\"http://wikimapia.org/29005105/fr/Rue-Turbigo-22\">Rue Turbigo, 22</a>","title":null,"tags":null,"wikipedia":null,"is_building":true,"is_region":false,"is_deleted":false,"parent_id":"0","polygon":[{"x":2.3507091,"y":48.8641321},{"x":2.3507863,"y":48.864148},{"x":2.3508032,"y":48.8641536},{"x":2.3508742,"y":48.8641694},{"x":2.3508779,"y":48.8641699},{"x":2.3509025,"y":48.8641299},{"x":2.3509019,"y":48.8641276},{"x":2.3508834,"y":48.864024},{"x":2.3508776,"y":48.8640248},{"x":2.3508158,"y":48.8640368},{"x":2.3507576,"y":48.8640406}],"location":{"lon":2.3508058,"lat":48.8640969,"north":48.8641699,"south":48.864024,"east":2.3509025,"west":2.3507091,"country":"France","state":"Ile-de-France","place":"Paris","country_adm_id":0,"gadm":null,"city_id":"5009811","city":"Paris","zoom":20},"description":null}]