[{"id":28959323,"language_id":2,"language_iso":"fr","urlhtml":"<a class=\"wikimapia-link\" href=\"http://wikimapia.org/28959323/fr/Indonesia\">Indonesia</a>","title":"Indonesia","tags":[{"id":74,"title":"restaurant, restauration"}],"wikipedia":null,"is_building":true,"is_region":false,"is_deleted":false,"parent_id":"0","polygon":[{"x":2.339627,"y":48.8491956},{"x":2.3395797,"y":48.8491977},{"x":2.3395655,"y":48.8490818},{"x":2.3395888,"y":48.8490785},{"x":2.3396426,"y":48.8490699},{"x":2.3396433,"y":48.8490754},{"x":2.3396592,"y":48.8491928}],"location":{"lon":2.3396123,"lat":48.8491338,"north":48.8491977,"south":48.8490699,"east":2.3396592,"west":2.3395655,"country":"France","state":"Ile-de-France","place":"Paris","country_adm_id":0,"gadm":null,"city_id":"5009811","city":"Paris","zoom":21},"description":null},{"id":28959631,"language_id":2,"language_iso":"fr","urlhtml":"<a class=\"wikimapia-link\" href=\"http://wikimapia.org/28959631/fr/Rue-Monsieur-le-Prince-21\">Rue Monsieur le Prince, 21</a>","title":null,"tags":null,"wikipedia":null,"is_building":true,"is_region":false,"is_deleted":false,"parent_id":"0","polygon":[{"x":2.3396675,"y":48.8511401},{"x":2.3396391,"y":48.8511746},{"x":2.3394981,"y":48.8511202},{"x":2.3395097,"y":48.8510999},{"x":2.3395342,"y":48.8510563},{"x":2.3395465,"y":48.8510551},{"x":2.3396314,"y":48.8511151}],"location":{"lon":2.3395828,"lat":48.8511148,"north":48.8511746,"south":48.8510551,"east":2.3396675,"west":2.3394981,"country":"France","state":"Ile-de-France","place":"Paris","country_adm_id":0,"gadm":null,"city_id":"5009811","city":"Paris","zoom":20},"description":null},{"id":28968181,"language_id":2,"language_iso":"fr","urlhtml":"<a class=\"wikimapia-link\" href=\"http://wikimapia.org/28968181/fr/Rue-de-la-Chaise-4\">Rue de la Chaise, 4</a>","title":null,"tags":null,"wikipedia":null,"is_building":true,"is_region":false,"is_deleted":false,"parent_id":"0","polygon":[{"x":2.3271363,"y":48.8537695},{"x":2.3271238,"y":48.8537481},{"x":2.3271081,"y":48.8537122},{"x":2.327249,"y":48.8536886},{"x":2.3272586,"y":48.8537172},{"x":2.327269,"y":48.8537487},{"x":2.3271433,"y":48.8537816}],"location":{"lon":2.3271885,"lat":48.8537351,"north":48.8537816,"south":48.8536886,"east":2.327269,"west":2.3271081,"country":"France","state":"Ile-de-France","place":"Paris","country_adm_id":0,"gadm":null,"city_id":"5009811","city":"Paris","zoom":20},"description":null},{"id":4963676,"language_id":0,"language_iso":"en","urlhtml":"<a class=\"wikimapia-link\" href=\"http://wikimapia.org/4963676/Starbucks\">Starbucks</a>","title":"Starbucks","tags":[{"id":217,"title":"bank"}],"wikipedia":null,"is_building":true,"is_region":false,"is_deleted":false,"parent_id":"0","polygon":[{"x":2.3427862,"y":48.8512148},{"x":2.3427433,"y":48.8511195},{"x":2.3428398,"y":48.8511054},{"x":2.3428775,"y":48.851194}],"location":{"lon":2.3428104,"lat":48.8511601,"north":48.8512148,"south":48.8511054,"east":2.3428775,"west":2.3427433,"country":"France","state":"Ile-de-France","place":"Paris","country_adm_id":101074,"gadm":[{"id":"74","country":"74","level":"0","is_last_level":"0","name":"France","iso":null,"type":null,"translation":"France"},{"id":"1000","country":"0","level":"0","is_last_level":"0","name":"World","iso":null,"type":null,"translation":"World"},{"id":"60533","country":"74","level":"1","is_last_level":"0","name":"Île-de-France","iso":null,"type":null,"translation":"Île-de-France"},{"id":"83881","country":"74","level":"2","is_last_level":"0","name":"Paris","iso":null,"type":null,"translation":"Paris"},{"id":"101072","country":"74","level":"3","is_last_level":"0","name":"Paris, 6e arrondissement","iso":null,"type":null,"translation":"Paris, 6e arrondissement"},{"id":"101073","country":"74","level":"4","is_last_level":"0","name":"Paris, 6e arrondissement","iso":null,"type":null,"translation":"Paris, 6e arrondissement"}],"city_id":"5009811","city":"Paris","zoom":20},"description":null},{"id":22248274,"language_id":1,"language_iso":"ru","urlhtml":"<a class=\"wikimapia-link\" href=\"http://wikimapia.org/22248274/ru/Hotel-Clement-2\">Hotel Clement  2*</a>","title":"Hotel Clement  2*","tags":[{"id":50,"title":"гостиница"}],"wikipedia":null,"is_building":true,"is_region":false,"is_deleted":false,"parent_id":"0","polygon":[{"x":2.3361276,"y":48.8526126},{"x":2.3361209,"y":48.8525332},{"x":2.3362523,"y":48.8525411},{"x":2.3362496,"y":48.8526064}],"location":{"lon":2.3361866,"lat":48.8525729,"north":48.8526126,"south":48.8525332,"east":2.3362523,"west":2.3361209,"country":"France","state":"Ile-de-France","place":"Paris","country_adm_id":101074,"gadm":[{"id":"74","country":"74","level":"0","is_last_level":"0","name":"France","iso":null,"type":null,"translation":"Франция"},{"id":"1000","country":"0","level":"0","is_last_level":"0","name":"World","iso":null,"type":null,"translation":"Мир "},{"id":"60533","country":"74","level":"1","is_last_level":"0","name":"Île-de-France","iso":null,"type":null,"translation":null},{"id":"83881","country":"74","level":"2","is_last_level":"0","name":"Paris","iso":null,"type":null,"translation":"Париж"},{"id":"101072","country":"74","level":"3","is_last_level":"0","name":"Paris, 6e arrondissement","iso":null,"type":null,"translation":null},{"id":"101073","country":"74","level":"4","is_last_level":"0","name":"Paris, 6e arrondissement","iso":null,"type":null,"translation":null}],"city_id":"5009811","city":"Paris","zoom":21},"description":"http://www.hotelclementparis.com/"},{"id":28943699,"language_id":2,"language_iso":"fr","urlhtml":"<a class=\"wikimapia-link\" href=\"http://wikimapia.org/28943699/fr/Laurence-Coiffure\">Laurence Coiffure</a>","title":"Laurence Coiffure","tags":[{"id":7417,"title":"Salon de Coiffure"}],"wikipedia":null,"is_building":true,"is_region":false,"is_deleted":false,"parent_id":"0","polygon":[{"x":2.3152094,"y":48.8141086},{"x":2.315174,"y":48.8141186},{"x":2.3151761,"y":48.8141219},{"x":2.3151735,"y":48.8141207},{"x":2.3150805,"y":48.8141449},{"x":2.3150425,"y":48.8140861},{"x":2.3151379,"y":48.8140587},{"x":2.3152064,"y":48.8140391},{"x":2.3152212,"y":48.8140642},{"x":2.3151748,"y":48.8140773},{"x":2.3151457,"y":48.814075},{"x":2.3151671,"y":48.8141081},{"x":2.3152035,"y":48.8140983}],"location":{"lon":2.3151318,"lat":48.814092,"north":48.8141449,"south":48.8140391,"east":2.3152212,"west":2.3150425,"country":"France","state":"Ile-de-France","place":"Montrouge","country_adm_id":0,"gadm":null,"city_id":"4561719","city":"Montrouge","zoom":20},"description":null},{"id":28945727,"language_id":2,"language_iso":"fr","urlhtml":"<a class=\"wikimapia-link\" href=\"http://wikimapia.org/28945727/fr/Rue-du-11-Novembre-34\">Rue du 11 Novembre, 34</a>","title":null,"tags":null,"wikipedia":null,"is_building":true,"is_region":false,"is_deleted":false,"parent_id":"0","polygon":[{"x":2.3104304,"y":48.8222405},{"x":2.3104075,"y":48.8222273},{"x":2.3103204,"y":48.8221774},{"x":2.3103319,"y":48.8221705},{"x":2.310357,"y":48.8221511},{"x":2.3103849,"y":48.8221304},{"x":2.3103894,"y":48.8221316},{"x":2.3104937,"y":48.8221923}],"location":{"lon":2.310407,"lat":48.8221854,"north":48.8222405,"south":48.8221304,"east":2.3104937,"west":2.3103204,"country":"France","state":"Ile-de-France","place":"Malakoff","country_adm_id":0,"gadm":null,"city_id":"0","city":false,"zoom":20},"description":null},{"id":28945827,"language_id":2,"language_iso":"fr","urlhtml":"<a class=\"wikimapia-link\" href=\"http://wikimapia.org/28945827/fr/Vaillant-Couturier\">Vaillant-Couturier</a>","title":"Vaillant-Couturier","tags":[{"id":45651,"title":"location de vélo-bicyclette"}],"wikipedia":null,"is_building":false,"is_region":false,"is_deleted":false,"parent_id":"0","polygon":[{"x":2.3324477,"y":48.8170245},{"x":2.3324416,"y":48.8170051},{"x":2.3328894,"y":48.8169414},{"x":2.3328963,"y":48.8169609}],"location":{"lon":2.3326689,"lat":48.8169829,"north":48.8170245,"south":48.8169414,"east":2.3328963,"west":2.3324416,"country":"France","state":"Ile-de-France","place":"Gentilly","country_adm_id":0,"gadm":null,"city_id":"0","city":false,"zoom":20},"description":null},{"id":28948589,"language_id":2,"language_iso":"fr","urlhtml":"<a class=\"wikimapia-link\" href=\"http://wikimapia.org/28948589/fr/Villa-des-Charmilles-6-bis\">Villa des Charmilles, 6 bis</a>","title":null,"tags":null,"wikipedia":null,"is_building":true,"is_region":false,"is_deleted":false,"parent_id":"0","polygon":[{"x":2.3077187,"y":48.832943},{"x":2.3076778,"y":48.8329056},{"x":2.3077036,"y":48.8328959},{"x":2.3078066,"y":48.8328534},{"x":2.3078431,"y":48.8328386},{"x":2.3078864,"y":48.8328773},{"x":2.3077972,"y":48.832913},{"x":2.3077273,"y":48.8329389}],"location":{"lon":2.3077821,"lat":48.8328908,"north":48.832943,"south":48.8328386,"east":2.3078864,"west":2.3076778,"country":"France","state":"Ile-de-France","place":"Malakoff","country_adm_id":0,"gadm":null,"city_id":"5009811","city":"Paris","zoom":20},"description":null},{"id":28948610,"language_id":2,"language_iso":"fr","urlhtml":"<a class=\"wikimapia-link\" href=\"http://wikimapia.org/28948610/fr/rue-Raymond-Losserand-93\">rue Raymond Losserand, 93</a>","title":null,"tags":null,"wikipedia":null,"is_building":true,"is_region":false,"is_deleted":false,"parent_id":"0","polygon":[{"x":2.3023469,"y":48.8308924},{"x":2.3023306,"y":48.8308666},{"x":2.3023106,"y":48.8308335},{"x":2.3024318,"y":48.8308001},{"x":2.3024682,"y":48.830836},{"x":2.3024895,"y":48.830855}],"location":{"lon":2.3024,"lat":48.8308462,"north":48.8308924,"south":48.8308001,"east":2.3024895,"west":2.3023106,"country":"France","state":"Ile-de-France","place":"Malakoff","country_adm_id":0,"gadm":null,"city_id":"5009811","city":"Paris","zoom":20},"description":null},{"id":28948622,"language_id":2,"language_iso":"fr","urlhtml":"<a class=\"wikimapia-link\" href=\"http://wikimapia.org/28948622/fr/Villa-des-Charmilles-13\">Villa des Charmilles, 13</a>","title":null,"tags":null,"wikipedia":null,"is_building":true,"is_region":false,"is_deleted":false,"parent_id":"0","polygon":[{"x":2.3047627,"y":48.8335073},{"x":2.3046477,"y":48.8335466},{"x":2.304598,"y":48.8334861},{"x":2.3047113,"y":48.8334452},{"x":2.3047227,"y":48.8334575}],"location":{"lon":2.3046803,"lat":48.8334959,"north":48.8335466,"south":48.8334452,"east":2.3047627,"west":2.304598,"country":"France","state":"Ile-de-France","place":"Malakoff","country_adm_id":0,"gadm":null,"city_id":"5009811","city":"Paris","zoom":20},"description":null},{"id":28948623,"language_id":2,"language_iso":"fr","urlhtml":"<a class=\"wikimapia-link\" href=\"http://wikimapia.org/28948623/fr/Villa-des-Charmilles-15\">Villa des Charmilles, 15</a>","title":null,"tags":null,"wikipedia":null,"is_building":true,"is_region":false,"is_deleted":false,"parent_id":"0","polygon":[{"x":2.3047032,"y":48.8336096},{"x":2.3046812,"y":48.8335864},{"x":2.3046624,"y":48.8335606},{"x":2.3046489,"y":48.8335465},{"x":2.3047647,"y":48.8335084},{"x":2.3047783,"y":48.8335248},{"x":2.3048145,"y":48.8335711},{"x":2.3047201,"y":48.8336042}],"location":{"lon":2.3047317,"lat":48.833559,"north":48.8336096,"south":48.8335084,"east":2.3048145,"west":2.3046489,"country":"France","state":"Ile-de-France","place":"Malakoff","country_adm_id":0,"gadm":null,"city_id":"5009811","city":"Paris","zoom":20},"description":null},{"id":28948625,"language_id":2,"language_iso":"fr","urlhtml":"<a class=\"wikimapia-link\" href=\"http://wikimapia.org/28948625/fr/Villa-des-Charmilles-2\">Villa des Charmilles, 2</a>","title":null,"tags":null,"wikipedia":null,"is_building":true,"is_region":false,"is_deleted":false,"parent_id":"0","polygon":[{"x":2.3045834,"y":48.8330492},{"x":2.3045467,"y":48.8330615},{"x":2.3045053,"y":48.8330742},{"x":2.3044825,"y":48.8330483},{"x":2.3044849,"y":48.8330196},{"x":2.3045068,"y":48.8330004},{"x":2.3045669,"y":48.8329471},{"x":2.3045707,"y":48.832948},{"x":2.3045744,"y":48.8329449},{"x":2.3046014,"y":48.8329933},{"x":2.3046161,"y":48.8330172},{"x":2.3045691,"y":48.8330295}],"location":{"lon":2.3045493,"lat":48.8330095,"north":48.8330742,"south":48.8329449,"east":2.3046161,"west":2.3044825,"country":"France","state":"Ile-de-France","place":"Malakoff","country_adm_id":0,"gadm":null,"city_id":"5009811","city":"Paris","zoom":20},"description":null},{"id":28949095,"language_id":2,"language_iso":"fr","urlhtml":"<a class=\"wikimapia-link\" href=\"http://wikimapia.org/28949095/fr/rue-du-chateau-8\">rue du chateau, 8</a>","title":null,"tags":null,"wikipedia":null,"is_building":true,"is_region":false,"is_deleted":false,"parent_id":"0","polygon":[{"x":2.3273066,"y":48.8358953},{"x":2.3273031,"y":48.8358971},{"x":2.3272927,"y":48.8358855},{"x":2.3273124,"y":48.8358773},{"x":2.3273227,"y":48.8358768},{"x":2.327287,"y":48.8358375},{"x":2.3272593,"y":48.8358485},{"x":2.3272488,"y":48.8358369},{"x":2.3272584,"y":48.8358326},{"x":2.3273202,"y":48.8358081},{"x":2.3273848,"y":48.8357879},{"x":2.3274087,"y":48.8358194},{"x":2.3274341,"y":48.8358524},{"x":2.3273593,"y":48.8358722},{"x":2.3273217,"y":48.8358896}],"location":{"lon":2.3273414,"lat":48.8358425,"north":48.8358971,"south":48.8357879,"east":2.3274341,"west":2.3272488,"country":"France","state":"Ile-de-France","place":"Gentilly","country_adm_id":0,"gadm":null,"city_id":"5009811","city":"Paris","zoom":20},"description":null},{"id":28951719,"language_id":2,"language_iso":"fr","urlhtml":"<a class=\"wikimapia-link\" href=\"http://wikimapia.org/28951719/fr/Rue-De-Vaugirard-282\">Rue De Vaugirard, 282</a>","title":null,"tags":[{"id":17,"title":"magasin"}],"wikipedia":null,"is_building":true,"is_region":false,"is_deleted":false,"parent_id":"0","polygon":[{"x":2.2990528,"y":48.838756},{"x":2.299067,"y":48.8388166},{"x":2.2988707,"y":48.8387178},{"x":2.298912,"y":48.8386832},{"x":2.2990031,"y":48.8387297}],"location":{"lon":2.2989688,"lat":48.8387499,"north":48.8388166,"south":48.8386832,"east":2.299067,"west":2.2988707,"country":"France","state":"Ile-de-France","place":"Malakoff","country_adm_id":0,"gadm":null,"city_id":"5009811","city":"Paris","zoom":20},"description":null},{"id":28952631,"language_id":2,"language_iso":"fr","urlhtml":"<a class=\"wikimapia-link\" href=\"http://wikimapia.org/28952631/ru/Rue-de-la-Grande-Chaumiere-46\">Rue de la Grande Chaumiere, 46</a>","title":null,"tags":null,"wikipedia":null,"is_building":true,"is_region":false,"is_deleted":false,"parent_id":"0","polygon":[{"x":2.3287713,"y":48.8429981},{"x":2.3287665,"y":48.842997},{"x":2.3287645,"y":48.8429962},{"x":2.328761,"y":48.8429938},{"x":2.3287587,"y":48.8429896},{"x":2.3287542,"y":48.8429872},{"x":2.3287526,"y":48.8429829},{"x":2.3287542,"y":48.8429791},{"x":2.3287529,"y":48.8429757},{"x":2.3287541,"y":48.8429733},{"x":2.3287562,"y":48.8429707},{"x":2.3287587,"y":48.8429678},{"x":2.3287623,"y":48.8429643},{"x":2.3287672,"y":48.8429627},{"x":2.3287699,"y":48.84296},{"x":2.3287746,"y":48.8429577},{"x":2.3287814,"y":48.8429564},{"x":2.3287859,"y":48.8429577},{"x":2.3288046,"y":48.8429456},{"x":2.3287717,"y":48.8429246},{"x":2.3288713,"y":48.8428637},{"x":2.3289,"y":48.8428806},{"x":2.328928,"y":48.8429019}],"location":{"lon":2.3288403,"lat":48.8429309,"north":48.8429981,"south":48.8428637,"east":2.328928,"west":2.3287526,"country":"France","state":"Ile-de-France","place":"Paris","country_adm_id":0,"gadm":null,"city_id":"5009811","city":"Paris","zoom":20},"description":null},{"id":28959423,"language_id":2,"language_iso":"fr","urlhtml":"<a class=\"wikimapia-link\" href=\"http://wikimapia.org/28959423/fr/Rue-Racine-7\">Rue Racine, 7</a>","title":null,"tags":null,"wikipedia":null,"is_building":true,"is_region":false,"is_deleted":false,"parent_id":"0","polygon":[{"x":2.3413608,"y":48.8500497},{"x":2.3413426,"y":48.8501002},{"x":2.3414709,"y":48.8501204},{"x":2.341515,"y":48.850127},{"x":2.3415337,"y":48.850076},{"x":2.3415196,"y":48.8500754}],"location":{"lon":2.3414381,"lat":48.8500883,"north":48.850127,"south":48.8500497,"east":2.3415337,"west":2.3413426,"country":"France","state":"Ile-de-France","place":"Paris","country_adm_id":0,"gadm":null,"city_id":"5009811","city":"Paris","zoom":21},"description":null},{"id":28959544,"language_id":2,"language_iso":"fr","urlhtml":"<a class=\"wikimapia-link\" href=\"http://wikimapia.org/28959544/Rue-de-Vaugirard-3b\">Rue de Vaugirard, 3b</a>","title":null,"tags":[{"id":44865,"title":"immeuble d&#039;appartements"}],"wikipedia":null,"is_building":true,"is_region":false,"is_deleted":false,"parent_id":"0","polygon":[{"x":2.340268,"y":48.848882},{"x":2.3403751,"y":48.8488521},{"x":2.3403473,"y":48.8487871},{"x":2.3402257,"y":48.8488039},{"x":2.3402232,"y":48.8488058}],"location":{"lon":2.3402991,"lat":48.8488345,"north":48.848882,"south":48.8487871,"east":2.3403751,"west":2.3402232,"country":"France","state":"Ile-de-France","place":"Paris","country_adm_id":0,"gadm":null,"city_id":"5009811","city":"Paris","zoom":20},"description":null},{"id":28970277,"language_id":2,"language_iso":"fr","urlhtml":"<a class=\"wikimapia-link\" href=\"http://wikimapia.org/28970277/fr/place-Paul-Painlev%C3%A9-15\">place Paul Painlevé, 15</a>","title":null,"tags":null,"wikipedia":null,"is_building":true,"is_region":false,"is_deleted":false,"parent_id":"0","polygon":[{"x":2.3426631,"y":48.8532777},{"x":2.3427056,"y":48.8532714},{"x":2.342704,"y":48.8532663},{"x":2.3426653,"y":48.8531936},{"x":2.3426625,"y":48.8531885},{"x":2.3426293,"y":48.8531368},{"x":2.3425817,"y":48.8530575},{"x":2.3425618,"y":48.8530566},{"x":2.3425446,"y":48.8530548},{"x":2.342563,"y":48.8530911},{"x":2.3425688,"y":48.853101},{"x":2.3425829,"y":48.8531244}],"location":{"lon":2.3426251,"lat":48.8531662,"north":48.8532777,"south":48.8530548,"east":2.3427056,"west":2.3425446,"country":"France","state":"Ile-de-France","place":"Paris","country_adm_id":0,"gadm":null,"city_id":"5009811","city":"Paris","zoom":20},"description":null},{"id":28970925,"language_id":2,"language_iso":"fr","urlhtml":"<a class=\"wikimapia-link\" href=\"http://wikimapia.org/28970925/fr/Rue-des-Ciseaux-10\">Rue des Ciseaux, 10</a>","title":null,"tags":null,"wikipedia":null,"is_building":true,"is_region":false,"is_deleted":false,"parent_id":"0","polygon":[{"x":2.333819,"y":48.8528474},{"x":2.3338061,"y":48.8527428},{"x":2.3338425,"y":48.8527461},{"x":2.3338823,"y":48.8527508},{"x":2.3338861,"y":48.8527518},{"x":2.3338883,"y":48.852754},{"x":2.3339051,"y":48.8528089},{"x":2.3339157,"y":48.8528453},{"x":2.3338219,"y":48.8528528}],"location":{"lon":2.3338609,"lat":48.8527978,"north":48.8528528,"south":48.8527428,"east":2.3339157,"west":2.3338061,"country":"France","state":"Ile-de-France","place":"Paris","country_adm_id":0,"gadm":null,"city_id":"5009811","city":"Paris","zoom":21},"description":null},{"id":28972191,"language_id":2,"language_iso":"fr","urlhtml":"<a class=\"wikimapia-link\" href=\"http://wikimapia.org/28972191/fr/rue-de-Buci-15\">rue de Buci, 15</a>","title":null,"tags":null,"wikipedia":null,"is_building":true,"is_region":false,"is_deleted":false,"parent_id":"0","polygon":[{"x":2.337428,"y":48.8537645},{"x":2.3373773,"y":48.8536403},{"x":2.3374532,"y":48.8536285},{"x":2.3374552,"y":48.8536386},{"x":2.3374444,"y":48.8536509},{"x":2.3374558,"y":48.8537009},{"x":2.3374912,"y":48.8536957},{"x":2.3375023,"y":48.8537537},{"x":2.33747,"y":48.8537584}],"location":{"lon":2.3374398,"lat":48.8536965,"north":48.8537645,"south":48.8536285,"east":2.3375023,"west":2.3373773,"country":"France","state":"Ile-de-France","place":"Paris","country_adm_id":0,"gadm":null,"city_id":"5009811","city":"Paris","zoom":20},"description":null},{"id":5563040,"language_id":2,"language_iso":"fr","urlhtml":"<a class=\"wikimapia-link\" href=\"http://wikimapia.org/5563040/fr/Biblioth%C3%A8que-municipale-Plaisance\">Bibliothèque municipale Plaisance</a>","title":"Bibliothèque municipale Plaisance","tags":[{"id":314,"title":"bibliothèque, médiathèque"}],"wikipedia":null,"is_building":true,"is_region":false,"is_deleted":false,"parent_id":"0","polygon":[{"x":2.311473,"y":48.831255},{"x":2.311528,"y":48.83129},{"x":2.31165,"y":48.831214},{"x":2.311593,"y":48.831173}],"location":{"lon":2.3115615,"lat":48.8312315,"north":48.83129,"south":48.831173,"east":2.31165,"west":2.311473,"country":"France","state":"Ile-de-France","place":"Malakoff","country_adm_id":100174,"gadm":[{"id":"74","country":"74","level":"0","is_last_level":"0","name":"France","iso":null,"type":null,"translation":"France"},{"id":"1000","country":"0","level":"0","is_last_level":"0","name":"World","iso":null,"type":null,"translation":"Monde "},{"id":"60533","country":"74","level":"1","is_last_level":"0","name":"Île-de-France","iso":null,"type":null,"translation":null},{"id":"83881","country":"74","level":"2","is_last_level":"0","name":"Paris","iso":null,"type":null,"translation":"Paris"},{"id":"100172","country":"74","level":"3","is_last_level":"0","name":"Paris, 14e arrondissement","iso":null,"type":null,"translation":null},{"id":"100173","country":"74","level":"4","is_last_level":"0","name":"Paris, 14e arrondissement","iso":null,"type":null,"translation":null}],"city_id":"5009811","city":"Paris","zoom":20},"description":"Bibliothèque adultes, jeunesse et discothèque\n5, rue de Ridder\n75014 Paris\n\nTél. : 01 45 41 24 74\nFax : 01 43 95 69 02\nMétro : Plaisance\nBus : 62\n\nAccès handicapés\n\nAccès internet"},{"id":13529596,"language_id":2,"language_iso":"fr","urlhtml":"<a class=\"wikimapia-link\" href=\"http://wikimapia.org/13529596/fr/station-m%C3%A9tro-Saint-Sulpice-ligne-4\">station métro \"Saint-Sulpice\" (ligne 4)</a>","title":"station métro \"Saint-Sulpice\" (ligne 4)","tags":[{"id":44758,"title":"station de métro"}],"wikipedia":"http://fr.wikipedia.org/wiki/Saint-Sulpice_(métro_de_Paris)","is_building":true,"is_region":false,"is_deleted":false,"parent_id":"0","polygon":[{"x":2.331073,"y":48.851469},{"x":2.3312929,"y":48.8516737},{"x":2.3313278,"y":48.851656},{"x":2.3310944,"y":48.8514584}],"location":{"lon":2.3312004,"lat":48.851566,"north":48.8516737,"south":48.8514584,"east":2.3313278,"west":2.331073,"country":"France","state":"Ile-de-France","place":"Paris","country_adm_id":101074,"gadm":[{"id":"74","country":"74","level":"0","is_last_level":"0","name":"France","iso":null,"type":null,"translation":"France"},{"id":"1000","country":"0","level":"0","is_last_level":"0","name":"World","iso":null,"type":null,"translation":"Monde "},{"id":"60533","country":"74","level":"1","is_last_level":"0","name":"Île-de-France","iso":null,"type":null,"translation":null},{"id":"83881","country":"74","level":"2","is_last_level":"0","name":"Paris","iso":null,"type":null,"translation":"Paris"},{"id":"101072","country":"74","level":"3","is_last_level":"0","name":"Paris, 6e arrondissement","iso":null,"type":null,"translation":null},{"id":"101073","country":"74","level":"4","is_last_level":"0","name":"Paris, 6e arrondissement","iso":null,"type":null,"translation":null}],"city_id":"5009811","city":"Paris","zoom":19},"description":"Saint-Sulpice est une station du métro de Paris sur la ligne 4, dans le 6e arrondissement de Paris."},{"id":25142432,"language_id":1,"language_iso":"ru","urlhtml":"<a class=\"wikimapia-link\" href=\"http://wikimapia.org/25142432/ru/%D0%A4%D0%BE%D0%BD%D1%82%D0%B0%D0%BD\">Фонтан</a>","title":"Фонтан","tags":[{"id":392,"title":"фонтан"}],"wikipedia":null,"is_building":false,"is_region":false,"is_deleted":false,"parent_id":"0","polygon":[{"x":2.3424765,"y":48.8486449},{"x":2.3424913,"y":48.8486732},{"x":2.3427622,"y":48.8486078},{"x":2.3427447,"y":48.8485778}],"location":{"lon":2.3426193,"lat":48.8486255,"north":48.8486732,"south":48.8485778,"east":2.3427622,"west":2.3424765,"country":"France","state":"Ile-de-France","place":"Paris","country_adm_id":100171,"gadm":[{"id":"74","country":"74","level":"0","is_last_level":"0","name":"France","iso":null,"type":null,"translation":"Франция"},{"id":"1000","country":"0","level":"0","is_last_level":"0","name":"World","iso":null,"type":null,"translation":"Мир "},{"id":"60533","country":"74","level":"1","is_last_level":"0","name":"Île-de-France","iso":null,"type":null,"translation":null},{"id":"83881","country":"74","level":"2","is_last_level":"0","name":"Paris","iso":null,"type":null,"translation":"Париж"},{"id":"100169","country":"74","level":"3","is_last_level":"0","name":"Paris, 5e arrondissement","iso":null,"type":null,"translation":null},{"id":"100170","country":"74","level":"4","is_last_level":"0","name":"Paris, 5e arrondissement","iso":null,"type":null,"translation":null}],"city_id":"5009811","city":"Paris","zoom":20},"description":null},{"id":28943708,"language_id":2,"language_iso":"fr","urlhtml":"<a class=\"wikimapia-link\" href=\"http://wikimapia.org/28943708/fr/Rue-Moli%C3%A8re-64\">Rue Molière, 64</a>","title":null,"tags":null,"wikipedia":null,"is_building":true,"is_region":false,"is_deleted":false,"parent_id":"0","polygon":[{"x":2.3137904,"y":48.8150766},{"x":2.3136259,"y":48.8151255},{"x":2.3135921,"y":48.8150738},{"x":2.3136034,"y":48.8150697},{"x":2.3136095,"y":48.8150785},{"x":2.3137447,"y":48.8150369},{"x":2.3137395,"y":48.8150288},{"x":2.3137542,"y":48.8150245},{"x":2.3137736,"y":48.8150514}],"location":{"lon":2.3136912,"lat":48.815075,"north":48.8151255,"south":48.8150245,"east":2.3137904,"west":2.3135921,"country":"France","state":"Ile-de-France","place":"Montrouge","country_adm_id":0,"gadm":null,"city_id":"4561719","city":"Montrouge","zoom":20},"description":null},{"id":28945956,"language_id":2,"language_iso":"fr","urlhtml":"<a class=\"wikimapia-link\" href=\"http://wikimapia.org/28945956/fr/GMSA-Al%C3%A9sia-Multi-Services\">GMSA Alésia Multi Services</a>","title":"GMSA Alésia Multi Services","tags":[{"id":17,"title":"magasin"}],"wikipedia":null,"is_building":true,"is_region":false,"is_deleted":false,"parent_id":"0","polygon":[{"x":2.33008,"y":48.8242652},{"x":2.3300636,"y":48.8242248},{"x":2.3300444,"y":48.8241868},{"x":2.3300821,"y":48.8241795},{"x":2.3301321,"y":48.8241696},{"x":2.3301716,"y":48.8242482},{"x":2.3301431,"y":48.8242528},{"x":2.3301519,"y":48.8242594},{"x":2.3301583,"y":48.8242756},{"x":2.3301521,"y":48.8242831},{"x":2.3301279,"y":48.8242869},{"x":2.3301122,"y":48.8242816},{"x":2.3301065,"y":48.8242685},{"x":2.3300852,"y":48.8242745}],"location":{"lon":2.330108,"lat":48.8242282,"north":48.8242869,"south":48.8241696,"east":2.3301716,"west":2.3300444,"country":"France","state":"Ile-de-France","place":"Gentilly","country_adm_id":0,"gadm":null,"city_id":"5009811","city":"Paris","zoom":20},"description":null},{"id":28959017,"language_id":2,"language_iso":"fr","urlhtml":"<a class=\"wikimapia-link\" href=\"http://wikimapia.org/28959017/fr/Rue-du-Cherche-Midi-22\">Rue du Cherche-Midi, 22</a>","title":null,"tags":null,"wikipedia":null,"is_building":true,"is_region":false,"is_deleted":false,"parent_id":"0","polygon":[{"x":2.3279016,"y":48.8507529},{"x":2.3279944,"y":48.8506611},{"x":2.328024,"y":48.850681},{"x":2.3280547,"y":48.8507002},{"x":2.3279745,"y":48.8507856}],"location":{"lon":2.3279781,"lat":48.8507233,"north":48.8507856,"south":48.8506611,"east":2.3280547,"west":2.3279016,"country":"France","state":"Ile-de-France","place":"Paris","country_adm_id":0,"gadm":null,"city_id":"5009811","city":"Paris","zoom":20},"description":null},{"id":28970322,"language_id":2,"language_iso":"fr","urlhtml":"<a class=\"wikimapia-link\" href=\"http://wikimapia.org/28970322/fr/Rue-Saint-Andr%C3%A9-des-Arts-57\">Rue Saint-André-des-Arts, 57</a>","title":null,"tags":null,"wikipedia":null,"is_building":true,"is_region":false,"is_deleted":false,"parent_id":"0","polygon":[{"x":2.3391999,"y":48.8535129},{"x":2.3391411,"y":48.8535224},{"x":2.3390872,"y":48.8535313},{"x":2.33909,"y":48.8535249},{"x":2.3391072,"y":48.8534819},{"x":2.3391194,"y":48.8534529},{"x":2.3391475,"y":48.853379},{"x":2.339175,"y":48.8533847},{"x":2.339152,"y":48.8534375},{"x":2.3391957,"y":48.8534448}],"location":{"lon":2.3391435,"lat":48.8534551,"north":48.8535313,"south":48.853379,"east":2.3391999,"west":2.3390872,"country":"France","state":"Ile-de-France","place":"Paris","country_adm_id":0,"gadm":null,"city_id":"5009811","city":"Paris","zoom":21},"description":null},{"id":28970826,"language_id":2,"language_iso":"fr","urlhtml":"<a class=\"wikimapia-link\" href=\"http://wikimapia.org/28970826/fr/Rue-Saint-Sulpice-14\">Rue Saint-Sulpice, 14</a>","title":null,"tags":null,"wikipedia":null,"is_building":true,"is_region":false,"is_deleted":false,"parent_id":"0","polygon":[{"x":2.3372065,"y":48.8516326},{"x":2.3371964,"y":48.851633},{"x":2.3371977,"y":48.8516162},{"x":2.3371977,"y":48.8515981},{"x":2.3371964,"y":48.8515902},{"x":2.3371864,"y":48.851517},{"x":2.3372319,"y":48.8515192},{"x":2.3372708,"y":48.8515209},{"x":2.3372735,"y":48.8516312},{"x":2.3372407,"y":48.8516317}],"location":{"lon":2.3372299,"lat":48.851575,"north":48.851633,"south":48.851517,"east":2.3372735,"west":2.3371864,"country":"France","state":"Ile-de-France","place":"Paris","country_adm_id":0,"gadm":null,"city_id":"5009811","city":"Paris","zoom":21},"description":null},{"id":28970864,"language_id":2,"language_iso":"fr","urlhtml":"<a class=\"wikimapia-link\" href=\"http://wikimapia.org/28970864/fr/Rue-Princesse-8\">Rue Princesse, 8</a>","title":null,"tags":null,"wikipedia":null,"is_building":true,"is_region":false,"is_deleted":false,"parent_id":"0","polygon":[{"x":2.3342408,"y":48.8524137},{"x":2.3342443,"y":48.8523908},{"x":2.3342874,"y":48.8523937},{"x":2.3342912,"y":48.8523674},{"x":2.3344463,"y":48.8523746},{"x":2.3344427,"y":48.8524003},{"x":2.3344382,"y":48.8524278}],"location":{"lon":2.3343435,"lat":48.8523976,"north":48.8524278,"south":48.8523674,"east":2.3344463,"west":2.3342408,"country":"France","state":"Ile-de-France","place":"Paris","country_adm_id":0,"gadm":null,"city_id":"5009811","city":"Paris","zoom":21},"description":null},{"id":28971009,"language_id":2,"language_iso":"fr","urlhtml":"<a class=\"wikimapia-link\" href=\"http://wikimapia.org/28971009/fr/Rue-Princesse-5\">Rue Princesse, 5</a>","title":null,"tags":null,"wikipedia":null,"is_building":true,"is_region":false,"is_deleted":false,"parent_id":"0","polygon":[{"x":2.3346451,"y":48.8525046},{"x":2.3345372,"y":48.8524981},{"x":2.3345401,"y":48.8524687},{"x":2.3345485,"y":48.852416},{"x":2.3346596,"y":48.8524268},{"x":2.3346562,"y":48.8524399},{"x":2.3346672,"y":48.8524411},{"x":2.3346661,"y":48.8524531},{"x":2.3346536,"y":48.8524506}],"location":{"lon":2.3346022,"lat":48.8524603,"north":48.8525046,"south":48.852416,"east":2.3346672,"west":2.3345372,"country":"France","state":"Ile-de-France","place":"Paris","country_adm_id":0,"gadm":null,"city_id":"5009811","city":"Paris","zoom":20},"description":null},{"id":28971224,"language_id":2,"language_iso":"fr","urlhtml":"<a class=\"wikimapia-link\" href=\"http://wikimapia.org/28971224/fr/Rue-Monsieur-le-Prince-9\">Rue Monsieur le Prince, 9</a>","title":null,"tags":null,"wikipedia":null,"is_building":true,"is_region":false,"is_deleted":false,"parent_id":"0","polygon":[{"x":2.3394091,"y":48.8514585},{"x":2.3393711,"y":48.851504},{"x":2.339219,"y":48.8514487},{"x":2.3392378,"y":48.8514259},{"x":2.3392582,"y":48.8514037}],"location":{"lon":2.339314,"lat":48.8514538,"north":48.851504,"south":48.8514037,"east":2.3394091,"west":2.339219,"country":"France","state":"Ile-de-France","place":"Paris","country_adm_id":0,"gadm":null,"city_id":"5009811","city":"Paris","zoom":20},"description":null},{"id":28973199,"language_id":2,"language_iso":"fr","urlhtml":"<a class=\"wikimapia-link\" href=\"http://wikimapia.org/28973199/fr/Rue-des-Quatre-Vents-15\">Rue des Quatre-Vents, 15</a>","title":null,"tags":null,"wikipedia":null,"is_building":true,"is_region":false,"is_deleted":false,"parent_id":"0","polygon":[{"x":2.3373359,"y":48.8517115},{"x":2.3373392,"y":48.8516268},{"x":2.337368,"y":48.8516255},{"x":2.3374431,"y":48.8516233},{"x":2.3374398,"y":48.8517111},{"x":2.3373915,"y":48.8517106}],"location":{"lon":2.3373895,"lat":48.8516674,"north":48.8517115,"south":48.8516233,"east":2.3374431,"west":2.3373359,"country":"France","state":"Ile-de-France","place":"Paris","country_adm_id":0,"gadm":null,"city_id":"5009811","city":"Paris","zoom":21},"description":null},{"id":13296601,"language_id":0,"language_iso":"en","urlhtml":"<a class=\"wikimapia-link\" href=\"http://wikimapia.org/13296601/Boulevard-du-Montparnasse-92bis\">Boulevard du Montparnasse, 92bis</a>","title":null,"tags":[{"id":27,"title":"stadium"}],"wikipedia":null,"is_building":true,"is_region":false,"is_deleted":false,"parent_id":"0","polygon":[{"x":2.3267848,"y":48.8427433},{"x":2.3265461,"y":48.8428227},{"x":2.3265796,"y":48.8428492},{"x":2.3268089,"y":48.8427707}],"location":{"lon":2.3266775,"lat":48.8427962,"north":48.8428492,"south":48.8427433,"east":2.3268089,"west":2.3265461,"country":"France","state":"Ile-de-France","place":"Paris","country_adm_id":100174,"gadm":[{"id":"74","country":"74","level":"0","is_last_level":"0","name":"France","iso":null,"type":null,"translation":"France"},{"id":"1000","country":"0","level":"0","is_last_level":"0","name":"World","iso":null,"type":null,"translation":"World"},{"id":"60533","country":"74","level":"1","is_last_level":"0","name":"Île-de-France","iso":null,"type":null,"translation":"Île-de-France"},{"id":"83881","country":"74","level":"2","is_last_level":"0","name":"Paris","iso":null,"type":null,"translation":"Paris"},{"id":"100172","country":"74","level":"3","is_last_level":"0","name":"Paris, 14e arrondissement","iso":null,"type":null,"translation":"Paris, 14e arrondissement"},{"id":"100173","country":"74","level":"4","is_last_level":"0","name":"Paris, 14e arrondissement","iso":null,"type":null,"translation":"Paris, 14e arrondissement"}],"city_id":"5009811","city":"Paris","zoom":20},"description":null},{"id":25142444,"language_id":1,"language_iso":"ru","urlhtml":"<a class=\"wikimapia-link\" href=\"http://wikimapia.org/25142444/ru/%D0%A4%D0%BE%D0%BD%D1%82%D0%B0%D0%BD\">Фонтан</a>","title":"Фонтан","tags":[{"id":392,"title":"фонтан"}],"wikipedia":null,"is_building":false,"is_region":false,"is_deleted":false,"parent_id":"0","polygon":[{"x":2.3424242,"y":48.8485611},{"x":2.3424443,"y":48.8485902},{"x":2.3427125,"y":48.8485222},{"x":2.3426964,"y":48.8484949}],"location":{"lon":2.3425683,"lat":48.8485425,"north":48.8485902,"south":48.8484949,"east":2.3427125,"west":2.3424242,"country":"France","state":"Ile-de-France","place":"Paris","country_adm_id":100171,"gadm":[{"id":"74","country":"74","level":"0","is_last_level":"0","name":"France","iso":null,"type":null,"translation":"Франция"},{"id":"1000","country":"0","level":"0","is_last_level":"0","name":"World","iso":null,"type":null,"translation":"Мир "},{"id":"60533","country":"74","level":"1","is_last_level":"0","name":"Île-de-France","iso":null,"type":null,"translation":null},{"id":"83881","country":"74","level":"2","is_last_level":"0","name":"Paris","iso":null,"type":null,"translation":"Париж"},{"id":"100169","country":"74","level":"3","is_last_level":"0","name":"Paris, 5e arrondissement","iso":null,"type":null,"translation":null},{"id":"100170","country":"74","level":"4","is_last_level":"0","name":"Paris, 5e arrondissement","iso":null,"type":null,"translation":null}],"city_id":"5009811","city":"Paris","zoom":20},"description":null},{"id":27201589,"language_id":1,"language_iso":"ru","urlhtml":"<a class=\"wikimapia-link\" href=\"http://wikimapia.org/27201589/fr/rue-de-S%C3%A8vres-66\">rue de Sèvres, 66</a>","title":null,"tags":null,"wikipedia":null,"is_building":true,"is_region":false,"is_deleted":false,"parent_id":"0","polygon":[{"x":2.3193048,"y":48.8480083},{"x":2.319392,"y":48.8480369},{"x":2.3194356,"y":48.8479513},{"x":2.3193537,"y":48.8479204}],"location":{"lon":2.3193702,"lat":48.8479786,"north":48.8480369,"south":48.8479204,"east":2.3194356,"west":2.3193048,"country":"France","state":"Ile-de-France","place":"Paris","country_adm_id":0,"gadm":null,"city_id":"5009811","city":"Paris","zoom":20},"description":null},{"id":28943603,"language_id":2,"language_iso":"fr","urlhtml":"<a class=\"wikimapia-link\" href=\"http://wikimapia.org/28943603/fr/Rue-de-Saisset-80\">Rue de Saisset, 80</a>","title":null,"tags":null,"wikipedia":null,"is_building":true,"is_region":false,"is_deleted":false,"parent_id":"0","polygon":[{"x":2.3123163,"y":48.8153146},{"x":2.3123553,"y":48.8153766},{"x":2.3123655,"y":48.8153882},{"x":2.3122386,"y":48.8154255},{"x":2.3122243,"y":48.8154029},{"x":2.3122596,"y":48.8153911},{"x":2.3122265,"y":48.8153426}],"location":{"lon":2.3122949,"lat":48.81537,"north":48.8154255,"south":48.8153146,"east":2.3123655,"west":2.3122243,"country":"France","state":"Ile-de-France","place":"Montrouge","country_adm_id":0,"gadm":null,"city_id":"4561719","city":"Montrouge","zoom":20},"description":null},{"id":28948460,"language_id":2,"language_iso":"fr","urlhtml":"<a class=\"wikimapia-link\" href=\"http://wikimapia.org/28948460/fr/Mini-Market\">Mini Market</a>","title":"Mini Market","tags":[{"id":17,"title":"magasin"},{"id":74,"title":"restaurant, restauration"}],"wikipedia":null,"is_building":true,"is_region":false,"is_deleted":false,"parent_id":"0","polygon":[{"x":2.3161182,"y":48.8286041},{"x":2.3160418,"y":48.8285537},{"x":2.3160928,"y":48.8285222},{"x":2.3161315,"y":48.8284963},{"x":2.3161658,"y":48.8285213},{"x":2.3162064,"y":48.828549}],"location":{"lon":2.3161241,"lat":48.8285502,"north":48.8286041,"south":48.8284963,"east":2.3162064,"west":2.3160418,"country":"France","state":"Ile-de-France","place":"Gentilly","country_adm_id":0,"gadm":null,"city_id":"5009811","city":"Paris","zoom":20},"description":null},{"id":28948849,"language_id":2,"language_iso":"fr","urlhtml":"<a class=\"wikimapia-link\" href=\"http://wikimapia.org/28948849/fr/Caldella\">Caldella</a>","title":"Caldella","tags":[{"id":74,"title":"restaurant, restauration"}],"wikipedia":null,"is_building":false,"is_region":false,"is_deleted":false,"parent_id":"0","polygon":[{"x":2.3201163,"y":48.832488},{"x":2.3200359,"y":48.8325379},{"x":2.3199451,"y":48.8324693},{"x":2.3200302,"y":48.8324231},{"x":2.3200753,"y":48.8324585},{"x":2.320041,"y":48.8324768},{"x":2.3200509,"y":48.832484},{"x":2.3200371,"y":48.83249},{"x":2.3200473,"y":48.8324973},{"x":2.3200956,"y":48.8324736},{"x":2.3200967,"y":48.8324747},{"x":2.3201039,"y":48.8324799}],"location":{"lon":2.3200307,"lat":48.8324805,"north":48.8325379,"south":48.8324231,"east":2.3201163,"west":2.3199451,"country":"France","state":"Ile-de-France","place":"Gentilly","country_adm_id":0,"gadm":null,"city_id":"5009811","city":"Paris","zoom":20},"description":null},{"id":28959411,"language_id":2,"language_iso":"fr","urlhtml":"<a class=\"wikimapia-link\" href=\"http://wikimapia.org/28959411/fr/Rue-Monsieur-le-Prince-71\">Rue Monsieur le Prince, 71</a>","title":null,"tags":null,"wikipedia":null,"is_building":true,"is_region":false,"is_deleted":false,"parent_id":"0","polygon":[{"x":2.3407883,"y":48.8482871},{"x":2.3408089,"y":48.8482926},{"x":2.3408705,"y":48.8483039},{"x":2.3409441,"y":48.8483268},{"x":2.3409691,"y":48.8482793},{"x":2.3409352,"y":48.848268},{"x":2.3408332,"y":48.8482383},{"x":2.3408159,"y":48.8482343},{"x":2.3408043,"y":48.8482564}],"location":{"lon":2.3408787,"lat":48.8482805,"north":48.8483268,"south":48.8482343,"east":2.3409691,"west":2.3407883,"country":"France","state":"Ile-de-France","place":"Paris","country_adm_id":0,"gadm":null,"city_id":"5009811","city":"Paris","zoom":20},"description":null},{"id":28959412,"language_id":2,"language_iso":"fr","urlhtml":"<a class=\"wikimapia-link\" href=\"http://wikimapia.org/28959412/fr/Rue-Monsieur-le-Prince-65\">Rue Monsieur le Prince, 65</a>","title":null,"tags":null,"wikipedia":null,"is_building":true,"is_region":false,"is_deleted":false,"parent_id":"0","polygon":[{"x":2.3406972,"y":48.8484733},{"x":2.3408413,"y":48.8485134},{"x":2.3408612,"y":48.8484785},{"x":2.3408739,"y":48.8484582},{"x":2.3407472,"y":48.848428},{"x":2.3407229,"y":48.8484236},{"x":2.3407126,"y":48.8484456}],"location":{"lon":2.3407855,"lat":48.8484685,"north":48.8485134,"south":48.8484236,"east":2.3408739,"west":2.3406972,"country":"France","state":"Ile-de-France","place":"Paris","country_adm_id":0,"gadm":null,"city_id":"5009811","city":"Paris","zoom":20},"description":null},{"id":32395199,"language_id":0,"language_iso":"en","urlhtml":"<a class=\"wikimapia-link\" href=\"http://wikimapia.org/32395199/Rue-Suger-6\">Rue Suger, 6</a>","title":null,"tags":[{"id":109,"title":"building"}],"wikipedia":null,"is_building":true,"is_region":false,"is_deleted":false,"parent_id":"0","polygon":[{"x":2.3423382,"y":48.8530921},{"x":2.3423302,"y":48.8530313},{"x":2.3424133,"y":48.853033},{"x":2.3424213,"y":48.8530833},{"x":2.3424455,"y":48.8531407},{"x":2.3423771,"y":48.8531513},{"x":2.3423583,"y":48.8530921}],"location":{"lon":2.3423878,"lat":48.8530913,"north":48.8531513,"south":48.8530313,"east":2.3424455,"west":2.3423302,"country":"France","state":"Ile-de-France","place":"Paris","country_adm_id":0,"gadm":null,"city_id":"5009811","city":"Paris","zoom":21},"description":null},{"id":20726505,"language_id":7,"language_iso":"ja","urlhtml":"<a class=\"wikimapia-link\" href=\"http://wikimapia.org/20726505/ja/%E3%83%9D%E3%83%AB%E3%83%88%E3%83%BB%E3%83%89%E3%82%A5%E3%83%BB%E3%83%B4%E3%82%A1%E3%83%B3%E3%83%B4\">ポルト・ドゥ・ヴァンヴ</a>","title":"ポルト・ドゥ・ヴァンヴ","tags":[{"id":44758,"title":"地下鉄駅"}],"wikipedia":"","is_building":false,"is_region":false,"is_deleted":false,"parent_id":"0","polygon":[{"x":2.3053855,"y":48.8278857},{"x":2.3055384,"y":48.8278522},{"x":2.3054525,"y":48.8277921},{"x":2.3053801,"y":48.8278186}],"location":{"lon":2.3054592,"lat":48.8278389,"north":48.8278857,"south":48.8277921,"east":2.3055384,"west":2.3053801,"country":"France","state":"Ile-de-France","place":"Malakoff","country_adm_id":100174,"gadm":[{"id":"74","country":"74","level":"0","is_last_level":"0","name":"France","iso":null,"type":null,"translation":"フランス"},{"id":"1000","country":"0","level":"0","is_last_level":"0","name":"World","iso":null,"type":null,"translation":"世界"},{"id":"60533","country":"74","level":"1","is_last_level":"0","name":"Île-de-France","iso":null,"type":null,"translation":null},{"id":"83881","country":"74","level":"2","is_last_level":"0","name":"Paris","iso":null,"type":null,"translation":"パリ"},{"id":"100172","country":"74","level":"3","is_last_level":"0","name":"Paris, 14e arrondissement","iso":null,"type":null,"translation":null},{"id":"100173","country":"74","level":"4","is_last_level":"0","name":"Paris, 14e arrondissement","iso":null,"type":null,"translation":null}],"city_id":"5009811","city":"Paris","zoom":20},"description":"地下鉄ポルト・ドゥ・ヴァンヴ（Porte de Vanves）駅は、ヴァンブの蚤の市で有名。\n蚤の市と反対に１０分ほど歩くと古本市で有名な「ジョルジュ・ブラッサンス公園（Parc Ggeorges BrassensPORTE DE VANVES）」がある。\n\nhttp://www.metro2003.com/station/ligne-13/1329.shtml"},{"id":28943620,"language_id":2,"language_iso":"fr","urlhtml":"<a class=\"wikimapia-link\" href=\"http://wikimapia.org/28943620/fr/Rue-Moli%C3%A8re-52\">Rue Molière, 52</a>","title":null,"tags":null,"wikipedia":null,"is_building":true,"is_region":false,"is_deleted":false,"parent_id":"0","polygon":[{"x":2.3146126,"y":48.8147441},{"x":2.3146026,"y":48.8147285},{"x":2.3145376,"y":48.8146232},{"x":2.3146046,"y":48.8146054},{"x":2.3146456,"y":48.8146686},{"x":2.3146555,"y":48.8146846},{"x":2.3146444,"y":48.8146882},{"x":2.3146627,"y":48.8147176},{"x":2.3146288,"y":48.8147261},{"x":2.3146376,"y":48.8147364}],"location":{"lon":2.3146001,"lat":48.8146747,"north":48.8147441,"south":48.8146054,"east":2.3146627,"west":2.3145376,"country":"France","state":"Ile-de-France","place":"Montrouge","country_adm_id":0,"gadm":null,"city_id":"4561719","city":"Montrouge","zoom":20},"description":null},{"id":28945814,"language_id":2,"language_iso":"fr","urlhtml":"<a class=\"wikimapia-link\" href=\"http://wikimapia.org/28945814/fr/Avenue-Henri-Ginoux-24\">Avenue Henri Ginoux, 24</a>","title":null,"tags":null,"wikipedia":null,"is_building":true,"is_region":false,"is_deleted":false,"parent_id":"0","polygon":[{"x":2.3206478,"y":48.8203609},{"x":2.3205183,"y":48.8203958},{"x":2.3204812,"y":48.8203399},{"x":2.3204995,"y":48.8203356},{"x":2.3206129,"y":48.8203049}],"location":{"lon":2.3205645,"lat":48.8203503,"north":48.8203958,"south":48.8203049,"east":2.3206478,"west":2.3204812,"country":"France","state":"Ile-de-France","place":"Gentilly","country_adm_id":0,"gadm":null,"city_id":"4561719","city":"Montrouge","zoom":20},"description":null},{"id":28945858,"language_id":2,"language_iso":"fr","urlhtml":"<a class=\"wikimapia-link\" href=\"http://wikimapia.org/28945858/fr/Avenue-Henri-Ginoux-34\">Avenue Henri Ginoux, 34</a>","title":null,"tags":[{"id":164,"title":"maison, résidence"}],"wikipedia":null,"is_building":true,"is_region":false,"is_deleted":false,"parent_id":"0","polygon":[{"x":2.3171507,"y":48.8198721},{"x":2.3171019,"y":48.8198823},{"x":2.3170978,"y":48.8198745},{"x":2.3170297,"y":48.819889},{"x":2.3169984,"y":48.8198251},{"x":2.3171145,"y":48.8198001}],"location":{"lon":2.3170745,"lat":48.8198445,"north":48.819889,"south":48.8198001,"east":2.3171507,"west":2.3169984,"country":"France","state":"Ile-de-France","place":"Montrouge","country_adm_id":0,"gadm":null,"city_id":"4561719","city":"Montrouge","zoom":20},"description":null},{"id":28945986,"language_id":2,"language_iso":"fr","urlhtml":"<a class=\"wikimapia-link\" href=\"http://wikimapia.org/28945986/fr/rue-d-Al%C3%A9sia-17-Bis\">rue d'Alésia, 17 Bis</a>","title":null,"tags":null,"wikipedia":null,"is_building":true,"is_region":false,"is_deleted":false,"parent_id":"0","polygon":[{"x":2.3239613,"y":48.8247792},{"x":2.323898,"y":48.824793},{"x":2.3238582,"y":48.824802},{"x":2.3238229,"y":48.8247329},{"x":2.3238202,"y":48.8247287},{"x":2.3239222,"y":48.8247054}],"location":{"lon":2.3238907,"lat":48.8247537,"north":48.824802,"south":48.8247054,"east":2.3239613,"west":2.3238202,"country":"France","state":"Ile-de-France","place":"Gentilly","country_adm_id":0,"gadm":null,"city_id":"5009811","city":"Paris","zoom":20},"description":null},{"id":28946106,"language_id":2,"language_iso":"fr","urlhtml":"<a class=\"wikimapia-link\" href=\"http://wikimapia.org/28946106/fr/Rue-de-Tolbiac-54\">Rue de Tolbiac, 54</a>","title":null,"tags":null,"wikipedia":null,"is_building":true,"is_region":false,"is_deleted":false,"parent_id":"0","polygon":[{"x":2.3425317,"y":48.826051},{"x":2.3424675,"y":48.8259744},{"x":2.3424837,"y":48.8259608},{"x":2.3425229,"y":48.8259286},{"x":2.3426069,"y":48.8260295},{"x":2.3426251,"y":48.826052},{"x":2.3426119,"y":48.8260564},{"x":2.3425877,"y":48.8260289}],"location":{"lon":2.3425463,"lat":48.8259925,"north":48.8260564,"south":48.8259286,"east":2.3426251,"west":2.3424675,"country":"France","state":"Ile-de-France","place":"Gentilly","country_adm_id":0,"gadm":null,"city_id":"5009811","city":"Paris","zoom":20},"description":null},{"id":28948465,"language_id":2,"language_iso":"fr","urlhtml":"<a class=\"wikimapia-link\" href=\"http://wikimapia.org/28948465/fr/Rue-Pierre-Larousse-5\">Rue Pierre Larousse, 5</a>","title":null,"tags":[{"id":203,"title":"école"}],"wikipedia":null,"is_building":true,"is_region":false,"is_deleted":false,"parent_id":"0","polygon":[{"x":2.3148432,"y":48.8305412},{"x":2.314778,"y":48.8304829},{"x":2.3148262,"y":48.8304604},{"x":2.314875,"y":48.8304376},{"x":2.3149194,"y":48.8304754},{"x":2.3149407,"y":48.8304956}],"location":{"lon":2.3148593,"lat":48.8304894,"north":48.8305412,"south":48.8304376,"east":2.3149407,"west":2.314778,"country":"France","state":"Ile-de-France","place":"Malakoff","country_adm_id":0,"gadm":null,"city_id":"5009811","city":"Paris","zoom":20},"description":null},{"id":28948563,"language_id":2,"language_iso":"fr","urlhtml":"<a class=\"wikimapia-link\" href=\"http://wikimapia.org/28948563/fr/rue-Raymond-Losserand-133\">rue Raymond Losserand, 133</a>","title":null,"tags":null,"wikipedia":null,"is_building":true,"is_region":false,"is_deleted":false,"parent_id":"0","polygon":[{"x":2.3027743,"y":48.8300111},{"x":2.302762,"y":48.8299396},{"x":2.3028724,"y":48.8299239},{"x":2.3028768,"y":48.8299382},{"x":2.3028941,"y":48.8299948},{"x":2.3028508,"y":48.8300005}],"location":{"lon":2.302828,"lat":48.8299675,"north":48.8300111,"south":48.8299239,"east":2.3028941,"west":2.302762,"country":"France","state":"Ile-de-France","place":"Malakoff","country_adm_id":0,"gadm":null,"city_id":"5009811","city":"Paris","zoom":20},"description":null},{"id":28948626,"language_id":2,"language_iso":"fr","urlhtml":"<a class=\"wikimapia-link\" href=\"http://wikimapia.org/28948626/fr/Villa-des-Charmilles-21\">Villa des Charmilles, 21</a>","title":null,"tags":null,"wikipedia":null,"is_building":true,"is_region":false,"is_deleted":false,"parent_id":"0","polygon":[{"x":2.3048491,"y":48.8337829},{"x":2.3048097,"y":48.8337373},{"x":2.3049059,"y":48.8337021},{"x":2.3049155,"y":48.8336985},{"x":2.3049301,"y":48.8337149},{"x":2.3049694,"y":48.8337616},{"x":2.3049123,"y":48.8337812},{"x":2.3048614,"y":48.8337977}],"location":{"lon":2.3048895,"lat":48.8337481,"north":48.8337977,"south":48.8336985,"east":2.3049694,"west":2.3048097,"country":"France","state":"Ile-de-France","place":"Malakoff","country_adm_id":0,"gadm":null,"city_id":"5009811","city":"Paris","zoom":20},"description":null},{"id":28948897,"language_id":2,"language_iso":"fr","urlhtml":"<a class=\"wikimapia-link\" href=\"http://wikimapia.org/28948897/fr/rue-d-Al%C3%A9sia-61\">rue d'Alésia, 61</a>","title":null,"tags":null,"wikipedia":null,"is_building":true,"is_region":false,"is_deleted":false,"parent_id":"0","polygon":[{"x":2.3300908,"y":48.8277344},{"x":2.3300869,"y":48.8276275},{"x":2.3301311,"y":48.8276098},{"x":2.3301301,"y":48.8276677},{"x":2.3301857,"y":48.827666},{"x":2.3301849,"y":48.8277346},{"x":2.3301343,"y":48.8277348}],"location":{"lon":2.3301363,"lat":48.8276723,"north":48.8277348,"south":48.8276098,"east":2.3301857,"west":2.3300869,"country":"France","state":"Ile-de-France","place":"Gentilly","country_adm_id":0,"gadm":null,"city_id":"5009811","city":"Paris","zoom":21},"description":null},{"id":28948971,"language_id":2,"language_iso":"fr","urlhtml":"<a class=\"wikimapia-link\" href=\"http://wikimapia.org/28948971/fr/rue-Raymond-Losserand-56\">rue Raymond Losserand, 56</a>","title":null,"tags":null,"wikipedia":null,"is_building":true,"is_region":false,"is_deleted":false,"parent_id":"0","polygon":[{"x":2.3179456,"y":48.8288896},{"x":2.3179127,"y":48.8289059},{"x":2.317883,"y":48.8289206},{"x":2.3178424,"y":48.8289166},{"x":2.3178048,"y":48.8288801},{"x":2.3177785,"y":48.8288561},{"x":2.3178653,"y":48.8288157},{"x":2.3178863,"y":48.8288353},{"x":2.3178725,"y":48.8288417},{"x":2.3178636,"y":48.8288335},{"x":2.3178398,"y":48.8288431},{"x":2.3178619,"y":48.8288647},{"x":2.3179007,"y":48.8288485}],"location":{"lon":2.317862,"lat":48.8288681,"north":48.8289206,"south":48.8288157,"east":2.3179456,"west":2.3177785,"country":"France","state":"Ile-de-France","place":"Gentilly","country_adm_id":0,"gadm":null,"city_id":"5009811","city":"Paris","zoom":20},"description":null},{"id":28949090,"language_id":2,"language_iso":"fr","urlhtml":"<a class=\"wikimapia-link\" href=\"http://wikimapia.org/28949090/fr/rue-du-chateau-4\">rue du chateau, 4</a>","title":null,"tags":null,"wikipedia":null,"is_building":true,"is_region":false,"is_deleted":false,"parent_id":"0","polygon":[{"x":2.3269189,"y":48.8360214},{"x":2.3268912,"y":48.8359878},{"x":2.3269924,"y":48.8359453},{"x":2.3270195,"y":48.8359804},{"x":2.3270444,"y":48.8360084},{"x":2.3270333,"y":48.8360121},{"x":2.3269434,"y":48.8360506}],"location":{"lon":2.3269678,"lat":48.8359979,"north":48.8360506,"south":48.8359453,"east":2.3270444,"west":2.3268912,"country":"France","state":"Ile-de-France","place":"Gentilly","country_adm_id":0,"gadm":null,"city_id":"5009811","city":"Paris","zoom":20},"description":null},{"id":28951684,"language_id":2,"language_iso":"fr","urlhtml":"<a class=\"wikimapia-link\" href=\"http://wikimapia.org/28951684/fr/Happy\">Happy</a>","title":"Happy","tags":[{"id":17,"title":"magasin"}],"wikipedia":null,"is_building":false,"is_region":false,"is_deleted":false,"parent_id":"0","polygon":[{"x":2.2960479,"y":48.8372969},{"x":2.2960503,"y":48.8372934},{"x":2.296053,"y":48.8372106},{"x":2.2960535,"y":48.8371851},{"x":2.2960535,"y":48.8371261},{"x":2.2960359,"y":48.8371187},{"x":2.2960194,"y":48.8371343},{"x":2.2960387,"y":48.8371458},{"x":2.2959553,"y":48.837207}],"location":{"lon":2.2960044,"lat":48.8372078,"north":48.8372969,"south":48.8371187,"east":2.2960535,"west":2.2959553,"country":"France","state":"Ile-de-France","place":"Malakoff","country_adm_id":0,"gadm":null,"city_id":"5009811","city":"Paris","zoom":21},"description":null},{"id":28951881,"language_id":2,"language_iso":"fr","urlhtml":"<a class=\"wikimapia-link\" href=\"http://wikimapia.org/28951881/fr/MJJ\">MJJ</a>","title":"MJJ","tags":[{"id":7417,"title":"Salon de Coiffure"}],"wikipedia":null,"is_building":true,"is_region":false,"is_deleted":false,"parent_id":"0","polygon":[{"x":2.2958424,"y":48.8406021},{"x":2.2958752,"y":48.8405644},{"x":2.2959458,"y":48.8405867},{"x":2.2959824,"y":48.8405994},{"x":2.2959231,"y":48.8406631},{"x":2.2959167,"y":48.8406674},{"x":2.2958361,"y":48.840638},{"x":2.2958621,"y":48.840608}],"location":{"lon":2.2959092,"lat":48.8406159,"north":48.8406674,"south":48.8405644,"east":2.2959824,"west":2.2958361,"country":"France","state":"Ile-de-France","place":"Malakoff","country_adm_id":0,"gadm":null,"city_id":"5009811","city":"Paris","zoom":20},"description":null},{"id":28952758,"language_id":2,"language_iso":"fr","urlhtml":"<a class=\"wikimapia-link\" href=\"http://wikimapia.org/28952758/fr/Rue-Saint-Jacques-62\">Rue Saint Jacques, 62</a>","title":null,"tags":null,"wikipedia":null,"is_building":true,"is_region":false,"is_deleted":false,"parent_id":"0","polygon":[{"x":2.3428002,"y":48.8422373},{"x":2.3428121,"y":48.8422269},{"x":2.3428193,"y":48.8422293},{"x":2.3428224,"y":48.8422219},{"x":2.3428392,"y":48.8422132},{"x":2.3428097,"y":48.8422074},{"x":2.3429108,"y":48.8421668},{"x":2.3429588,"y":48.8421739},{"x":2.3429373,"y":48.842217},{"x":2.3429158,"y":48.8422601}],"location":{"lon":2.3428795,"lat":48.8422134,"north":48.8422601,"south":48.8421668,"east":2.3429588,"west":2.3428002,"country":"France","state":"Ile-de-France","place":"Paris","country_adm_id":0,"gadm":null,"city_id":"5009811","city":"Paris","zoom":20},"description":null},{"id":28959212,"language_id":2,"language_iso":"fr","urlhtml":"<a class=\"wikimapia-link\" href=\"http://wikimapia.org/28959212/fr/Pierre-Leroux-18\">Pierre Leroux, 18</a>","title":null,"tags":null,"wikipedia":null,"is_building":true,"is_region":false,"is_deleted":false,"parent_id":"0","polygon":[{"x":2.3189115,"y":48.8491375},{"x":2.3189184,"y":48.8491216},{"x":2.3189441,"y":48.8491267},{"x":2.3189615,"y":48.8491183},{"x":2.3189667,"y":48.8491078},{"x":2.3189795,"y":48.8491096},{"x":2.3189865,"y":48.8490958},{"x":2.319114,"y":48.8491214},{"x":2.3191021,"y":48.8491465},{"x":2.3190888,"y":48.8491737},{"x":2.3190461,"y":48.8491656}],"location":{"lon":2.3190127,"lat":48.8491347,"north":48.8491737,"south":48.8490958,"east":2.319114,"west":2.3189115,"country":"France","state":"Ile-de-France","place":"Paris","country_adm_id":0,"gadm":null,"city_id":"5009811","city":"Paris","zoom":20},"description":null},{"id":28959278,"language_id":2,"language_iso":"fr","urlhtml":"<a class=\"wikimapia-link\" href=\"http://wikimapia.org/28959278/fr/rue-de-S%C3%A8vres-42b\">rue de Sèvres, 42b</a>","title":null,"tags":null,"wikipedia":null,"is_building":true,"is_region":false,"is_deleted":false,"parent_id":"0","polygon":[{"x":2.3210181,"y":48.8487619},{"x":2.3210283,"y":48.8487691},{"x":2.3211062,"y":48.8488098},{"x":2.3211617,"y":48.8488394},{"x":2.32113,"y":48.8488682},{"x":2.3210293,"y":48.8488502},{"x":2.3210034,"y":48.8488256}],"location":{"lon":2.3210825,"lat":48.848815,"north":48.8488682,"south":48.8487619,"east":2.3211617,"west":2.3210034,"country":"France","state":"Ile-de-France","place":"Paris","country_adm_id":0,"gadm":null,"city_id":"5009811","city":"Paris","zoom":20},"description":null},{"id":28970684,"language_id":2,"language_iso":"fr","urlhtml":"<a class=\"wikimapia-link\" href=\"http://wikimapia.org/28970684/fr/Rue-Bernard-Palissy-7\">Rue Bernard Palissy, 7</a>","title":null,"tags":null,"wikipedia":null,"is_building":true,"is_region":false,"is_deleted":false,"parent_id":"0","polygon":[{"x":2.3317643,"y":48.8531401},{"x":2.3317837,"y":48.8530411},{"x":2.3318068,"y":48.8530417},{"x":2.3318086,"y":48.8530286},{"x":2.3318732,"y":48.8530355},{"x":2.3318323,"y":48.853143},{"x":2.3317968,"y":48.8531418}],"location":{"lon":2.3318187,"lat":48.8530858,"north":48.853143,"south":48.8530286,"east":2.3318732,"west":2.3317643,"country":"France","state":"Ile-de-France","place":"Paris","country_adm_id":0,"gadm":null,"city_id":"5009811","city":"Paris","zoom":21},"description":null},{"id":28971665,"language_id":2,"language_iso":"fr","urlhtml":"<a class=\"wikimapia-link\" href=\"http://wikimapia.org/28971665/fr/Passage-de-la-Petite-Boucherie-1\">Passage de la Petite Boucherie, 1</a>","title":null,"tags":null,"wikipedia":null,"is_building":true,"is_region":false,"is_deleted":false,"parent_id":"0","polygon":[{"x":2.3358286,"y":48.8538017},{"x":2.3358832,"y":48.853785},{"x":2.335915,"y":48.8538261},{"x":2.3359822,"y":48.8539161},{"x":2.3359511,"y":48.8539258},{"x":2.3359302,"y":48.8539325},{"x":2.335848,"y":48.8538227},{"x":2.3358335,"y":48.8538049}],"location":{"lon":2.3359054,"lat":48.8538587,"north":48.8539325,"south":48.853785,"east":2.3359822,"west":2.3358286,"country":"France","state":"Ile-de-France","place":"Paris","country_adm_id":0,"gadm":null,"city_id":"5009811","city":"Paris","zoom":20},"description":null},{"id":2768,"language_id":0,"language_iso":"en","urlhtml":"<a class=\"wikimapia-link\" href=\"http://wikimapia.org/2768/Le-Lyon-de-Denfert\">Le Lyon de Denfert</a>","title":"Le Lyon de Denfert","tags":[{"id":90,"title":"statue"},{"id":261,"title":"monument"}],"wikipedia":null,"is_building":true,"is_region":false,"is_deleted":false,"parent_id":"0","polygon":[{"x":2.332359,"y":48.834296},{"x":2.33244,"y":48.834386},{"x":2.33251,"y":48.834363},{"x":2.332437,"y":48.834275}],"location":{"lon":2.3324345,"lat":48.8343305,"north":48.834386,"south":48.834275,"east":2.33251,"west":2.332359,"country":"France","state":"Ile-de-France","place":"Gentilly","country_adm_id":100174,"gadm":[{"id":"74","country":"74","level":"0","is_last_level":"0","name":"France","iso":null,"type":null,"translation":"France"},{"id":"1000","country":"0","level":"0","is_last_level":"0","name":"World","iso":null,"type":null,"translation":"World"},{"id":"60533","country":"74","level":"1","is_last_level":"0","name":"Île-de-France","iso":null,"type":null,"translation":"Île-de-France"},{"id":"83881","country":"74","level":"2","is_last_level":"0","name":"Paris","iso":null,"type":null,"translation":"Paris"},{"id":"100172","country":"74","level":"3","is_last_level":"0","name":"Paris, 14e arrondissement","iso":null,"type":null,"translation":"Paris, 14e arrondissement"},{"id":"100173","country":"74","level":"4","is_last_level":"0","name":"Paris, 14e arrondissement","iso":null,"type":null,"translation":"Paris, 14e arrondissement"}],"city_id":"5009811","city":"Paris","zoom":20},"description":"Place Denfert Rochereau\nhttp://www.parisbalades.com/Photo1/photo15/Place_Denfert-Rochereau.jpg\n"},{"id":28943592,"language_id":2,"language_iso":"fr","urlhtml":"<a class=\"wikimapia-link\" href=\"http://wikimapia.org/28943592/fr/Rue-de-Saisset-83\">Rue de Saisset, 83</a>","title":null,"tags":null,"wikipedia":null,"is_building":true,"is_region":false,"is_deleted":false,"parent_id":"0","polygon":[{"x":2.3115649,"y":48.8153659},{"x":2.3116453,"y":48.8153442},{"x":2.3116536,"y":48.8153563},{"x":2.3116686,"y":48.8153541},{"x":2.3117107,"y":48.815416},{"x":2.3116188,"y":48.815443},{"x":2.3116063,"y":48.8154257}],"location":{"lon":2.3116378,"lat":48.8153936,"north":48.815443,"south":48.8153442,"east":2.3117107,"west":2.3115649,"country":"France","state":"Ile-de-France","place":"Montrouge","country_adm_id":0,"gadm":null,"city_id":"4561719","city":"Montrouge","zoom":20},"description":null},{"id":28946043,"language_id":2,"language_iso":"fr","urlhtml":"<a class=\"wikimapia-link\" href=\"http://wikimapia.org/28946043/fr/boulevard-Jourdan-38\">boulevard Jourdan, 38</a>","title":null,"tags":null,"wikipedia":null,"is_building":true,"is_region":false,"is_deleted":false,"parent_id":"0","polygon":[{"x":2.3334044,"y":48.8216798},{"x":2.3334204,"y":48.8217304},{"x":2.3334145,"y":48.8217315},{"x":2.3334416,"y":48.8217956},{"x":2.3334215,"y":48.8218002},{"x":2.3334101,"y":48.821777},{"x":2.3333956,"y":48.8217696},{"x":2.3333578,"y":48.8217779},{"x":2.3333419,"y":48.8217476},{"x":2.3333299,"y":48.8217489},{"x":2.3333043,"y":48.8217019},{"x":2.3333424,"y":48.8216929}],"location":{"lon":2.3333729,"lat":48.82174,"north":48.8218002,"south":48.8216798,"east":2.3334416,"west":2.3333043,"country":"France","state":"Ile-de-France","place":"Gentilly","country_adm_id":0,"gadm":null,"city_id":"5009811","city":"Paris","zoom":20},"description":null},{"id":28958658,"language_id":2,"language_iso":"fr","urlhtml":"<a class=\"wikimapia-link\" href=\"http://wikimapia.org/28958658/fr/Rue-Dupin-19\">Rue Dupin, 19</a>","title":null,"tags":null,"wikipedia":null,"is_building":true,"is_region":false,"is_deleted":false,"parent_id":"0","polygon":[{"x":2.3257253,"y":48.8495589},{"x":2.325634,"y":48.8495216},{"x":2.3256724,"y":48.8494842},{"x":2.3256999,"y":48.8494539},{"x":2.3257865,"y":48.8494914}],"location":{"lon":2.3257102,"lat":48.8495064,"north":48.8495589,"south":48.8494539,"east":2.3257865,"west":2.325634,"country":"France","state":"Ile-de-France","place":"Paris","country_adm_id":0,"gadm":null,"city_id":"5009811","city":"Paris","zoom":20},"description":null},{"id":28959091,"language_id":2,"language_iso":"fr","urlhtml":"<a class=\"wikimapia-link\" href=\"http://wikimapia.org/28959091/fr/Rue-De-Vaugirard-72\">Rue De Vaugirard, 72</a>","title":null,"tags":null,"wikipedia":null,"is_building":true,"is_region":false,"is_deleted":false,"parent_id":"0","polygon":[{"x":2.3301988,"y":48.8481428},{"x":2.3302128,"y":48.8480767},{"x":2.3302465,"y":48.8480864},{"x":2.3303846,"y":48.8481261},{"x":2.3303818,"y":48.8481308},{"x":2.330378,"y":48.8481299},{"x":2.3303787,"y":48.8481387},{"x":2.3303649,"y":48.848141},{"x":2.3303654,"y":48.848142},{"x":2.3303616,"y":48.8481423},{"x":2.3303532,"y":48.8481448},{"x":2.3303516,"y":48.848147},{"x":2.3303484,"y":48.848151},{"x":2.3303449,"y":48.8481569}],"location":{"lon":2.3302917,"lat":48.8481168,"north":48.8481569,"south":48.8480767,"east":2.3303846,"west":2.3301988,"country":"France","state":"Ile-de-France","place":"Paris","country_adm_id":0,"gadm":null,"city_id":"5009811","city":"Paris","zoom":20},"description":null},{"id":28959744,"language_id":2,"language_iso":"fr","urlhtml":"<a class=\"wikimapia-link\" href=\"http://wikimapia.org/28959744/fr/San-Francisco-Book-Company\">San Francisco Book Company</a>","title":"San Francisco Book Company","tags":[{"id":17,"title":"magasin"}],"wikipedia":null,"is_building":true,"is_region":false,"is_deleted":false,"parent_id":"0","polygon":[{"x":2.3396048,"y":48.8511779},{"x":2.3395658,"y":48.851225},{"x":2.3394333,"y":48.8511743},{"x":2.3394414,"y":48.8511619},{"x":2.3394644,"y":48.8511248}],"location":{"lon":2.339519,"lat":48.8511749,"north":48.851225,"south":48.8511248,"east":2.3396048,"west":2.3394333,"country":"France","state":"Ile-de-France","place":"Paris","country_adm_id":0,"gadm":null,"city_id":"5009811","city":"Paris","zoom":20},"description":null},{"id":28966678,"language_id":2,"language_iso":"fr","urlhtml":"<a class=\"wikimapia-link\" href=\"http://wikimapia.org/28966678/fr/Rue-de-Varenne-3\">Rue de Varenne, 3</a>","title":null,"tags":null,"wikipedia":null,"is_building":true,"is_region":false,"is_deleted":false,"parent_id":"0","polygon":[{"x":2.326892,"y":48.8532069},{"x":2.3268625,"y":48.8531275},{"x":2.3269674,"y":48.853111},{"x":2.3269939,"y":48.8531827},{"x":2.3269407,"y":48.8531945}],"location":{"lon":2.3269282,"lat":48.8531589,"north":48.8532069,"south":48.853111,"east":2.3269939,"west":2.3268625,"country":"France","state":"Ile-de-France","place":"Paris","country_adm_id":0,"gadm":null,"city_id":"5009811","city":"Paris","zoom":20},"description":null},{"id":28967279,"language_id":2,"language_iso":"fr","urlhtml":"<a class=\"wikimapia-link\" href=\"http://wikimapia.org/28967279/fr/Square-La-Rochefoucauld-7\">Square La Rochefoucauld, 7</a>","title":null,"tags":null,"wikipedia":null,"is_building":true,"is_region":false,"is_deleted":false,"parent_id":"0","polygon":[{"x":2.3230052,"y":48.8531545},{"x":2.3230198,"y":48.8531955},{"x":2.3229193,"y":48.8532115},{"x":2.3228201,"y":48.853227},{"x":2.3228068,"y":48.8531884}],"location":{"lon":2.3229133,"lat":48.8531907,"north":48.853227,"south":48.8531545,"east":2.3230198,"west":2.3228068,"country":"France","state":"Ile-de-France","place":"Paris","country_adm_id":0,"gadm":null,"city_id":"5009811","city":"Paris","zoom":21},"description":null},{"id":28970789,"language_id":2,"language_iso":"fr","urlhtml":"<a class=\"wikimapia-link\" href=\"http://wikimapia.org/28970789/fr/Rue-Guisarde-7\">Rue Guisarde, 7</a>","title":null,"tags":null,"wikipedia":null,"is_building":true,"is_region":false,"is_deleted":false,"parent_id":"0","polygon":[{"x":2.3347771,"y":48.8518705},{"x":2.3347791,"y":48.8518546},{"x":2.3347918,"y":48.8517836},{"x":2.3348108,"y":48.8517843},{"x":2.3348171,"y":48.8517557},{"x":2.3348193,"y":48.8517563},{"x":2.334872,"y":48.8517598},{"x":2.3348525,"y":48.8518771},{"x":2.3348148,"y":48.8518742}],"location":{"lon":2.3348245,"lat":48.8518164,"north":48.8518771,"south":48.8517557,"east":2.334872,"west":2.3347771,"country":"France","state":"Ile-de-France","place":"Paris","country_adm_id":0,"gadm":null,"city_id":"5009811","city":"Paris","zoom":21},"description":null},{"id":28970950,"language_id":2,"language_iso":"fr","urlhtml":"<a class=\"wikimapia-link\" href=\"http://wikimapia.org/28970950/fr/Rue-Guisarde-10\">Rue Guisarde, 10</a>","title":null,"tags":null,"wikipedia":null,"is_building":true,"is_region":false,"is_deleted":false,"parent_id":"0","polygon":[{"x":2.3342358,"y":48.8520015},{"x":2.334223,"y":48.8520016},{"x":2.3342367,"y":48.851892},{"x":2.3342736,"y":48.8518947},{"x":2.3343131,"y":48.8518981},{"x":2.3343097,"y":48.8519341},{"x":2.3343057,"y":48.8519677},{"x":2.3343044,"y":48.8519979},{"x":2.3343045,"y":48.8520023}],"location":{"lon":2.334268,"lat":48.8519471,"north":48.8520023,"south":48.851892,"east":2.3343131,"west":2.334223,"country":"France","state":"Ile-de-France","place":"Paris","country_adm_id":0,"gadm":null,"city_id":"5009811","city":"Paris","zoom":21},"description":null},{"id":28971078,"language_id":2,"language_iso":"fr","urlhtml":"<a class=\"wikimapia-link\" href=\"http://wikimapia.org/28971078/fr/Rue-Saint-Andr%C3%A9-des-Arts-63\">Rue Saint-André-des-Arts, 63</a>","title":null,"tags":null,"wikipedia":null,"is_building":true,"is_region":false,"is_deleted":false,"parent_id":"0","polygon":[{"x":2.3387886,"y":48.8535724},{"x":2.338808,"y":48.8534747},{"x":2.3388489,"y":48.8534705},{"x":2.3388472,"y":48.8534806},{"x":2.3388405,"y":48.8534808},{"x":2.3388422,"y":48.8534844},{"x":2.3388432,"y":48.8534892},{"x":2.3388432,"y":48.8534936},{"x":2.3388707,"y":48.8534923},{"x":2.3388777,"y":48.8534689},{"x":2.3389089,"y":48.8534672},{"x":2.3388834,"y":48.8535598}],"location":{"lon":2.3388487,"lat":48.8535198,"north":48.8535724,"south":48.8534672,"east":2.3389089,"west":2.3387886,"country":"France","state":"Ile-de-France","place":"Paris","country_adm_id":0,"gadm":null,"city_id":"5009811","city":"Paris","zoom":20},"description":null},{"id":28972431,"language_id":2,"language_iso":"fr","urlhtml":"<a class=\"wikimapia-link\" href=\"http://wikimapia.org/28972431/fr/Rue-des-Quatre-Vents-7\">Rue des Quatre-Vents, 7</a>","title":null,"tags":null,"wikipedia":null,"is_building":true,"is_region":false,"is_deleted":false,"parent_id":"0","polygon":[{"x":2.3378475,"y":48.8517049},{"x":2.3378475,"y":48.8516488},{"x":2.3378924,"y":48.851648},{"x":2.3378937,"y":48.8516361},{"x":2.3379319,"y":48.8516361},{"x":2.3379413,"y":48.8516608},{"x":2.3380003,"y":48.8516608},{"x":2.338001,"y":48.8517009},{"x":2.3380017,"y":48.8517031},{"x":2.3379145,"y":48.8517044}],"location":{"lon":2.3379246,"lat":48.8516705,"north":48.8517049,"south":48.8516361,"east":2.3380017,"west":2.3378475,"country":"France","state":"Ile-de-France","place":"Paris","country_adm_id":0,"gadm":null,"city_id":"5009811","city":"Paris","zoom":21},"description":null},{"id":29451754,"language_id":2,"language_iso":"fr","urlhtml":"<a class=\"wikimapia-link\" href=\"http://wikimapia.org/29451754/fr/Lion-de-Nubie-et-sa-proie\">Lion de Nubie et sa proie</a>","title":"Lion de Nubie et sa proie","tags":[{"id":90,"title":"statue"}],"wikipedia":"http://fr.wikipedia.org/wiki/Auguste_Cain","is_building":false,"is_region":false,"is_deleted":false,"parent_id":"0","polygon":[{"x":2.3362764,"y":48.84491},{"x":2.3362764,"y":48.8448147},{"x":2.3363515,"y":48.8448112},{"x":2.3363675,"y":48.8449171}],"location":{"lon":2.3363219,"lat":48.8448641,"north":48.8449171,"south":48.8448112,"east":2.3363675,"west":2.3362764,"country":"France","state":"Ile-de-France","place":"Paris","country_adm_id":0,"gadm":null,"city_id":"5009811","city":"Paris","zoom":21},"description":"par Auguste Cain (1821-1894)\n\nAuguste Nicolas Cain (Paris, 10 novembre 1821 - Paris, 25 août 1894), est un sculpteur animalier français. Il est le père du peintre et écrivain Georges Cain, et de l'homme de lettres et peintre Henri Cain."},{"id":31147675,"language_id":2,"language_iso":"fr","urlhtml":"<a class=\"wikimapia-link\" href=\"http://wikimapia.org/31147675/fr/Jeux-pour-enfants\">Jeux pour enfants</a>","title":"Jeux pour enfants","tags":[{"id":499,"title":"terrain de jeu pour enfants"}],"wikipedia":null,"is_building":false,"is_region":false,"is_deleted":false,"parent_id":"0","polygon":[{"x":2.3346416,"y":48.8537222},{"x":2.3347582,"y":48.853716},{"x":2.3347824,"y":48.8536622},{"x":2.3347167,"y":48.8536446},{"x":2.3346456,"y":48.8536648}],"location":{"lon":2.334712,"lat":48.8536834,"north":48.8537222,"south":48.8536446,"east":2.3347824,"west":2.3346416,"country":"France","state":"Ile-de-France","place":"Paris","country_adm_id":0,"gadm":null,"city_id":"5009811","city":"Paris","zoom":20},"description":null},{"id":4045430,"language_id":2,"language_iso":"fr","urlhtml":"<a class=\"wikimapia-link\" href=\"http://wikimapia.org/4045430/fr/Th%C3%A9atre-du-Guichet-Montparnasse\">Théatre du Guichet Montparnasse</a>","title":"Théatre du Guichet Montparnasse","tags":[{"id":133,"title":"théâtre, salle de spectacles"}],"wikipedia":null,"is_building":false,"is_region":false,"is_deleted":false,"parent_id":"0","polygon":[{"x":2.3223312,"y":48.8405692},{"x":2.32235,"y":48.840469},{"x":2.3224357,"y":48.8404699},{"x":2.3224048,"y":48.8405728}],"location":{"lon":2.3223834,"lat":48.8405209,"north":48.8405728,"south":48.840469,"east":2.3224357,"west":2.3223312,"country":"France","state":"Ile-de-France","place":"Gentilly","country_adm_id":100174,"gadm":[{"id":"74","country":"74","level":"0","is_last_level":"0","name":"France","iso":null,"type":null,"translation":"France"},{"id":"1000","country":"0","level":"0","is_last_level":"0","name":"World","iso":null,"type":null,"translation":"Monde "},{"id":"60533","country":"74","level":"1","is_last_level":"0","name":"Île-de-France","iso":null,"type":null,"translation":null},{"id":"83881","country":"74","level":"2","is_last_level":"0","name":"Paris","iso":null,"type":null,"translation":"Paris"},{"id":"100172","country":"74","level":"3","is_last_level":"0","name":"Paris, 14e arrondissement","iso":null,"type":null,"translation":null},{"id":"100173","country":"74","level":"4","is_last_level":"0","name":"Paris, 14e arrondissement","iso":null,"type":null,"translation":null}],"city_id":"5009811","city":"Paris","zoom":21},"description":null},{"id":28943657,"language_id":2,"language_iso":"fr","urlhtml":"<a class=\"wikimapia-link\" href=\"http://wikimapia.org/28943657/fr/Rue-de-Saisset-74\">Rue de Saisset, 74</a>","title":null,"tags":null,"wikipedia":null,"is_building":true,"is_region":false,"is_deleted":false,"parent_id":"0","polygon":[{"x":2.3127844,"y":48.8151783},{"x":2.3128196,"y":48.8152319},{"x":2.3128259,"y":48.8152418},{"x":2.3128346,"y":48.8152521},{"x":2.3128315,"y":48.8152538},{"x":2.312744,"y":48.8152804},{"x":2.3126933,"y":48.8152057}],"location":{"lon":2.3127639,"lat":48.8152293,"north":48.8152804,"south":48.8151783,"east":2.3128346,"west":2.3126933,"country":"France","state":"Ile-de-France","place":"Montrouge","country_adm_id":0,"gadm":null,"city_id":"4561719","city":"Montrouge","zoom":20},"description":null},{"id":28943754,"language_id":2,"language_iso":"fr","urlhtml":"<a class=\"wikimapia-link\" href=\"http://wikimapia.org/28943754/fr/Villa-Jos%C3%A9phine-1bis\">Villa Joséphine, 1bis</a>","title":null,"tags":null,"wikipedia":null,"is_building":true,"is_region":false,"is_deleted":false,"parent_id":"0","polygon":[{"x":2.3143196,"y":48.8143894},{"x":2.3143201,"y":48.8143896},{"x":2.3142293,"y":48.8144142},{"x":2.3141813,"y":48.8143376},{"x":2.3142733,"y":48.8143133}],"location":{"lon":2.3142507,"lat":48.8143637,"north":48.8144142,"south":48.8143133,"east":2.3143201,"west":2.3141813,"country":"France","state":"Ile-de-France","place":"Montrouge","country_adm_id":0,"gadm":null,"city_id":"4561719","city":"Montrouge","zoom":20},"description":null},{"id":28945960,"language_id":2,"language_iso":"fr","urlhtml":"<a class=\"wikimapia-link\" href=\"http://wikimapia.org/28945960/fr/Affinit%C3%A9-Beaut%C3%A9\">Affinité Beauté</a>","title":"Affinité Beauté","tags":[{"id":17,"title":"magasin"}],"wikipedia":null,"is_building":true,"is_region":false,"is_deleted":false,"parent_id":"0","polygon":[{"x":2.3293677,"y":48.8248413},{"x":2.3293302,"y":48.8247667},{"x":2.3293884,"y":48.824755},{"x":2.3294317,"y":48.8247462},{"x":2.3294364,"y":48.8247564},{"x":2.3294659,"y":48.8248229}],"location":{"lon":2.329398,"lat":48.8247937,"north":48.8248413,"south":48.8247462,"east":2.3294659,"west":2.3293302,"country":"France","state":"Ile-de-France","place":"Gentilly","country_adm_id":0,"gadm":null,"city_id":"5009811","city":"Paris","zoom":20},"description":null},{"id":28948407,"language_id":2,"language_iso":"fr","urlhtml":"<a class=\"wikimapia-link\" href=\"http://wikimapia.org/28948407/fr/Rue-des-Suisses-162\">Rue des Suisses, 162</a>","title":null,"tags":null,"wikipedia":null,"is_building":true,"is_region":false,"is_deleted":false,"parent_id":"0","polygon":[{"x":2.3153853,"y":48.831711},{"x":2.3153469,"y":48.8316469},{"x":2.3153824,"y":48.8316391},{"x":2.3155722,"y":48.8315959}],"location":{"lon":2.3154595,"lat":48.8316534,"north":48.831711,"south":48.8315959,"east":2.3155722,"west":2.3153469,"country":"France","state":"Ile-de-France","place":"Gentilly","country_adm_id":0,"gadm":null,"city_id":"5009811","city":"Paris","zoom":20},"description":null},{"id":28949084,"language_id":2,"language_iso":"fr","urlhtml":"<a class=\"wikimapia-link\" href=\"http://wikimapia.org/28949084/fr/rue-du-chateau-20\">rue du chateau, 20</a>","title":null,"tags":null,"wikipedia":null,"is_building":true,"is_region":false,"is_deleted":false,"parent_id":"0","polygon":[{"x":2.3271158,"y":48.8354238},{"x":2.3270265,"y":48.8354578},{"x":2.3269966,"y":48.8354197},{"x":2.3269905,"y":48.8354237},{"x":2.3269699,"y":48.8354198},{"x":2.3269582,"y":48.8354019},{"x":2.3270676,"y":48.8353593},{"x":2.3270909,"y":48.8353901}],"location":{"lon":2.327037,"lat":48.8354085,"north":48.8354578,"south":48.8353593,"east":2.3271158,"west":2.3269582,"country":"France","state":"Ile-de-France","place":"Gentilly","country_adm_id":0,"gadm":null,"city_id":"5009811","city":"Paris","zoom":20},"description":null},{"id":28952131,"language_id":2,"language_iso":"fr","urlhtml":"<a class=\"wikimapia-link\" href=\"http://wikimapia.org/28952131/fr/rue-Sain-Charles-64-A\">rue Sain-Charles, 64 A</a>","title":null,"tags":null,"wikipedia":null,"is_building":true,"is_region":false,"is_deleted":false,"parent_id":"0","polygon":[{"x":2.2969645,"y":48.8451526},{"x":2.2970394,"y":48.8451221},{"x":2.2970251,"y":48.845111},{"x":2.2969323,"y":48.8450357},{"x":2.2968843,"y":48.8450637}],"location":{"lon":2.2969618,"lat":48.8450941,"north":48.8451526,"south":48.8450357,"east":2.2970394,"west":2.2968843,"country":"France","state":"Ile-de-France","place":"Malakoff","country_adm_id":0,"gadm":null,"city_id":"5009811","city":"Paris","zoom":20},"description":null},{"id":28959124,"language_id":2,"language_iso":"fr","urlhtml":"<a class=\"wikimapia-link\" href=\"http://wikimapia.org/28959124/fr/Rue-Cassette-10\">Rue Cassette, 10</a>","title":null,"tags":null,"wikipedia":null,"is_building":true,"is_region":false,"is_deleted":false,"parent_id":"0","polygon":[{"x":2.330621,"y":48.8501659},{"x":2.3306243,"y":48.8501257},{"x":2.3306511,"y":48.850127},{"x":2.3306525,"y":48.8501143},{"x":2.3306632,"y":48.8501072},{"x":2.3306833,"y":48.8501085},{"x":2.330684,"y":48.8500993},{"x":2.3307631,"y":48.8500997},{"x":2.3307557,"y":48.8501676}],"location":{"lon":2.330692,"lat":48.8501334,"north":48.8501676,"south":48.8500993,"east":2.3307631,"west":2.330621,"country":"France","state":"Ile-de-France","place":"Paris","country_adm_id":0,"gadm":null,"city_id":"5009811","city":"Paris","zoom":21},"description":null},{"id":28959603,"language_id":2,"language_iso":"fr","urlhtml":"<a class=\"wikimapia-link\" href=\"http://wikimapia.org/28959603/fr/Rue-de-Cond%C3%A9-23\">Rue de Condé, 23</a>","title":null,"tags":null,"wikipedia":null,"is_building":true,"is_region":false,"is_deleted":false,"parent_id":"0","polygon":[{"x":2.3380475,"y":48.8500257},{"x":2.3380431,"y":48.8499971},{"x":2.3380384,"y":48.8499688},{"x":2.3381402,"y":48.8499578},{"x":2.3381717,"y":48.8499547},{"x":2.3381739,"y":48.8499629},{"x":2.3381779,"y":48.8499883},{"x":2.3381821,"y":48.8500172}],"location":{"lon":2.3381102,"lat":48.8499902,"north":48.8500257,"south":48.8499547,"east":2.3381821,"west":2.3380384,"country":"France","state":"Ile-de-France","place":"Paris","country_adm_id":0,"gadm":null,"city_id":"5009811","city":"Paris","zoom":21},"description":null},{"id":28966528,"language_id":2,"language_iso":"fr","urlhtml":"<a class=\"wikimapia-link\" href=\"http://wikimapia.org/28966528/fr/Rue-de-Grenelle-4\">Rue de Grenelle, 4</a>","title":null,"tags":null,"wikipedia":null,"is_building":true,"is_region":false,"is_deleted":false,"parent_id":"0","polygon":[{"x":2.3298874,"y":48.8525198},{"x":2.3298365,"y":48.8524867},{"x":2.3298915,"y":48.8524484},{"x":2.3299604,"y":48.8523974},{"x":2.3299873,"y":48.8524362},{"x":2.3299617,"y":48.8524494},{"x":2.3299789,"y":48.8524663}],"location":{"lon":2.3299119,"lat":48.8524586,"north":48.8525198,"south":48.8523974,"east":2.3299873,"west":2.3298365,"country":"France","state":"Ile-de-France","place":"Paris","country_adm_id":0,"gadm":null,"city_id":"5009811","city":"Paris","zoom":20},"description":null},{"id":28969650,"language_id":2,"language_iso":"fr","urlhtml":"<a class=\"wikimapia-link\" href=\"http://wikimapia.org/28969650/fr/Rue-de-l-Hirondelle-29\">Rue de l'Hirondelle, 29</a>","title":null,"tags":null,"wikipedia":null,"is_building":true,"is_region":false,"is_deleted":false,"parent_id":"0","polygon":[{"x":2.3426439,"y":48.8536736},{"x":2.3426094,"y":48.8536392},{"x":2.342587,"y":48.8536174},{"x":2.342591,"y":48.8536167},{"x":2.3427083,"y":48.8535916},{"x":2.3427563,"y":48.8536538}],"location":{"lon":2.3426716,"lat":48.8536326,"north":48.8536736,"south":48.8535916,"east":2.3427563,"west":2.342587,"country":"France","state":"Ile-de-France","place":"Paris","country_adm_id":0,"gadm":null,"city_id":"5009811","city":"Paris","zoom":21},"description":null},{"id":28969680,"language_id":2,"language_iso":"fr","urlhtml":"<a class=\"wikimapia-link\" href=\"http://wikimapia.org/28969680/fr/Rue-de-l-Hirondelle-27\">Rue de l'Hirondelle, 27</a>","title":null,"tags":null,"wikipedia":null,"is_building":true,"is_region":false,"is_deleted":false,"parent_id":"0","polygon":[{"x":2.3427576,"y":48.8536538},{"x":2.3427948,"y":48.8536452},{"x":2.3428461,"y":48.8536346},{"x":2.3427999,"y":48.8535763},{"x":2.3428186,"y":48.8535706},{"x":2.3428022,"y":48.853541},{"x":2.3427657,"y":48.8535525},{"x":2.3427445,"y":48.853536},{"x":2.3427191,"y":48.8535437},{"x":2.3427355,"y":48.8535653},{"x":2.3427583,"y":48.8535975},{"x":2.3427264,"y":48.8536088}],"location":{"lon":2.3427826,"lat":48.8535949,"north":48.8536538,"south":48.853536,"east":2.3428461,"west":2.3427191,"country":"France","state":"Ile-de-France","place":"Paris","country_adm_id":0,"gadm":null,"city_id":"5009811","city":"Paris","zoom":20},"description":null},{"id":28971967,"language_id":2,"language_iso":"fr","urlhtml":"<a class=\"wikimapia-link\" href=\"http://wikimapia.org/28971967/fr/Rue-Gr%C3%A9goire-de-Tours-36\">Rue Grégoire de Tours, 36</a>","title":null,"tags":null,"wikipedia":null,"is_building":true,"is_region":false,"is_deleted":false,"parent_id":"0","polygon":[{"x":2.3374827,"y":48.8523222},{"x":2.3373975,"y":48.8523385},{"x":2.3373955,"y":48.852331},{"x":2.3374002,"y":48.8523262},{"x":2.3374069,"y":48.8523249},{"x":2.3374002,"y":48.8523085},{"x":2.3373593,"y":48.8523165},{"x":2.3373426,"y":48.8522812},{"x":2.3374177,"y":48.8522688},{"x":2.3374136,"y":48.85226},{"x":2.337476,"y":48.852253},{"x":2.3374867,"y":48.8522834},{"x":2.3374995,"y":48.8523183}],"location":{"lon":2.337421,"lat":48.8522957,"north":48.8523385,"south":48.852253,"east":2.3374995,"west":2.3373426,"country":"France","state":"Ile-de-France","place":"Paris","country_adm_id":0,"gadm":null,"city_id":"5009811","city":"Paris","zoom":20},"description":null},{"id":5910896,"language_id":2,"language_iso":"fr","urlhtml":"<a class=\"wikimapia-link\" href=\"http://wikimapia.org/5910896/fr/impasse-Florimont\">impasse Florimont</a>","title":"impasse Florimont","tags":null,"wikipedia":"http://fr.wikipedia.org/wiki/Impasse_Florimont","is_building":true,"is_region":false,"is_deleted":false,"parent_id":"0","polygon":[{"x":2.316012,"y":48.831589},{"x":2.315803,"y":48.831732},{"x":2.315763,"y":48.83176},{"x":2.315782,"y":48.831767},{"x":2.316018,"y":48.831605},{"x":2.316165,"y":48.831514},{"x":2.316211,"y":48.831471}],"location":{"lon":2.315987,"lat":48.831619,"north":48.831767,"south":48.831471,"east":2.316211,"west":2.315763,"country":"France","state":"Ile-de-France","place":"Gentilly","country_adm_id":100174,"gadm":[{"id":"74","country":"74","level":"0","is_last_level":"0","name":"France","iso":null,"type":null,"translation":"France"},{"id":"1000","country":"0","level":"0","is_last_level":"0","name":"World","iso":null,"type":null,"translation":"Monde "},{"id":"60533","country":"74","level":"1","is_last_level":"0","name":"Île-de-France","iso":null,"type":null,"translation":null},{"id":"83881","country":"74","level":"2","is_last_level":"0","name":"Paris","iso":null,"type":null,"translation":"Paris"},{"id":"100172","country":"74","level":"3","is_last_level":"0","name":"Paris, 14e arrondissement","iso":null,"type":null,"translation":null},{"id":"100173","country":"74","level":"4","is_last_level":"0","name":"Paris, 14e arrondissement","iso":null,"type":null,"translation":null}],"city_id":"5009811","city":"Paris","zoom":19},"description":"Au numero 9 de l'impasse Florimont figure la maison de Jeanne dans laquelle vecut Georges Brassens pendant plusieurs années."},{"id":21093174,"language_id":2,"language_iso":"fr","urlhtml":"<a class=\"wikimapia-link\" href=\"http://wikimapia.org/21093174/fr/Hotel-Cluny-Square\">Hotel Cluny Square</a>","title":"Hotel Cluny Square","tags":[{"id":50,"title":"hôtel, hébergement"}],"wikipedia":"","is_building":false,"is_region":false,"is_deleted":false,"parent_id":"0","polygon":[{"x":2.3434152,"y":48.851499},{"x":2.343438,"y":48.8515263},{"x":2.3435707,"y":48.8515043},{"x":2.3435386,"y":48.8514601},{"x":2.3434997,"y":48.8514495},{"x":2.3434393,"y":48.8514592}],"location":{"lon":2.3434929,"lat":48.8514879,"north":48.8515263,"south":48.8514495,"east":2.3435707,"west":2.3434152,"country":"France","state":"Ile-de-France","place":"Paris","country_adm_id":100171,"gadm":[{"id":"74","country":"74","level":"0","is_last_level":"0","name":"France","iso":null,"type":null,"translation":"France"},{"id":"1000","country":"0","level":"0","is_last_level":"0","name":"World","iso":null,"type":null,"translation":"Monde "},{"id":"60533","country":"74","level":"1","is_last_level":"0","name":"Île-de-France","iso":null,"type":null,"translation":null},{"id":"83881","country":"74","level":"2","is_last_level":"0","name":"Paris","iso":null,"type":null,"translation":"Paris"},{"id":"100169","country":"74","level":"3","is_last_level":"0","name":"Paris, 5e arrondissement","iso":null,"type":null,"translation":null},{"id":"100170","country":"74","level":"4","is_last_level":"0","name":"Paris, 5e arrondissement","iso":null,"type":null,"translation":null}],"city_id":"5009811","city":"Paris","zoom":21},"description":"21 Boulevard Saint-Michel\n75005 Paris, France\n+33 1 43 54 21 39"},{"id":28943642,"language_id":2,"language_iso":"fr","urlhtml":"<a class=\"wikimapia-link\" href=\"http://wikimapia.org/28943642/fr/Rue-de-Saisset-72\">Rue de Saisset, 72</a>","title":null,"tags":null,"wikipedia":null,"is_building":true,"is_region":false,"is_deleted":false,"parent_id":"0","polygon":[{"x":2.3127843,"y":48.8151785},{"x":2.312904,"y":48.8151399},{"x":2.312936,"y":48.8151841},{"x":2.312889,"y":48.8151982},{"x":2.3128775,"y":48.8152027},{"x":2.3128893,"y":48.8152203},{"x":2.3128259,"y":48.8152429},{"x":2.3128184,"y":48.8152309}],"location":{"lon":2.3128601,"lat":48.8151914,"north":48.8152429,"south":48.8151399,"east":2.312936,"west":2.3127843,"country":"France","state":"Ile-de-France","place":"Montrouge","country_adm_id":0,"gadm":null,"city_id":"4561719","city":"Montrouge","zoom":20},"description":null},{"id":28943906,"language_id":2,"language_iso":"fr","urlhtml":"<a class=\"wikimapia-link\" href=\"http://wikimapia.org/28943906/fr/%C3%80-c%C3%B4t%C3%A9-du-82\">À côté du 82...</a>","title":"À côté du 82...","tags":[{"id":74,"title":"restaurant, restauration"}],"wikipedia":null,"is_building":true,"is_region":false,"is_deleted":false,"parent_id":"0","polygon":[{"x":2.3178875,"y":48.8159589},{"x":2.317791,"y":48.8159837},{"x":2.3177804,"y":48.8159864},{"x":2.3177403,"y":48.8159237},{"x":2.3178494,"y":48.8158955}],"location":{"lon":2.3178139,"lat":48.8159409,"north":48.8159864,"south":48.8158955,"east":2.3178875,"west":2.3177403,"country":"France","state":"Ile-de-France","place":"Montrouge","country_adm_id":0,"gadm":null,"city_id":"4561719","city":"Montrouge","zoom":20},"description":null},{"id":28948311,"language_id":2,"language_iso":"fr","urlhtml":"<a class=\"wikimapia-link\" href=\"http://wikimapia.org/28948311/fr/Rue-des-Suisses-114\">Rue des Suisses, 114</a>","title":null,"tags":null,"wikipedia":null,"is_building":true,"is_region":false,"is_deleted":false,"parent_id":"0","polygon":[{"x":2.3147476,"y":48.832304},{"x":2.3148298,"y":48.8322428},{"x":2.3149076,"y":48.8322819},{"x":2.314906,"y":48.8322835},{"x":2.3148214,"y":48.8323406},{"x":2.3147966,"y":48.832328},{"x":2.31479,"y":48.8323349},{"x":2.3147798,"y":48.8323285},{"x":2.3147865,"y":48.8323237}],"location":{"lon":2.3148276,"lat":48.8322917,"north":48.8323406,"south":48.8322428,"east":2.3149076,"west":2.3147476,"country":"France","state":"Ile-de-France","place":"Malakoff","country_adm_id":0,"gadm":null,"city_id":"5009811","city":"Paris","zoom":20},"description":null},{"id":28948611,"language_id":2,"language_iso":"fr","urlhtml":"<a class=\"wikimapia-link\" href=\"http://wikimapia.org/28948611/fr/rue-Raymond-Losserand-95\">rue Raymond Losserand, 95</a>","title":null,"tags":null,"wikipedia":null,"is_building":true,"is_region":false,"is_deleted":false,"parent_id":"0","polygon":[{"x":2.30231,"y":48.8308339},{"x":2.3022917,"y":48.8308003},{"x":2.3022707,"y":48.8307653},{"x":2.3023116,"y":48.8307564},{"x":2.3023689,"y":48.8307407},{"x":2.3023896,"y":48.8307602},{"x":2.3023924,"y":48.8307628},{"x":2.302366,"y":48.8307696},{"x":2.3023706,"y":48.8307775},{"x":2.3023813,"y":48.8307751},{"x":2.3023856,"y":48.8307837},{"x":2.3024074,"y":48.8307772},{"x":2.3024319,"y":48.8308007}],"location":{"lon":2.3023513,"lat":48.8307873,"north":48.8308339,"south":48.8307407,"east":2.3024319,"west":2.3022707,"country":"France","state":"Ile-de-France","place":"Malakoff","country_adm_id":0,"gadm":null,"city_id":"5009811","city":"Paris","zoom":20},"description":null},{"id":28948766,"language_id":2,"language_iso":"fr","urlhtml":"<a class=\"wikimapia-link\" href=\"http://wikimapia.org/28948766/fr/unknown\">unknown</a>","title":"unknown","tags":[{"id":17,"title":"magasin"}],"wikipedia":null,"is_building":true,"is_region":false,"is_deleted":false,"parent_id":"0","polygon":[{"x":2.2900716,"y":48.8357549},{"x":2.2900113,"y":48.8358498},{"x":2.2900819,"y":48.8358696},{"x":2.2901425,"y":48.8357776}],"location":{"lon":2.2900769,"lat":48.8358122,"north":48.8358696,"south":48.8357549,"east":2.2901425,"west":2.2900113,"country":"France","state":"Ile-de-France","place":"Malakoff","country_adm_id":0,"gadm":null,"city_id":"5009811","city":"Paris","zoom":20},"description":null},{"id":28951826,"language_id":2,"language_iso":"fr","urlhtml":"<a class=\"wikimapia-link\" href=\"http://wikimapia.org/28951826/fr/boulevard-de-Vaugirard-22\">boulevard de Vaugirard, 22</a>","title":null,"tags":null,"wikipedia":null,"is_building":true,"is_region":false,"is_deleted":false,"parent_id":"0","polygon":[{"x":2.3123921,"y":48.8426233},{"x":2.3122966,"y":48.8425931},{"x":2.3123527,"y":48.8425252},{"x":2.3124452,"y":48.842556},{"x":2.3124141,"y":48.8425935}],"location":{"lon":2.3123709,"lat":48.8425742,"north":48.8426233,"south":48.8425252,"east":2.3124452,"west":2.3122966,"country":"France","state":"Ile-de-France","place":"Malakoff","country_adm_id":0,"gadm":null,"city_id":"5009811","city":"Paris","zoom":20},"description":null},{"id":28952242,"language_id":2,"language_iso":"fr","urlhtml":"<a class=\"wikimapia-link\" href=\"http://wikimapia.org/28952242/fr/Immeuble-Studio-H%C3%B4tel\">Immeuble \"Studio Hôtel\"</a>","title":"Immeuble \"Studio Hôtel\"","tags":[{"id":50,"title":"hôtel, hébergement"},{"id":352,"title":"bar"}],"wikipedia":null,"is_building":true,"is_region":false,"is_deleted":false,"parent_id":"0","polygon":[{"x":2.3286056,"y":48.841684},{"x":2.328634,"y":48.8415953},{"x":2.3286448,"y":48.8415973},{"x":2.3287165,"y":48.8416073},{"x":2.3286977,"y":48.841696}],"location":{"lon":2.328661,"lat":48.8416456,"north":48.841696,"south":48.8415953,"east":2.3287165,"west":2.3286056,"country":"France","state":"Ile-de-France","place":"Paris","country_adm_id":0,"gadm":null,"city_id":"5009811","city":"Paris","zoom":20},"description":null},{"id":28969760,"language_id":0,"language_iso":"en","urlhtml":"<a class=\"wikimapia-link\" href=\"http://wikimapia.org/28969760/Rue-Saint-Andr%C3%A9-des-Arts-34\">Rue Saint-André-des-Arts, 34</a>","title":null,"tags":[{"id":109,"title":"building"}],"wikipedia":null,"is_building":true,"is_region":false,"is_deleted":false,"parent_id":"0","polygon":[{"x":2.3418766,"y":48.8533995},{"x":2.3418754,"y":48.8533936},{"x":2.3419238,"y":48.8533912},{"x":2.3419756,"y":48.8533889},{"x":2.3420044,"y":48.8534721},{"x":2.34192,"y":48.8534774}],"location":{"lon":2.3419399,"lat":48.8534331,"north":48.8534774,"south":48.8533889,"east":2.3420044,"west":2.3418754,"country":"France","state":"Ile-de-France","place":"Paris","country_adm_id":0,"gadm":null,"city_id":"5009811","city":"Paris","zoom":20},"description":null},{"id":28970690,"language_id":2,"language_iso":"fr","urlhtml":"<a class=\"wikimapia-link\" href=\"http://wikimapia.org/28970690/fr/Rue-des-Canettes-12\">Rue des Canettes, 12</a>","title":null,"tags":null,"wikipedia":null,"is_building":true,"is_region":false,"is_deleted":false,"parent_id":"0","polygon":[{"x":2.3336562,"y":48.8522044},{"x":2.3335206,"y":48.8522052},{"x":2.3335204,"y":48.8521806},{"x":2.3334634,"y":48.8521804},{"x":2.3334642,"y":48.8521592},{"x":2.3336617,"y":48.8521555},{"x":2.3336592,"y":48.8521794}],"location":{"lon":2.3335625,"lat":48.8521803,"north":48.8522052,"south":48.8521555,"east":2.3336617,"west":2.3334634,"country":"France","state":"Ile-de-France","place":"Paris","country_adm_id":0,"gadm":null,"city_id":"5009811","city":"Paris","zoom":21},"description":null},{"id":28971132,"language_id":2,"language_iso":"fr","urlhtml":"<a class=\"wikimapia-link\" href=\"http://wikimapia.org/28971132/fr/Rue-de-Buci-36\">Rue de Buci, 36</a>","title":null,"tags":null,"wikipedia":null,"is_building":true,"is_region":false,"is_deleted":false,"parent_id":"0","polygon":[{"x":2.3358519,"y":48.8534869},{"x":2.3358818,"y":48.8534695},{"x":2.3359765,"y":48.8534119},{"x":2.3359967,"y":48.8534255},{"x":2.336025,"y":48.8534454},{"x":2.3359411,"y":48.8534883},{"x":2.3359501,"y":48.8534956},{"x":2.3359231,"y":48.8535264},{"x":2.3359235,"y":48.8535273},{"x":2.3359159,"y":48.8535303}],"location":{"lon":2.3359384,"lat":48.8534711,"north":48.8535303,"south":48.8534119,"east":2.336025,"west":2.3358519,"country":"France","state":"Ile-de-France","place":"Paris","country_adm_id":0,"gadm":null,"city_id":"5009811","city":"Paris","zoom":20},"description":null}]